Workbook
Name carrier_BioWet: Carrier!$A$3

Sheet README
A1: README
A3: Contact
A4: Baron Chen | B4: yi-chung.chen@empa.ch
A5: Robin Mutschler | B5: robin.mutschler@empa.ch
A7: Relevant datasets | B7: Description | C7: Link
A8: IEA | B8: ETP Clean Energy Technology Guide is an interactive framework that contains information for nearly 600 individual technology designs and components across the whole energy system | C8: ETP Clean Energy Technology Guide – Data Tools - IEA
A9: Danish Energy Agency | B9: Extensive and high quality technology descriptions | C9: https://ens.dk/en/analyses-and-statistics
A10: European Commission | B10: JRC-EU-TIMES Full model dataset | C10: https://data.jrc.ec.europa.eu/dataset/8141a398-41a8-42fa-81a4-5b825a51761b
A11: SWEET | B11: energy tech data | C11: https://sweet-cross.ch/data/energy-tech-parameters/2024-02-27/
A12: Preliminary work | B12: Preliminary classification & parameterization work by Robin & Cristina | C12: https://docs.google.com/presentation/d/1oeQVAHrxMZgUv_lBlpRWjX9dcrnxatpXH_WOpPOPivE/edit?usp=sharing
A13: Technology representation | B13: Preliminary work to define the boundary condition of a technology | C13: https://docs.google.com/presentation/d/1Js4_w0kzhL3zGCj_5YsGCvKfnxXCUHVAVOwmXP_sHO0/edit#slide=id.g24c4e5253f6_0_5
A14: Energieperspektiven BFE | B14: xkurs Negativemissionstechnologien und CCS | C14: https://www.bfe.admin.ch/bfe/fr/home/politik/energieperspektiven-2050-plus.exturl.html/aHR0cHM6Ly9wdWJkYi5iZmUuYWRtaW4uY2gvZGUvcHVibGljYX/Rpb24vZG93bmxvYWQvMTA2MjA=.html
A15: Energieperspektiven BFE | B15: Energieperspektiven alle Reports | C15: https://www.bfe.admin.ch/bfe/de/home/politik/energieperspektiven-2050-plus.html
A16: Energiestatistik BFE | B16: Energiestatistik BFE | C16: https://www.bfe.admin.ch/bfe/de/home/versorgung/statistik-und-geodaten/energiestatistiken/gesamtenergiestatistik.html
A17: VSE Studies | B17: Important reference for the Empa Swiss model | C17: https://www.strom.ch/de/energiezukunft-2050/download
A18: about database | B18: this Excel file is the collaborative document to contribute the data for reFuel.ch
B19: the cleaned data will be store in another format (e.g. csv, JSON)
A20: Energy-X path representation | B20: Empa's preliminary path representation | C20: https://miro.com/app/board/uXjVOAn1i64=/
A21: Previous VSE technology data collection | B21: The Google Sheet with previous VSE data | C21: https://docs.google.com/spreadsheets/d/1eQCuOR8Kq5_W_c7xZtdGj87lEK-D1_rSEdts_J6jZLs/edit?gid=369202019#gid=369202019
A23: FAIR principle:
A24: Findable
A25: Accessible
A26: Interoperable | B26: are the assumptions and definitions clear?
A27: Reusable | B27: Can the data be exported in other formats?
A28: NOTE | B28: seperate "data" and "information"
A30: Other guidelines
A31: Clear define each parameter and terminology and reference it
A32: Provide key info about the data (e.g. assumption, reference, boundary conditions…)
A33: Clean and structured data that can be read by the machine
A35: Adding reference
A36: if the reference do not have a DOI, you can upload a BibTex file, using following steps: 1. add reference in a reference management tool (e.g. Zetero) 2. select "Export item" with format "BibTex" 3. change the file name the same as reference ID in the Reference sheet. 4. upload the file to reFuel.ch WP3 teams folder (see link on the right) | B36: folder for BibTex files
A38: NOTE: | B38: download a copy of reference from report, in case it is not available later
A43: TODO [2026-01-23] | B43: align Ch4 and CH4
B44: clean the second column name in row 4 in ConvTech, remove 'unit'
B45: check the one_time_opex for in ConvTech
B46: do we really need 'main input', if the main input is always with ratio 1?

Sheet Metadata
A1: Sheet Name | B1: Column header | C1: Mapping header | D1: Unit / Format | E1: Description | F1: ehubX name | G1: Ontology IRI | H1: Note
A2: ConvTech | B2: ehubX Tech ID | C2: {=TRANSPOSE(OFFSET(ConvTech!F4,0,0,1,56))} -> ehubX Tech ID | D2: {=TRANSPOSE(OFFSET(ConvTech!F2,0,0,1,44))} -> [ehubX Tech ID] | E2: ehubX technology ID | F2: tech_id
C3: tech_id | D3: [Datapaper Tech ID] | E3: Internationalized Resource Identifier (IRI) of an ontology
A4: ConvTech | B4: Tech Ontology IRI | C4: Tech Ontology IRI | D4: [Ontology IRI] | E4: High level process type? TBD | H4: provide additional information about the process (e.g. SOFC, Alkaline, PEM…)
A5: ConvTech | B5: Process Type | C5: process_type | D5: [ProcessType] | E5: Description of the technology
A6: ConvTech | B6: Description | C6: description | D6: [str]
A7: ConvTech | B7: Main Sector | C7: unit_operation | D7: [str] | E7: The main sector (based on what?) of the technology, see "Predefined" sheet | H7: not clera what serctor/category/group refer to
A8: ConvTech | B8: Main Category | C8: main_sector | D8: [MainSector] | E8: The main category (based on what?) of the technology, see "Predefined" sheet
A9: ConvTech | B9: Category Specification | C9: main_category | D9: [MainCategory] | E9: Subcategory of the technology, based on technology details
A10: ConvTech | B10: Tech Type | C10: category_spec | D10: [CategorySpec] | E10: High-level technology type (based on what?) | H10: different then ehubX type
A11: ConvTech | B11: Reference Unit Size | C11: tech_type | D11: [TechType] | E11: The tech-econo data is based on this reference capacity (e.g.10 MW) | H11: one unit size, another for the unit of capacity (kW or kg/yr)?
A12: ConvTech | B12: Technology Year | C12: reference_unit_size | D12: [MWh/h] or [t/h] | E12: The year that the technology is available and the tech-econo data are based on
A13: ConvTech | B13: Cost Base | C13: cost_base_year | D13: [Year] | E13: The location/region that the cost parameters are based on (e.g. CH or Europe) | H13: specific for location?
A14: ConvTech | B14: Currency | C14: Cost Base | D14: [Location] | E14: The currency of the cost parameter | H14: move to economic?
A15: ConvTech | B15: Data Reference Year | C15: Currency | D15: [Currency] | E15: The year that the technology data are evaluated on (e.g. a technology is evaluted in 2020) | H15: change to 'Data Reference Year' to reflect that only cost but other data are evaluated
A16: ConvTech | B16: Technology Readiness Level | C16: Data Reference Year | D16: [Year] | E16: The technology readiness level, scale 1 to 9
A17: ConvTech | B17: Technology Maturity Evaluation | C17: trl_(1-9) | D17: [TRL 1-9] | E17: How maturity is a technology, see "Predefined" sheet | F17: trl
A18: ConvTech | B18: Technology Boundary | C18: tech_maturity | D18: [TechMaturity] | E18: The boundary of the technololgy (e.g. core componen, full system ready for operation?), TBD | H18: need to be defined?
A19: ConvTech | B19: Tech Drawing Added? | C19: tech_boundary | D19: [TechBoundary]
A20: ConvTech | B20: Overall Efficiency | C20: Tech Drawing Added? | D20: [boolean] | E20: The overall efficiency based on the specific inputs and outputs
A21: ConvTech | B21: Input, Output for Overall Efficiency | C21: overall_efficiency | D21: [0-1] | E21: The inputs and outputs for overall efficiency calculation
A22: ConvTech | B22: Input Carriers | C22: Input, Output for Overall Efficiency | D22: [Input Carrier, Output Carrier] | E22: The list of input carriers of the technology/process | F22: in_ecs
A23: ConvTech | B23: Main Input Carrier | C23: carriers_in | D23: [list of Carriers] | E23: In case multiple inputs are present, the main input has to be defined. The output efficiency is relative to the main input
A24: ConvTech | B24: Input Shares | C24: main_input | D24: [Carrier] | E24: The share of input energy/mass for each carrier | F24: in_ecs
A25: ConvTech | B25: Input Units | C25: Input Shares | D25: [list of floats, comma separated] | E25: The unit of the input shares
A26: ConvTech | B26: Output Carriers | C26: Input Units - Shares | D26: [list of units in kWh and kg] | E26: The list of output carriers of the technology/process | F26: out_ecs
A27: ConvTech | B27: Main Output Carrier | C27: ratios_in | D27: [list of float, comma separated] | E27: Relevant to dimension the plant / tech | F27: main_out_ec
A28: ConvTech | B28: Output Shares | C28: units_in | D28: [list of units, comma separated] | E28: The share of output energy/mass for each carrier | F28: out_ecs
A29: ConvTech | B29: Output Units | C29: carriers_out | D29: [list of Carriers] | E29: The unit of the output shares
A30: ConvTech | B30: Minimum Installation | C30: SwissX_carriers_out | D30: [list of Carriers] | E30: The minimumal installation capacity | F30: unit_cap_min
A31: ConvTech | B31: Economic Lifetime | C31: main_out | D31: [Carrier] | E31: The system lifetime for tech-econo assessment | F31: lifetime
A32: ConvTech | B32: CAPEX One Time | C32: ratios_out | D32: [list of float, comma separated] | E32: The fixed Capex independent from the capacity (e.g. project planning, adminstration...) | F32: one_time_capex
A33: ConvTech | B33: CAPEX Power Capacity | C33: SwissX_ratios_out | D33: [list of float, comma separated] | E33: The Capex depends on the capacity | F33: capex_per_cap
A34: ConvTech | B34: OPEX One Time | C34: units_out | D34: [list of units, comma separated] | E34: The fixed Opex independent from the capacity (e.g. license, management) | F34: one_time_opex | H34: is it one-time (CHF) or fixed (CHF/yr)?
A35: ConvTech | B35: OPEX Power Capacity as percentage of CAPEX | C35: Output Shares | D35: [list of float, comma separated] | E35: The percentage to estimate Opex based on the CAPEX (e.g. Opex CHF/yr is 4% of Capex)
A36: ConvTech | B36: OPEX Power Capacity | C36: Output Units - Shares | D36: [list of units, comma separated] | E36: The Opex based on the power capacity of the system | F36: opex_per_cap
A37: ConvTech | B37: OPEX Energy | C37: theoretical_efficiency | D37: [0-1] | E37: The Opex based on the annual energy production of the system | F37: opex_per_energy
A38: ConvTech | B38: Discount Rate | C38: operating_temperature_c | D38: °C | E38: The discoiunt rate to estimate the levelised costs of the technology | F38: interest_rate
A39: ConvTech | B39: Value Range Check | C39: min_installation_size | D39: kW, kg/hr | E39: If the technology has a value range
A40: ConvTech | B40: Uncertainty Rating | C40: lifetime_yr | D40: Years | E40: The rating of uncertainty level for tech-econo parameters
A41: ConvTech | B41: LCA ID | C41: capex_one_time_eur | D41: Currency | E41: The ID of LCA (from PSI Premise model)
A42: ConvTech | B42: LCA unit | C42: capex_power_capacity_eur_per_kw | D42: Currency/OutputUnit/Hour | E42: The LCA unit (e.g. kW, t/h) of the value of embedded carbon | F42: co2_per_cap | G42: http://openenergy-platform.org/ontology/oeo/OEO_00000148 | H42: need to check unit when put in the ehubX
A43: ConvTech | B43: Embedded Carbon | C43: opex_one_time_eur | D43: Currency | E43: The value of embedded carbon (from PSI Premise model)
A44: ConvTech | B44: LCA Scenario | C44: opex_fix_pct_of_capex | D44: % | E44: The LCA scenario (from PSI Premise model)
A45: ConvTech | B45: References | C45: opex_fix_power_capacity_eur_per_kw_yr | D45: Currency/OutputUnit/Year. Excl. fuels! | E45: The information of reference of the data
A46: ConvTech | B46: Review Comment | C46: opex_energy_eur_per_unit
A47: ConvTech | B47: Note | C47: discount_rate_pct
A48: ConvTech | B48: Status (VSE 2025) | C48: Value Range Check
C49: uncertainty_rating
C50: lca_id
C51: lca_unit
C52: embedded_carbon_kgco2e_per_lca_unit
C53: lca_scenario
C54: Mass Inflows
C55: Mass Outflows
C56: energy_balance_error_pct
C57: mass_balance_error_pct
B60: Not in ConvTech | C60: Not in StorTech Sheet | D60: Both
A62: StorTech | B62: ehubX tech ID | C62: {=TRANSPOSE(StorTech!E3:AS3)} -> ehubX Tech ID | D62: {=TRANSPOSE(StorTech!E2:AS2)} -> [ehubX Tech ID]
A63: StorTech | B63: Tech Ontology IRI | C63: Tech Ontology IRI | D63: [Ontology IRI]
A64: StorTech | B64: Process Type | C64: Process Type | D64: [ProcessType]
A65: StorTech | B65: Description | C65: Description | D65: [str]
A66: StorTech | B66: Main Sector | C66: Main Sector | D66: [MainSector]
A67: StorTech | B67: Main Category | C67: Main Category | D67: [MainCategory]
A68: StorTech | B68: Category Specification | C68: Category Specification | D68: [CategorySpec]
A69: StorTech | B69: Tech Type | C69: Tech Type | D69: [TechType]
A70: StorTech | B70: Reference Unit Size | C70: Reference Unit Size | D70: kW
A71: StorTech | B71: Technology Year | C71: Technology Year | D71: [Year]
A72: StorTech | B72: Cost Base | C72: Cost Base | D72: [Location]
A73: StorTech | B73: Currency | C73: Currency | D73: [Currency]
A74: StorTech | B74: Data Reference Year | C74: Data Reference Year | D74: [Year]
... A78: StorTech | B78: Overall Efficiency | C78: Overall Efficiency | D78: [0-1]
A79: StorTech | B79: Input, Output for Overall Efficiency | C79: Input, Output for Overall Efficiency | D79: [Input Carrier, Output Carrier] | F79: sto_ec
A80: StorTech | B80: Input Carriers | C80: Input Carriers | D80: [list of Carriers] | F80: unit_cap_min
A81: StorTech | B81: Storage Carrier | C81: Storage Carrier | D81: [Carrier] | F81: charge_max
A82: StorTech | B82: Minimum Installation | C82: Minimum Installation | D82: kWh | F82: discharge_max
A83: StorTech | B83: Charging Capacity Factor | C83: Charging Capacity Factor | D83: [float] | F83: in_eff
A84: StorTech | B84: Discharging Capacity Factor | C84: Discharging Capacity Factor | D84: [float] | F84: out_eff
A85: StorTech | B85: Charging Efficiency | C85: Charging Efficiency | D85: [float] | F85: soc_min
A86: StorTech | B86: Discharging Efficiency | C86: Discharging Efficiency | D86: [float] | F86: soc_max
A87: StorTech | B87: Minimum SOC | C87: Minimum SOC | D87: [float] | F87: standby_loss
A88: StorTech | B88: Maximum SOC | C88: Maximum SOC | D88: [float] | F88: lifetime
A89: StorTech | B89: Standby Loss | C89: Standby Loss | D89: Loss/hour | F89: interest_rate
A90: StorTech | B90: Economic Lifetime | C90: Economic Lifetime | D90: Years | F90: one_time_capex
... A93: StorTech | B93: OPEX One Time | C93: OPEX One Time | D93: Currency/year | F93: opex_per_cap
A94: StorTech | B94: OPEX Storage Capacity | C94: OPEX Storage Capacity | D94: Currency/kWh.year
A95: StorTech | B95: Discount Rate | C95: Discount Rate | D95: [float]
B96: Value Range Check | C96: Value Range Check | D96: [boolean]
B97: Uncertainty Rating | C97: Uncertainty Rating | D97: [UncertaintyLevel]
A98: StorTech | B98: LCA ID | C98: LCA ID | D98: [LCA ID] | F98: co2_per_cap
A99: StorTech | B99: LCA Unit | C99: LCA Unit | D99: [LCA Unit]
A100: StorTech | B100: Embedded Carbon | C100: Embedded Carbon | D100: [kgCO2-eq/LCA unit]
A101: StorTech | B101: LCA Scenario | C101: LCA Scenario | D101: [LCA Scenario]
A102: StorTech | B102: References | C102: References | D102: [dict of ReferenceID]
A104: SolarTech | B104: ehubX Tech ID | C104: {=TRANSPOSE(SolarTech!E3:AU3)} -> ehubX Tech ID | D104: {=TRANSPOSE(SolarTech!E2:AU2)} -> [ehubX Tech ID] | F104: tech_id
A105: SolarTech | B105: Tech Ontology IRI | C105: Tech Ontology IRI | D105: [Ontology IRI]
A106: SolarTech | B106: Description | C106: Process Type | D106: [ProcessType]
A107: SolarTech | B107: Process | C107: Description | D107: [Description]
A108: SolarTech | B108: Main Sector | C108: Main Sector | D108: [MainSector]
A109: SolarTech | B109: Main Category | C109: Main Category | D109: [MainCategory]
...

Sheet Predefined
A1: Sheet name | B1: Column header | C1: Values | D1: Description | E1: Ontology IRI | F1: Note
A2: ConvTech | B2: process_type | C2: Carbon Black Production
A3: ConvTech | B3: process_type | C3: CO2 capture
A4: ConvTech | B4: process_type | C4: CO2 transport
A5: ConvTech | B5: process_type | C5: Digestion
A6: ConvTech | B6: process_type | C6: Electricity production / Hydrogen use
A7: ConvTech | B7: process_type | C7: Electrochemical CO2 reduction
A8: ConvTech | B8: process_type | C8: Electrolysis
A9: ConvTech | B9: process_type | C9: Eletricity Transmission
A10: ConvTech | B10: process_type | C10: Fischer Tropsch
A11: ConvTech | B11: process_type | C11: Gas Boiler
A12: ConvTech | B12: process_type | C12: Gas Turbine
A13: ConvTech | B13: process_type | C13: Haberbosch
... A96: ConvTech | B96: lca_scenario | C96: SSP2-PkBudg1150_2050
A97: ConvTech | B97: tech_maturity | C97: Mature | F97: see Sheet "TechMaturity"
A98: ConvTech | B98: tech_maturity | C98: Emerging | F98: see Sheet "TechMaturity"
A99: ConvTech | B99: tech_maturity | C99: Prototype | F99: see Sheet "TechMaturity"
A100: ConvTech
A101: ConvTech
A102: ConvTech
A103: ConvTech
A104: ConvTech
A105: ConvTech
A106: ConvTech
A107: ConvTech
A108: ConvTech
A109: ConvTech
A110: ConvTech
A111: ConvTech
... A113: ConvTech

Sheet Unique values
A1: Sheet name | B1: ConvTech | C1: ConvTech | D1: ConvTech | E1: ConvTech | F1: ConvTech | G1: ConvTech | H1: ConvTech | I1: ConvTech | J1: ConvTech | K1: ConvTech
A2: Column header | B2: =ConvTech!I4 -> process_type | C2: =ConvTech!L4 -> main_sector | D2: =ConvTech!M4 -> main_category | E2: =ConvTech!N4 -> category_spec | F2: =ConvTech!O4 -> tech_type | G2: =ConvTech!R4 -> Cost Base | H2: =ConvTech!S4 -> Currency | I2: =ConvTech!V4 -> tech_maturity | J2: =ConvTech!W4 -> tech_boundary | K2: =ConvTech!BE4 -> lca_scenario
A3: Unique value count | B3: =COUNTA(B5:B1000) -> 28 | C3: =COUNTA(C5:C1000) -> 17 | D3: =COUNTA(D5:D1000) -> 22 | E3: =COUNTA(E5:E1000) -> 19 | F3: =COUNTA(F5:F1000) -> 2 | G3: =COUNTA(G5:G1000) -> 2 | H3: =COUNTA(H5:H1000) -> 2 | I3: =COUNTA(I5:I1000) -> 3 | ... K3: =COUNTA(K5:K1000) -> 5
A5: Unique values | B5: {=_xlfn.UNIQUE(_xlfn._xlws.FILTER(ConvTech!I5:I1066, (ConvTech!I5:I1066<>"")*(ConvTech!I5:I1066<>0)*(ConvTech!I5:I1066<>"na")))} -> CO2 capture | C5: {=_xlfn.UNIQUE(_xlfn._xlws.FILTER(ConvTech!L5:L1066, (ConvTech!L5:L1066<>"")*(ConvTech!L5:L1066<>0)*(ConvTech!L5:L1066<>"na")))} -> CO2 capture | D5: {=_xlfn.UNIQUE(_xlfn._xlws.FILTER(ConvTech!M5:M1066, (ConvTech!M5:M1066<>"")*(ConvTech!M5:M1066<>0)*(ConvTech!M5:M1066<>"na")))} -> Point source capture | E5: {=_xlfn.UNIQUE(_xlfn._xlws.FILTER(ConvTech!N5:N1066, (ConvTech!N5:N1066<>"")*(ConvTech!N5:N1066<>0)*(ConvTech!N5:N1066<>"na")))} -> Amine washing | F5: {=_xlfn.UNIQUE(_xlfn._xlws.FILTER(ConvTech!O5:O1066, (ConvTech!O5:O1066<>"")*(ConvTech!O5:O1066<>0)*(ConvTech!O5:O1066<>"na")))} -> Conversion | G5: {=_xlfn.UNIQUE(_xlfn._xlws.FILTER(ConvTech!R5:R1066, (ConvTech!R5:R1066<>"")*(ConvTech!R5:R1066<>0)*(ConvTech!R5:R1066<>"na")))} -> CH | H5: {=_xlfn.UNIQUE(_xlfn._xlws.FILTER(ConvTech!S5:S1066, (ConvTech!S5:S1066<>"")*(ConvTech!S5:S1066<>0)*(ConvTech!S5:S1066<>"na")))} -> CHF | I5: {=_xlfn.UNIQUE(_xlfn._xlws.FILTER(ConvTech!V5:V1066, (ConvTech!V5:V1066<>"")*(ConvTech!V5:V1066<>0)*(ConvTech!V5:V1066<>"na")))} -> Mature | J5: {=_xlfn.UNIQUE(_xlfn._xlws.FILTER(ConvTech!W5:W1066, (ConvTech!W5:W1066<>"")*(ConvTech!W5:W1066<>0)*(ConvTech!W5:W1066<>"na")))} -> Plant ready to operate | K5: {=_xlfn.UNIQUE(_xlfn._xlws.FILTER(ConvTech!BE5:BE1066, (ConvTech!BE5:BE1066<>"")*(ConvTech!BE5:BE1066<>0)*(ConvTech!BE5:BE1066<>"na")))} -> SSP2-PkBudg1000_2030
B6: Haberbosch | C6: Ammonia | D6: Pyrolysis | E6: Wet Biomass | F6: Transport | G6: CHF | H6: EUR | I6: Emerging | J6: Complete installation | K6: SSP2-PkBudg1000_2040
B7: Carbon black production | C7: Carbon Black | D7: DAC | E7: Adsorption | I7: Prototype | J7: FALSE | K7: SSP2-PkBudg1000_2050
B8: Gas Turbine | C8: Carbon Capture | D8: Digestion | E8: HPC cycling | K8: SSP2-PkBudg1000_2025
B9: Heat and Electricity generation | C9: Methane | D9: Fuelcell | E9: Waste
B10: Digestion | C10: Electricity / Hydrogen | D10: Grid / Hydrogen | E10: Methane
B11: Electricity production / Hydrogen use | C11: Thermal | D11: Building | E11: CO2 hydrogenation
B12: Gas Boiler | C12: CO2 transport | D12: Hydrogenation | E12: Transmission
B13: Heat generation | C13: Carbon Monoxide | D13: Pipeline | E13: Distribution
B14: Methane synthesis | C14: Electricity | D14: NonPipeline | E14: Thermal
B15: CO2 transport | C15: Methanol | D15: Electrochemical | E15: RWGS
B16: Electrochemical CO2 reduction | C16: Hydrogen / Electricity | D16: Grid | E16: Kerosine
B17: Eletricity Transmission | C17: Synfuels | D17: Process | E17: Gasoline
B18: Thermal Powerplant | C18: Hydro | D18: Hydrogen | E18: Mustrun Turbine
B19: Methanol production | C19: Syngas | D19: Thermochemical | E19: Oil
B20: Reverse water gas shift | C20: Hydrogen | D20: Electrolysis | E20: PV
B21: Hydrogen production / Electricity use | C21: Cement | D21: Hydrocarbons | E21: CO hydrogenation
B22: Fischer Tropsch | D22: Hydro | E22: Wind
B23: Thermochemical CO Hydrogenation | D23: Waste | E23: Wood
B24: Water turbine | D24: New Renewable
B25: Hydro | D25: Nuclear
B26: Solar | D26: Gasification
B27: Heat transfer
B28: Syngas production
B29: Hydrogen production
B30: Wind turbine
B31: SAF production (HEFA)
B32: Cement

Sheet Glossary
A1: Name | B1: Description
A2: LHV | B2: Low Heating Value
A3: HHV | B3: High Heating Value

Sheet Carrier
A1: Carrier Abbreviation | B1: Carrier description | C1: Carrier Type | D1: Carrier Category | E1: Base Carrier | F1: Color Code (HEX) | G1: Note | H1: Reference
A2: Biomass | B2: Woody & dry biomass | C2: Energy | D2: Bioenergy | E2: Biomass | G2: ehubX carrier
A3: BioWet | B3: Wet biomass | C3: Energy | D3: Bioenergy | E3: BioWet | G3: ehubX carrier
A4: Wood | B4: Energy Wood | C4: Energy | D4: Bioenergy | E4: Wood | G4: ehubX carrier
A5: WoodCh | B5: Energy Wood from Switzerland | C5: Energy | D5: Bioenergy | E5: Wood | G5: ehubX carrier
A6: WoodEu | B6: Energy Wood from Europe | C6: Energy | D6: Bioenergy | E6: Wood | G6: ehubX carrier
A7: El13 | B7: Electricity grid level 1 to 3 (Swissgrid definition of grid levels 380kV - 220kV) | C7: Energy | D7: Electricity | E7: El | G7: ehubX carrier | H7: https://www.swissgrid.ch/en/home/operation/power-grid/grid-levels.html
A8: ElDsr | B8: Electricity associated with Demand Side Response | C8: Energy | D8: Electricity | E8: El | G8: ehubX carrier
A9: El47 | B9: Electricity grid level 4 to 7 (Swissgrid definition of grid levels 1kV - 36kV) | C9: Energy | D9: Electricity | E9: El | G9: ehubX carrier | H9: https://www.swissgrid.ch/en/home/operation/power-grid/grid-levels.html
A10: ElBdg | B10: Behind the meter electricity in buildings | C10: Energy | D10: Electricity | E10: El | G10: ehubX carrier
A11: ElPvAlpin | B11: Electricity from alpine PV | C11: Energy | D11: Electricity | E11: El | G11: ehubX carrier
A12: ElRest | B12: Behind the meter electricity at non-residential buildings and sites | C12: Energy | D12: Electricity | E12: El | G12: ehubX carrier
A13: ElWind | B13: Electricity generated from wind turbines | C13: Energy | D13: Electricity | E13: El | G13: ehubX carrier
A14: ElExp | B14: Exported electricity (Grid level 1 to 3) | C14: Energy | D14: Electricity | E14: El | G14: ehubX carrier
A15: Ch4 | B15: Methane | C15: Energy | D15: Chemical fuel | E15: Ch4 | G15: ehubX carrier
A16: Ch4BioCh | B16: Biogas (Methane) sourced in CH | C16: Energy | D16: Chemical fuel | E16: Ch4 | G16: ehubX carrier
A17: Ch4SynEu | B17: Biogas (Methane) imported from the EU | C17: Energy | D17: Chemical fuel | E17: Ch4 | G17: ehubX carrier
A18: C8 | B18: Hydrocarbon fuels with 8 carbon atoms (representing gasoline) | C18: Energy | D18: Chemical fuel | E18: C8 | G18: ehubX carrier
A19: C12 | B19: Hydrocarbon fuel with 12 carbon atoms (representing diesel) | C19: Energy | D19: Chemical fuel | E19: C12 | G19: ehubX carrier
A20: C12Syn | B20: Hydrocarbon fuel with 12 carbon atoms (representing diesel). Synthesized. | C20: Energy | D20: Chemical fuel | E20: C12 | G20: ehubX carrier
A21: C12Av | B21: Hydrocarbon fuel with 12 carbon atoms (representing aviation fuels). | C21: Energy | D21: Chemical fuel | E21: C12 | G21: ehubX carrier
A22: CBio | B22: Biochar (Carbon from biomass) | C22: Material | E22: C | G22: ehubX carrier
A23: CO2 | B23: Carbon Dioxide | C23: Material | E23: CO2 | G23: ehubX carrier
A24: CO2Sys | B24: Carbon Dioxide as a ressource in the energy system | C24: Material | E24: CO2 | G24: ehubX carrier
A25: CO2Waste | B25: Carbon dioxide in the exhaust of waste incineration plants | C25: Material | E25: CO2 | G25: ehubX carrier
A26: CO2Wood | B26: Carbon dioxide in the exhaust of wood fired powerplants | C26: Material | E26: CO2 | G26: ehubX carrier
A27: CO2Exp | B27: Physically exported Carbon Dioxide | C27: Material | E27: CO2 | G27: ehubX carrier
A28: CO2Fluegas | B28: Carbon Dioxide from flue gas | C28: Material | E28: CO2
A29: O2 | B29: Oxygen | C29: Material | E29: O2 | G29: ehubX carrier
A30: H2 | B30: Hydrogen | C30: Energy | D30: Chemical fuel | E30: H2 | G30: ehubX carrier
A31: H2BlueEu | B31: Blue hydrogen (produced with carbon capture) imported from the EU | C31: Energy | D31: Chemical fuel | E31: H2 | G31: ehubX carrier
A32: H2GreenEu | B32: Green hydrogen (produced from renewables) imported from the EU | C32: Energy | D32: Chemical fuel | E32: H2 | G32: ehubX carrier
A33: H2Process | B33: Process Hydrogen (mixed with CO in syngas) | C33: Energy | D33: Chemical fuel | E33: H2 | G33: ehubX carrier
A34: HydroPumped | B34: Pumped Hydro | C34: Energy | E34: Hydro | G34: ehubX carrier
A35: HydroRor | B35: Run-of-River Hydro | C35: Energy | E35: Hydro | G35: ehubX carrier
A36: HydroS | B36: Hydro Storage | C36: Energy | E36: Hydro | G36: ehubX carrier
A37: HydroSMustrun | B37: Hydro Storage, Must-run fraction | C37: Energy | E37: Hydro | G37: ehubX carrier
A38: MeOH | B38: Methano | C38: Energy | E38: MeOH | G38: ehubX carrier
A39: Msw | B39: Municipal Solid Waste | C39: Energy | E39: Msw | G39: ehubX carrier
A40: MswPh | B40: Solid Waste Utilized for Process Heat | C40: Energy | E40: Msw | G40: ehubX carrier
A41: CO | B41: Carbon Monoxide | C41: Material | E41: CO | G41: ehubX carrier
A42: COSys | B42: Carbon Monooxide as a ressource in the energy system | C42: Material | E42: CO
A43: ThBdg | B43: Thermal energy in buildings (space heating and domestic hot water) | C43: Energy | E43: Th | G43: ehubX carrier
A44: ThAmb | B44: Ambient heat (0-20°C) | C44: Energy | E44: Th | G44: ehubX carrier
A45: ThDh | B45: District heating (to be refined) | C45: Energy | E45: Th | G45: ehubX carrier
A46: ThDhw | B46: Domestic hot water (ThHt, 60-120°C) | C46: Energy | E46: Th | G46: ehubX carrier
A47: ThGround | B47: Geothermal heat (ThAmb, 0-20°C) | C47: Energy | E47: Th | G47: ehubX carrier
A48: ThHt | B48: High-temperature heat (60-120°C) | C48: Energy | E48: Th | G48: ehubX carrier
A49: ThLt | B49: Low-temperature heat (20-60°C) | C49: Energy | E49: Th | G49: ehubX carrier
A50: ThPhI | B50: Process Heat, Steam (120-200°C) | C50: Energy | E50: Th | G50: ehubX carrier
A51: ThPhII | B51: Process Heat (above 200°C) | C51: Energy | E51: Th | G51: ehubX carrier
A52: ThSc | B52: Space cooling (ThAmb, 0-20°C) | C52: Energy | E52: Th | G52: ehubX carrier
A53: ThSh | B53: Space heating for buildings (ThHt, 60-120°C) | C53: Energy | E53: Th | G53: ehubX carrier
A54: U235 | B54: Nuclear fuel | C54: Energy | E54: U235 | G54: ehubX carrier
A55: ThPh | B55: to de define! | C55: Energy | E55: Th
A56: Csw | B56: to de define! | C56: Energy | E56: Csw
A57: N2 | B57: Nitrogen | C57: Material | E57: N2
A58: NaturalGas | B58: Natural gas | C58: Energy | D58: Chemical fuel | E58: NaturalGas
A59: NH3 | B59: Amonia | C59: Energy | D59: Chemical fuel | E59: NH3

Sheet Location
A1: Location Abbreviation | B1: Location Description | C1: Reference
A2: CH | B2: Switzerland
A3: ECA | B3: Europe and Central Asia | C3: https://ourworldindata.org/grapher/world-regions-according-to-the-world-bank
A4: NAC | B4: North America | C4: https://ourworldindata.org/grapher/world-regions-according-to-the-world-bank
A5: SAR | B5: South Asia | C5: https://ourworldindata.org/grapher/world-regions-according-to-the-world-bank
A6: MENA | B6: Middle East and North Africa | C6: https://ourworldindata.org/grapher/world-regions-according-to-the-world-bank
A7: SSA | B7: Sub-Saharan Africa | C7: https://ourworldindata.org/grapher/world-regions-according-to-the-world-bank
A8: EAP | B8: East Asia and Pacific | C8: https://ourworldindata.org/grapher/world-regions-according-to-the-world-bank

Sheet Currency
A1: Currency Name | B1: Currency Description | C1: Symbol | D1: Reference | E1: Assumption | F1: Note
A2: CHF | B2: Swiss franc | C2: Fr.
A3: USE | B3: United States dollar | C3: $
A4: EUR | B4: Euro | C4: €

Sheet Process
A1: Process ID | B1: Process Description | C1: Tech Type | D1: Process Category | E1: Primay Feedstock | F1: Feedstocks | G1: Products | H1: Reference | I1: Assumption
A2: electrolysis_water | B2: Electrolysis, water | C2: Conversion | D2: Electrolysis | E2: Hydrogen | F2: H2O, Electricity | G2: H2
A3: biomass_gasification_to_syngas | B3: Biomass gasification to syngas | C3: Conversion | D3: Gasification | E3: Syngas | F3: Wood, O2 | G3: H2
A4: msw_gasification_to_syngas | B4: Municipal solid waste gasification to syngas | C4: Conversion | D4: Gasification | E4: Syngas | F4: MSW | G4: H2
A5: wet_biomass_anaerobic_digestion_gas_separation | B5: Wet biomass anaerobic digestion with gas separation | C5: Conversion | D5: Digestion | E5: Methane | F5: BioWet | G5: CH4, CO2
A6: methane_synthesis_h2_co2_sabatier | B6: Methane synthesis from H2 and CO2 via the thermo catalytic Sabatier reaction | C6: Conversion | D6: Hydrogenation | E6: Methane | F6: H2, CO2 | G6: CH4, H2O, heat
A7: methane_synthesis_syngas_sabatier | B7: Methane synthesis from Syngas via the thermo catalytic Sabatier reaction | C7: Conversion | D7: Hydrogenation | E7: Methane | F7: H2, CO | G7: CH4, H2O, heat
A8: reverse_water_gas_shift_reaction | B8: Reverse water gas shift reaction plant | C8: Conversion | D8: Reverse Water Gas Shift Reaction | E8: CarbonMonoxide | F8: H2, CO2, heat | G8: CO
A9: methane_synthesis_biomass | B9: Biological methaniation | C9: Conversion | D9: Hydrogenation | E9: Methane | F9: H2, CO2 | G9: CH4, H2O, heat | H9: paper_müller_PowerX_2025
A10: methane_synthesis_archea | B10: Bioelectrochemical CO2 hydrogenation via methanogenic archea | C10: Conversion | D10: Hydrogenation | E10: Methane | F10: H2, CO2 | G10: CH4, H2O, heat | H10: paper_müller_PowerX_2025
A11: co2_direct_reaction | B11: CO2 reduction at electrode surface | C11: Conversion | D11: Hydrogenation | F11: CO2, H20, Electricity | G11: CO | H11: paper_müller_PowerX_2025
A12: co_electrolysis | B12: High temperature co-electrolysis of CO2 and H2O | C12: Conversion | D12: Electrolysis | E12: Co2 | F12: CO2, H2O, Electricity, heat | G12: CO, H2O, O2 | H12: paper_müller_PowerX_2025
A13: Elec_El13_El47 | B13: Electricity network between El13 and El47 | C13: Network | D13: Electricity Transport | G13: electricity
A14: Elec_El47_El13 | B14: Coupled electricity network between El47 and El13. | C14: Network | D14: Electricity Transport | G14: electricity
A15: Elec_El47_ElBdg | B15: Electricity network connection between El47 and buildings. | C15: Network | D15: Electricity Transport | G15: electricity
A16: Elec_ElBdg_El47 | B16: Coupled electricity network between buildings and El47. | C16: Network | D16: Electricity Transport | G16: electricity
A17: Elec_El47_ElRest | B17: Electricity network connection between El47 and other electricity nodes. | C17: Network | D17: Electricity Transport | G17: electricity
A18: Elec_ElRest_El47 | B18: Coupled electricity network between other electricity nodes and El47. | C18: Network | D18: Electricity Transport | G18: electricity
A19: Elec_Nuclear_U235_El13 | B19: Electricity generation from nuclear power (U235) at node El13. | C19: Conversion | D19: Fission | F19: U235 | G19: electricity
A20: Elec_Msw_Incinerator | B20: Electricity generation from municipal solid waste (MSW) incineration. | C20: Conversion | D20: Digestion | F20: Municipal solid waste | G20: electricity
A21: Elec_H2_Ccgt | B21: Hydrogen-fueled combined cycle gas turbine (CCGT) electricity generation). | C21: Conversion | D21: Electricity Generation | F21: H2 | G21: electricity
A22: Elec_H2_Ocgt | B22: Hydrogen-fueled open cycle gas turbine (OCGT) electricity generation. | C22: Conversion | D22: Electricity Generation | F22: H2 | G22: electricity
A23: Elec_Ch4_Chp | B23: Combined heat and power (CHP) generation using methane (CH₄). | C23: Conversion | D23: Electricity Generation | F23: CH4 | G23: heat, electricity
A24: Elec_Ch4_Ocgt | B24: Methane-fueled open cycle gas turbine (OCGT) electricity generation. | C24: Conversion | D24: Electricity Generation | F24: CH4 | G24: electricity
A25: Elec_Ch4_Ccgt | B25: Methane-fueled CCGT with carbon capture and storage (CCS). | C25: Conversion | D25: Electricity Generation | F25: CH4
A26: Elec_Ch4_CcgtCcs | B26: Methane-fueled CCGT with carbon capture and storage (CCS). | C26: Conversion | D26: Electricity Generation | F26: CH4
A27: Elec_Wood_Chp | B27: Combined heat and power (CHP) generation using wood. | C27: Conversion | D27: CHP Generation | F27: Wood | G27: heat, electricity
A28: Elec_Geothermal_Chp | B28: Geothermal-based CHP generation (2040). | C28: Conversion | D28: CHP Generation | F28: heat (geothermal) | G28: heat, electricity
A29: Elec_Fuelcell_El47 | B29: Electricity generation via fuel cells at node El47. | C29: Conversion | D29: Fuelcell
A30: Elec_FuelcellCh4_El47 | B30: Methane-fueled fuel cell electricity generation at El47. | C30: Conversion | D30: Fuelcell
A31: Hydro_HydroRor_Plant | B31: Run-of-river hydroelectric power plant. | C31: Conversion | D31: Hydropower | F31: H2O | G31: electricity
A32: Hydro_HydroS_Turbine | B32: Hydroelectric power generation from storage reservoirs. | C32: Conversion | D32: Hydropower | F32: H2O | G32: electricity
A33: Hydro_HydroSMustrun_Turbine | B33: Must-run hydroelectric power generation from storage reservoirs. | C33: Conversion | D33: Hydropower | F33: H2O | G33: electricity
A34: Hydro_HydroPumped_Turbine | B34: Pumped hydroelectric power generation (turbine mode). | C34: Conversion | D34: Hydropower | F34: H2O | G34: electricity
A35: Hydro_HydroPumped_Pump | B35: Pumped hydroelectric energy storage (pump mode). | C35: Conversion | D35: Hydropower | F35: H2O | G35: electricity
A36: Elec_Fuelcell_ElBdg | B36: Electricity generation via fuel cells in buildings (2030). | C36: Conversion | D36: Fuelcell | G36: electricity
A37: Elec_FuelcellCh4_ElBdg | B37: Methane-fueled fuel cell electricity generation in buildings (2030). | C37: Conversion | D37: Fuelcell | F37: CH4 | G37: heat
A38: Thermal_ThermalBdg_Hp | B38: Generic heat pump for residential heating, fixed COP 4 | C38: Conversion | D38: Heatpump | F38: heat | G38: heat
A39: Thermal_ThermalBdg_HpSc | B39: Coupled heat pump system for buildings. | C39: Conversion | D39: Heatpump | F39: heat
A40: Thermal_ThermalBdg_ElBdg_ThSc | B40: Electric heating system for buildings with thermal storage. | C40: Conversion | D40: Heating | F40: electricity
A41: Thermal_ThermalBdg_El | B41: Electric heating system for buildings. | C41: Conversion | D41: Heating | F41: electricity | G41: heat
A42: Thermal_ThermalBdg_Wood | B42: Wood-fueled heating system for buildings. | C42: Conversion | D42: Heating | F42: wood | G42: heat
A43: Thermal_ThermalBdg_Ch4 | B43: Methane-fueled heating system for buildings. | C43: Conversion | D43: Heating | F43: methane | G43: heat
A44: Thermal_ThermalBdg_C12 | B44: Hydrocarbon-fueled heating system for buildings. | C44: Conversion | D44: Heating | F44: CHn | G44: heat
A45: Thermal_MswPh_ThPh_Waste | B45: Waste-fueled thermal energy generation in power plants. | C45: Conversion | D45: Heat generation | F45: waste | G45: heat
A46: Thermal_ThAmb_ThHt | B46: Ambient heat extraction for heating (2030). | C46: Conversion | D46: Heat extraction | F46: heat | G46: heat
A47: Thermal_ThLt_ThHt | B47: Low-temperature heat upgrade for district heating. | C47: Conversion | D47: Heat generation | F47: heat | G47: heat
A48: Thermal_ThermalPh_El | B48: Electric heating system for thermal power plants. | C48: Conversion | D48: Heat generation | F48: electricity | G48: electricity
A49: Thermal_ThermalPh_Wood | B49: Wood-fueled heating system for thermal power plants. | C49: Conversion | D49: Heat generation | F49: wood | G49: electricity
A50: Thermal_ThermalPh_Ch4 | B50: Methane-fueled heating system for thermal power plants. | C50: Conversion | D50: Heat generation | F50: CH4 | G50: electricity
A51: Thermal_ThermalPh_C12 | B51: Hydrocarbon-fueled heating system for thermal power plants. | C51: Conversion | D51: Heat generation | F51: CHn | G51: electricity
A52: Thermal_ThermalPh_H2 | B52: Hydrogen-fueled heating system for thermal power plants (2030). | C52: Conversion | D52: Heat generation | F52: H2 | G52: electricity
A53: Thermal_ThDh_ThBdg | B53: Thermal network connection between district heating and buildings. | C53: Network | D53: Transport | F53: heat
A54: Thermal_ThHt_ThDh | B54: Thermal network connection between heat sources and district heating. | C54: Network | D54: Heat transport | F54: heat
A55: ThBdg_Vent | B55: Ventilation heat loss in buildings. | C55: Conversion | D55: Heat loss | F55: heat
A56: ThLt_Vent | B56: Ventilation heat loss at low-temperature heat nodes. | C56: Conversion | D56: Heat loss | F56: heat
A57: ThHt_Vent | B57: Ventilation heat loss at high-temperature heat nodes. | C57: Conversion | D57: Heat loss | F57: heat
A58: ThPh_Vent | B58: Ventilation heat loss at thermal power plants. | C58: Conversion | D58: Heat loss | F58: heat
A59: Hydrogen_Electrolysis_El47_H2 | B59: Electrolysis 2030, Alkaline technology is the benchmark | C59: Conversion | D59: Electrolysis | F59: H2O
A60: Hydrogen_Gasification_Wood_Syngas | B60: Woody biomass gasification to syngas | C60: Conversion | D60: Gasification | F60: wood | G60: CO, H2
A61: Hydrogen_Gasification_Msw_Syngas | B61: Municipal solid waste gasification to syngas | C61: Conversion | D61: Gasification | F61: waste | G61: CO, H2
A62: Hydrogen_Gasification_Wood_H2 | B62: Woody biomass gasification to hydrogen | C62: Conversion | D62: Gasification | F62: wood | G62: H2
A63: Hydrogen_Gasification_Msw_H2 | B63: Municipal solid waste gasification to hydrogen | C63: Conversion | D63: Gasification | F63: waste | G63: J2
A64: Methane_Digestion_BioWet_Ch4 | B64: Wet biomass anaerobic digestion with gas separation | C64: Conversion | D64: Digestion | F64: biomass | G64: CH4
A65: Methane_Hydrogenation_CO2_Ch4 | B65: Methane synthesis from H2 and CO2 via the thermo catalytic Sabatier reaction. | C65: Conversion | D65: Hydrogenation | F65: H2, CO2 | G65: CH4
A66: Methane_Hydrogenation_Syngas_Ch4 | B66: Methane synthesis from Syngas via the thermo catalytic CO hydrogenation. | C66: Conversion | D66: Hydrogenation | G66: CH4
A67: Methanol_Syngas_MeOH | C67: Conversion | G67: CH4
A68: Methanol_Hydrogenation_H2_MeOH | B68: Methanol sysnthesis from hydrogenation | C68: Conversion | D68: Hydrogenation | G68: CH4
A69: CarbonDioxide_CO2Sys_Vent | B69: Carbon dioxide venting from the CO₂ system. | C69: Conversion | D69: CO2 Venting | F69: CO2
A70: CarbonCapture_Amine | B70: CO2 post combustion capture via Amine washing. Temperature swing process. 2030 reference based on an approx. 150 ktCO2/a plant size. | C70: Conversion | D70: Carbon Capture | F70: CO2, amine
A71: CarbonCapture_Hpc | B71: CO2 post combustion capture via Hot-Potassium Carbonate cycling. Pressure swing process. 2030 reference based on an approx. 150 ktCO2/a plant size. | C71: Conversion | D71: Carbon Capture | F71: CO2
A72: CarbonCapture_CO2Waste_Vent | B72: CO₂ venting from waste-related processes. | C72: Conversion | D72: Carbon Capture | F72: waste
A73: CarbonCapture_CO2Wood_Vent | B73: CO₂ venting from wood-related processes. | C73: Conversion | D73: Carbon Capture | F73: wood
A74: CarbonCapture_DacAds | B74: Direct air capture using adsorption technology. | C74: Conversion | D74: Carbon Capture | F74: air
A75: CarbonDioxide_Pipeline | B75: Not in Tech description | C75: Conversion | D75: Carbon Transport
A76: CarbonMonoxide_Rwgs_H2_CO | B76: Reverse water gas shift reaction plant. Emerging technology. | C76: Conversion | D76: Reverse Water Gas Shift Reaction
A77: CarbonMonoxide_ElecRR_CO2_CO | B77: Reverse water gas shift reaction plant. Mature technology, 2040. | C77: Conversion | D77: Reverse Water Gas Shift Reaction
A78: CarbonMonoxide_CO_Vent | B78: Carbon monoxide venting. | C78: Conversion | D78: CO2 Venting
A79: CarbonDioxide_RoadRail | B79: Not in Tech description | C79: Network | D79: CO2 Transport | G79: biochar
A80: Pyrolysis_Wood_CBio | B80: Biochar production via pyrolysis of wood. | C80: Conversion | D80: Pyrolysis | F80: wood | G80: biochar
A81: Pyrolysis_BioWet_CBio | B81: Biochar production via pyrolysis of wet biomass. | C81: Conversion | D81: Pyrolysis | F81: biomass | G81: biochar
A82: Pyrolysis_Ch4_CCh4 | B82: Not in Tech description | C82: Conversion | D82: Pyrolysis
A83: Hydrocarbons_FischerTropsch_C8 | B83: Hydrocarbon (C8) synthesis via Fischer-Tropsch process. | C83: Conversion | D83: FischerTropsch | G83: C8
A84: Hydrocarbons_FischerTropsch_C12 | B84: Hydrocarbon (C12) synthesis via Fischer-Tropsch process. | C84: Conversion | D84: FischerTropsch | G84: C12
A85: Wind_Turbine_Generic | B85: Generic wind turbine electricity generation (2020). | C85: Conversion | D85: Wind Turbine | F85: wind | G85: electricity
A86: Ammonia_HaberBosch | B86: Synthesizing Ammonia from Haber Bosch Process | C86: Conversion | D86: Haber Bosch

Sheet Process ID
A1: Processes Classification
A2: Process ID | B2: Process Description | C2: Tech Type | D2: Process Category | E2: Primay Feedstock | F2: Feedstocks | G2: Products | H2: Reference | I2: Assumption
A3: Ammonia_HaberBosch | B3: Synthesizing Ammonia from Haber Bosch Process | C3: Conversion | D3: Haber Bosch
A4: biomass_gasification_to_syngas | B4: Biomass gasification to syngas | C4: Conversion | D4: Gasification | E4: Syngas | F4: Wood, O2 | G4: H2
A5: CarbonCapture_Amine | B5: CO2 post combustion capture via Amine washing. Temperature swing process. 2030 reference based on an approx. 150 ktCO2/a plant size. | C5: Conversion | D5: Carbon Capture | F5: CO2, amine
A6: CarbonCapture_CO2Waste_Vent | B6: CO₂ venting from waste-related processes. | C6: Conversion | D6: Carbon Capture | F6: waste
A7: CarbonCapture_CO2Wood_Vent | B7: CO₂ venting from wood-related processes. | C7: Conversion | D7: Carbon Capture | F7: wood
A8: CarbonCapture_DacAds | B8: Direct air capture using adsorption technology. | C8: Conversion | D8: Carbon Capture | F8: air
A9: CarbonCapture_Hpc | B9: CO2 post combustion capture via Hot-Potassium Carbonate cycling. Pressure swing process. 2030 reference based on an approx. 150 ktCO2/a plant size. | C9: Conversion | D9: Carbon Capture | F9: CO2
A10: CarbonDioxide_CO2Sys_Vent | B10: Carbon dioxide venting from the CO₂ system. | C10: Conversion | D10: CO2 Venting | F10: CO2
A11: CarbonDioxide_Pipeline | B11: Not in Tech description | C11: Conversion | D11: Carbon Transport
A12: CarbonDioxide_RoadRail | B12: Not in Tech description | C12: Network | D12: CO2 Transport | G12: biochar
A13: CarbonMonoxide_CO_Vent | B13: Carbon monoxide venting. | C13: Conversion | D13: CO2 Venting
A14: CarbonMonoxide_ElecRR_CO2_CO | B14: Reverse water gas shift reaction plant. Mature technology, 2040. | C14: Conversion | D14: Reverse Water Gas Shift Reaction
A15: CarbonMonoxide_Rwgs_H2_CO | B15: Reverse water gas shift reaction plant. Emerging technology. | C15: Conversion | D15: Reverse Water Gas Shift Reaction
A16: co_electrolysis | B16: High temperature co-electrolysis of CO2 and H2O | C16: Conversion | D16: Electrolysis | E16: Co2 | F16: CO2, H2O, Electricity, heat | G16: CO, H2O, O2 | H16: paper_müller_PowerX_2025
A17: co2_direct_reaction | B17: CO2 reduction at electrode surface | C17: Conversion | D17: Hydrogenation | F17: CO2, H20, Electricity | G17: CO | H17: paper_müller_PowerX_2025
A18: Elec_Ch4_Ccgt | B18: Methane-fueled CCGT with carbon capture and storage (CCS). | C18: Conversion | D18: Electricity Generation | F18: CH4
A19: Elec_Ch4_CcgtCcs | B19: Methane-fueled CCGT with carbon capture and storage (CCS). | C19: Conversion | D19: Electricity Generation | F19: CH4
A20: Elec_Ch4_Chp | B20: Combined heat and power (CHP) generation using methane (CH₄). | C20: Conversion | D20: Electricity Generation | F20: CH4 | G20: heat, electricity
A21: Elec_Ch4_Ocgt | B21: Methane-fueled open cycle gas turbine (OCGT) electricity generation. | C21: Conversion | D21: Electricity Generation | F21: CH4 | G21: electricity
A22: Elec_El13_El47 | B22: Electricity network between El13 and El47 | C22: Network | D22: Electricity Transport | G22: electricity
A23: Elec_El47_El13 | B23: Coupled electricity network between El47 and El13. | C23: Network | D23: Electricity Transport | G23: electricity
A24: Elec_El47_ElBdg | B24: Electricity network connection between El47 and buildings. | C24: Network | D24: Electricity Transport | G24: electricity
A25: Elec_El47_ElRest | B25: Electricity network connection between El47 and other electricity nodes. | C25: Network | D25: Electricity Transport | G25: electricity
A26: Elec_ElBdg_El47 | B26: Coupled electricity network between buildings and El47. | C26: Network | D26: Electricity Transport | G26: electricity
A27: Elec_ElRest_El47 | B27: Coupled electricity network between other electricity nodes and El47. | C27: Network | D27: Electricity Transport | G27: electricity
A28: Elec_Fuelcell_El47 | B28: Electricity generation via fuel cells at node El47. | C28: Conversion | D28: Fuelcell
A29: Elec_Fuelcell_ElBdg | B29: Electricity generation via fuel cells in buildings (2030). | C29: Conversion | D29: Fuelcell | G29: electricity
A30: Elec_FuelcellCh4_El47 | B30: Methane-fueled fuel cell electricity generation at El47. | C30: Conversion | D30: Fuelcell
A31: Elec_FuelcellCh4_ElBdg | B31: Methane-fueled fuel cell electricity generation in buildings (2030). | C31: Conversion | D31: Fuelcell | F31: CH4 | G31: heat
A32: Elec_Geothermal_Chp | B32: Geothermal-based CHP generation (2040). | C32: Conversion | D32: CHP Generation | F32: heat (geothermal) | G32: heat, electricity
A33: Elec_H2_Ccgt | B33: Hydrogen-fueled combined cycle gas turbine (CCGT) electricity generation). | C33: Conversion | D33: Electricity Generation | F33: H2 | G33: electricity
A34: Elec_H2_Ocgt | B34: Hydrogen-fueled open cycle gas turbine (OCGT) electricity generation. | C34: Conversion | D34: Electricity Generation | F34: H2 | G34: electricity
A35: Elec_Msw_Incinerator | B35: Electricity generation from municipal solid waste (MSW) incineration. | C35: Conversion | D35: Digestion | F35: Municipal solid waste | G35: electricity
A36: Elec_Nuclear_U235_El13 | B36: Electricity generation from nuclear power (U235) at node El13. | C36: Conversion | D36: Fission | F36: U235 | G36: electricity
A37: Elec_Wood_Chp | B37: Combined heat and power (CHP) generation using wood. | C37: Conversion | D37: CHP Generation | F37: Wood | G37: heat, electricity
A38: electrolysis_water | B38: Electrolysis, water | C38: Conversion | D38: Electrolysis | E38: Hydrogen | F38: H2O, Electricity | G38: H2
A39: Hydro_HydroPumped_Pump | B39: Pumped hydroelectric energy storage (pump mode). | C39: Conversion | D39: Hydropower | F39: H2O | G39: electricity
A40: Hydro_HydroPumped_Turbine | B40: Pumped hydroelectric power generation (turbine mode). | C40: Conversion | D40: Hydropower | F40: H2O | G40: electricity
A41: Hydro_HydroRor_Plant | B41: Run-of-river hydroelectric power plant. | C41: Conversion | D41: Hydropower | F41: H2O | G41: electricity
A42: Hydro_HydroS_Turbine | B42: Hydroelectric power generation from storage reservoirs. | C42: Conversion | D42: Hydropower | F42: H2O | G42: electricity
A43: Hydro_HydroSMustrun_Turbine | B43: Must-run hydroelectric power generation from storage reservoirs. | C43: Conversion | D43: Hydropower | F43: H2O | G43: electricity
A44: Hydrocarbons_FischerTropsch_C12 | B44: Hydrocarbon (C12) synthesis via Fischer-Tropsch process. | C44: Conversion | D44: FischerTropsch | G44: C12
A45: Hydrocarbons_FischerTropsch_C8 | B45: Hydrocarbon (C8) synthesis via Fischer-Tropsch process. | C45: Conversion | D45: FischerTropsch | G45: C8
A46: Hydrogen_Electrolysis_El47_H2 | B46: Electrolysis 2030, Alkaline technology is the benchmark | C46: Conversion | D46: Electrolysis | F46: H2O
A47: Hydrogen_Gasification_Msw_H2 | B47: Municipal solid waste gasification to hydrogen | C47: Conversion | D47: Gasification | F47: waste | G47: J2
A48: Hydrogen_Gasification_Msw_Syngas | B48: Municipal solid waste gasification to syngas | C48: Conversion | D48: Gasification | F48: waste | G48: CO, H2
A49: Hydrogen_Gasification_Wood_H2 | B49: Woody biomass gasification to hydrogen | C49: Conversion | D49: Gasification | F49: wood | G49: H2
A50: Hydrogen_Gasification_Wood_Syngas | B50: Woody biomass gasification to syngas | C50: Conversion | D50: Gasification | F50: wood | G50: CO, H2
A51: Methane_Digestion_BioWet_Ch4 | B51: Wet biomass anaerobic digestion with gas separation | C51: Conversion | D51: Digestion | F51: biomass | G51: CH4
A52: Methane_Hydrogenation_CO2_Ch4 | B52: Methane synthesis from H2 and CO2 via the thermo catalytic Sabatier reaction. | C52: Conversion | D52: Hydrogenation | F52: H2, CO2 | G52: CH4
A53: Methane_Hydrogenation_Syngas_Ch4 | B53: Methane synthesis from Syngas via the thermo catalytic CO hydrogenation. | C53: Conversion | D53: Hydrogenation | G53: CH4
A54: methane_synthesis_archea | B54: Bioelectrochemical CO2 hydrogenation via methanogenic archea | C54: Conversion | D54: Hydrogenation | E54: Methane | F54: H2, CO2 | G54: CH4, H2O, heat | H54: paper_müller_PowerX_2025
A55: methane_synthesis_biomass | B55: Biological methaniation | C55: Conversion | D55: Hydrogenation | E55: Methane | F55: H2, CO2 | G55: CH4, H2O, heat | H55: paper_müller_PowerX_2025
A56: methane_synthesis_h2_co2_sabatier | B56: Methane synthesis from H2 and CO2 via the thermo catalytic Sabatier reaction | C56: Conversion | D56: Hydrogenation | E56: Methane | F56: H2, CO2 | G56: CH4, H2O, heat
A57: methane_synthesis_syngas_sabatier | B57: Methane synthesis from Syngas via the thermo catalytic Sabatier reaction | C57: Conversion | D57: Hydrogenation | E57: Methane | F57: H2, CO | G57: CH4, H2O, heat
A58: Methanol_Hydrogenation_H2_MeOH | B58: Methanol sysnthesis from hydrogenation | C58: Conversion | D58: Hydrogenation | G58: CH4
A59: Methanol_Syngas_MeOH | C59: Conversion | G59: CH4
A60: msw_gasification_to_syngas | B60: Municipal solid waste gasification to syngas | C60: Conversion | D60: Gasification | E60: Syngas | F60: MSW | G60: H2
A61: Pyrolysis_BioWet_CBio | B61: Biochar production via pyrolysis of wet biomass. | C61: Conversion | D61: Pyrolysis | F61: biomass | G61: biochar
A62: Pyrolysis_Ch4_CCh4 | B62: Not in Tech description | C62: Conversion | D62: Pyrolysis
A63: Pyrolysis_Wood_CBio | B63: Biochar production via pyrolysis of wood. | C63: Conversion | D63: Pyrolysis | F63: wood | G63: biochar
A64: reverse_water_gas_shift_reaction | B64: Reverse water gas shift reaction plant | C64: Conversion | D64: Reverse Water Gas Shift Reaction | E64: CarbonMonoxide | F64: H2, CO2, heat | G64: CO
A65: ThBdg_Vent | B65: Ventilation heat loss in buildings. | C65: Conversion | D65: Heat loss | F65: heat
A66: Thermal_MswPh_ThPh_Waste | B66: Waste-fueled thermal energy generation in power plants. | C66: Conversion | D66: Heat generation | F66: waste | G66: heat
A67: Thermal_ThAmb_ThHt | B67: Ambient heat extraction for heating (2030). | C67: Conversion | D67: Heat extraction | F67: heat | G67: heat
A68: Thermal_ThDh_ThBdg | B68: Thermal network connection between district heating and buildings. | C68: Network | D68: Transport | F68: heat
A69: Thermal_ThermalBdg_C12 | B69: Hydrocarbon-fueled heating system for buildings. | C69: Conversion | D69: Heating | F69: CHn | G69: heat
A70: Thermal_ThermalBdg_Ch4 | B70: Methane-fueled heating system for buildings. | C70: Conversion | D70: Heating | F70: methane | G70: heat
A71: Thermal_ThermalBdg_El | B71: Electric heating system for buildings. | C71: Conversion | D71: Heating | F71: electricity | G71: heat
A72: Thermal_ThermalBdg_ElBdg_ThSc | B72: Electric heating system for buildings with thermal storage. | C72: Conversion | D72: Heating | F72: electricity
A73: Thermal_ThermalBdg_Hp | B73: Generic heat pump for residential heating, fixed COP 4 | C73: Conversion | D73: Heatpump | F73: heat | G73: heat
A74: Thermal_ThermalBdg_HpSc | B74: Coupled heat pump system for buildings. | C74: Conversion | D74: Heatpump | F74: heat
A75: Thermal_ThermalBdg_Wood | B75: Wood-fueled heating system for buildings. | C75: Conversion | D75: Heating | F75: wood | G75: heat
A76: Thermal_ThermalPh_C12 | B76: Hydrocarbon-fueled heating system for thermal power plants. | C76: Conversion | D76: Heat generation | F76: CHn | G76: electricity
A77: Thermal_ThermalPh_Ch4 | B77: Methane-fueled heating system for thermal power plants. | C77: Conversion | D77: Heat generation | F77: CH4 | G77: electricity
A78: Thermal_ThermalPh_El | B78: Electric heating system for thermal power plants. | C78: Conversion | D78: Heat generation | F78: electricity | G78: electricity
A79: Thermal_ThermalPh_H2 | B79: Hydrogen-fueled heating system for thermal power plants (2030). | C79: Conversion | D79: Heat generation | F79: H2 | G79: electricity
A80: Thermal_ThermalPh_Wood | B80: Wood-fueled heating system for thermal power plants. | C80: Conversion | D80: Heat generation | F80: wood | G80: electricity
A81: Thermal_ThHt_ThDh | B81: Thermal network connection between heat sources and district heating. | C81: Network | D81: Heat transport | F81: heat
A82: Thermal_ThLt_ThHt | B82: Low-temperature heat upgrade for district heating. | C82: Conversion | D82: Heat generation | F82: heat | G82: heat
A83: ThHt_Vent | B83: Ventilation heat loss at high-temperature heat nodes. | C83: Conversion | D83: Heat loss | F83: heat
A84: ThLt_Vent | B84: Ventilation heat loss at low-temperature heat nodes. | C84: Conversion | D84: Heat loss | F84: heat
A85: ThPh_Vent | B85: Ventilation heat loss at thermal power plants. | C85: Conversion | D85: Heat loss | F85: heat
A86: wet_biomass_anaerobic_digestion_gas_separation | B86: Wet biomass anaerobic digestion with gas separation | C86: Conversion | D86: Digestion | E86: Methane | F86: BioWet | G86: CH4, CO2
A87: Wind_Turbine_Generic | B87: Generic wind turbine electricity generation | C87: Conversion | D87: Wind Turbine | F87: wind | G87: electricity

Sheet Technology ID
A1: Technology Classification
A2: [Sheet] | B2: [Datapaper Tech ID] | C2: [ehubX Tech ID] | D2: [Process ID] | E2: [Process Type] | F2: [str] | G2: [Ontology IRI] | H2: [str] | I2: [Tech Year] | J2: [MainSector] | K2: [MainCategory] | L2: [CategorySpec] | M2: [TechType]
A3: sheet | B3: tech_id | C3: ehubX Tech ID | D3: process_id | E3: process_type | F3: unit_operation | G3: tech_ontology_IRI | H3: description | I3: tech_year | J3: main_sector | K3: main_category | L3: category_spec | M3: tech_type
A4: ConvTech | B4: Ammonia_HaberBosch | C4: T_C_Conv_Ammonia_HaberBosch | D4: Ammonia_HaberBosch | E4: Ammonia Synthesis | F4: Haber Bosch unit | H4: Ammonia synthesis via Haber Bosch process. | I4: 2050 | J4: Ammonia | K4: Chemical Synthesis | L4: Haber Bosch | M4: Conversion
A5: ConvTech | B5: Ammonia_OCGT | C5: T_C_Conv_Ammonia_OCGT | D5: Ammonia_OCGT | E5: Electricity Generation | F5: OCGT | I5: 2050 | J5: Electricity | K5: Gas Turbine | L5: Ammonia fueled | M5: Conversion
A6: ConvTech | B6: Amine_Washing_CO2 | C6: T_C_Conv_CarbonCapture_Amine | D6: CarbonCapture_Amine | E6: CO2 Capture | F6: Amine washing unit | H6: CO2 post combustion capture via Amine washing. Temperature swing process. Reference based on an approx. 150 ktCO2/a plant size. | I6: 2030, 2040, 2050 | J6: Carbon Capture | K6: Point Source Capture | L6: Amine washing | M6: Conversion
A7: ConvTech | B7: Waste_Venting_CO2 | C7: T_C_Conv_CarbonCapture_CO2Waste_Vent | D7: CarbonCapture_CO2Waste_Vent | E7: CO2 Capture | F7: Ventilator | H7: CO2 venting from waste-related processes. | I7: 2050 | J7: Carbon Capture | K7: Ventilation | L7: Waste | M7: Conversion
A8: ConvTech | B8: Wood_Venting_CO2 | C8: T_C_Conv_CarbonCapture_CO2Wood_Vent | D8: CarbonCapture_CO2Wood_Vent | E8: CO2 Capture | F8: Ventilator | H8: CO2 venting from wood-related processes. | I8: 2050 | J8: Carbon Capture | K8: Ventilation | L8: Wood | M8: Conversion
A9: ConvTech | B9: CarbonCapture_Direct | C9: T_C_Conv_CarbonCapture_DacAds | D9: CarbonCapture_DacAds | E9: CO2 Capture | F9: DAC | H9: Direct air capture using adsorption technology. | I9: 2030, 2040, 2050 | J9: Carbon Capture | K9: DAC | L9: Adsorption | M9: Conversion
A10: ConvTech | B10: CarbonCapture_PressureSwing | C10: T_C_Conv_CarbonCapture_Hpc | D10: CarbonCapture_Hpc | E10: CO2 Capture | F10: Potassium Carbonate Cycling | H10: CO2 post combustion capture via Hot-Potassium Carbonate cycling. Pressure swing process. Reference based on an approx. 150 ktCO2/a plant size. | I10: 2030, 2040, 2050 | J10: Carbon Capture | K10: Point Source Capture | L10: HPC cycling | M10: Conversion
A11: ConvTech | B11: CO2_Venting | C11: T_C_Conv_CarbonDioxide_CO2Sys_Vent | D11: CarbonDioxide_CO2Sys_Vent | E11: CO2 Venting | F11: Ventilator | H11: Carbon dioxide venting from the CO2 system. | I11: na | J11: Carbon Dioxide | K11: Ventilation | L11: CO2 System | M11: Conversion
A12: ConvTech | B12: CO2_Pipeline | C12: T_C_Net_CarbonDioxide_Pipeline (T_C_Net_CarbonDioxide_CO2Sys_CO2Exp) | D12: CarbonDioxide_Pipeline | E12: CO2 Transport | F12: Pipeline | H12: Carbon Dioxide Pipeline | I12: 2050 | J12: Carbon Dioxide | K12: Pipeline | L12: General | M12: Transport
A13: ConvTech | B13: CO2_Roadrail | C13: T_C_Net_CarbonDioxide_RoadRail | D13: CarbonDioxide_RoadRail | E13: CO2 Transport | F13: Road, Rail | H13: Not in Tech description | I13: na | J13: Carbon Dioxide | K13: Road, Rail | L13: General | M13: Transport
A14: ConvTech | B14: CO_Venting | C14: T_C_Conv_CarbonMonoxide_CO_Vent | D14: CarbonMonoxide_CO_Vent | E14: CO Venting | F14: Venitlator | H14: Carbon monoxide venting. | I14: na | J14: Carbon Monoxide | K14: Ventilation | L14: General | M14: Conversion
A15: ConvTech | B15: CO2_RWGS_CO | C15: T_C_CarbonMonoxide_ElecRR_CO2 | D15: CarbonMonoxide_ElecRR_CO2 | E15: Electrochemical CO2 Reduction | F15: Electrolyzer | I15: na | J15: Carbon Monoxide | K15: Electrolysis | L15: Reduction | M15: Conversion
A16: ConvTech | B16: H2_CO2_RWGS_CO | C16: T_C_Conv_CarbonMonoxide_Rwgs_H2_CO | D16: CarbonMonoxide_Rwgs_H2_CO | E16: Reverse Water Gas Shift | F16: RWGS reactor | H16: Reverse water gas shift reaction plant. Emerging technology. | I16: 2030, 2040 | J16: Carbon Monoxide | K16: RWGS | L16: General | M16: Conversion
A17: ConvTech | B17: CH4_CCGT | C17: T_C_Conv_Elec_CH4_Ccgt | D17: Elec_CH4_Ccgt | E17: Electricity Generation | F17: CCGT | H17: Methane-fueled CCGT | I17: 2050 | J17: Electricity | K17: Gas Turbine | L17: Methane fueled | M17: Conversion
A18: ConvTech | B18: CH4_CCGT_CCS | C18: T_C_Conv_Elec_CH4_CCGT + CCS Combo | D18: Elec_CH4_CCGT + CCS Combo | E18: Electricity Generation | F18: CCGT, CCS | H18: Methane-fueled CCGT with carbon capture and storage (CCS). | I18: 2050 | J18: Electricity, Carbon Capture | K18: Gas Turbine, CCS | L18: Methane fueled | M18: Conversion
A19: ConvTech | B19: CH4_CHP | C19: T_C_Conv_Elec_CH4_Chp | D19: Elec_CH4_Chp | E19: CHP Generation | F19: Heat and power co-generation unit | H19: Combined heat and power (CHP) generation using methane (CH₄). | I19: 2050 | J19: Electricity, Heat | K19: CHP | L19: Methane fueled | M19: Conversion
A20: ConvTech | B20: CH4_OCGT | C20: T_C_Conv_Elec_CH4_Ocgt | D20: Elec_CH4_Ocgt | E20: Electricity Generation | F20: OCGT | H20: Methane-fueled open cycle gas turbine (OCGT) electricity generation. | I20: 2050 | J20: Electricity | K20: Gas Turbine | L20: Methane fueled | M20: Conversion
A21: ConvTech | B21: Electricity | C21: T_C_Net_Elec_El13_El47 | D21: Elec_El13_El47 | E21: Eletricity Transmission | F21: Transformer | H21: Not in Tech description | I21: 2020, 2030, 2040, 2050 | J21: Electricity | K21: Grid | L21: Transmission | M21: Transport
A22: ConvTech | B22: Electricity_Buildings | C22: T_C_Net_Elec_El47_ElBdg | D22: Elec_El47_ElBdg | E22: Eletricity Transmission | F22: Grid | H22: Electricity network connection between El47 and buildings. | I22: 2020, 2030, 2040, 2050 | J22: Electricity | K22: Grid | L22: Distribution | M22: Transport
A23: ConvTech | B23: Electricity_Node47_ToRest | C23: T_C_Net_Elec_El47_ElRest | D23: Elec_El47_ElRest | E23: Eletricity Transmission | F23: Grid | H23: Electricity network connection between El47 and other electricity nodes. | I23: 2020, 2030, 2040, 2050 | J23: Electricity | K23: Grid | L23: Distribution | M23: Transport
A24: ConvTech | B24: Coupled_Electricity_Buildings | C24: T_C_NetCoupled_Elec_ElBdg_El47 | D24: Elec_ElBdg_El47 | E24: Eletricity Transmission | F24: Grid | H24: Coupled electricity network between buildings and El47. | I24: 2020, 2050 | J24: Electricity | K24: Grid | L24: Distribution | M24: Transport
A25: ConvTech | B25: Coupled_Electricity_Node47_ToRest | C25: T_C_NetCoupled_Elec_ElRest_El47 | D25: Elec_ElRest_El47 | E25: Eletricity Transmission | F25: Grid | H25: Coupled electricity network between other electricity nodes and El47. | I25: 2020, 2050 | J25: Electricity | K25: Grid | L25: Distribution | M25: Transport
A26: ConvTech | B26: H2_Fuelcell_Buildings | C26: T_C_Conv_Elec_Fuelcell_ElBdg | D26: Elec_Fuelcell_ElBdg | E26: Electricity Generation | F26: Fuel cell | H26: Electricity generation via fuel cells in buildings. | I26: 2040, 2050 | J26: Electricity | K26: Fuel Cell | L26: Hydrogen fueled | M26: Conversion
A27: ConvTech | B27: H2_Fuelcell | C27: T_C_Conv_Elec_Fuelcell_H2_El47 | D27: Elec_Fuelcell_H2_El47 | E27: Electricity Generation | F27: Fuel cell | H27: Electricity generation via fuel cells at node El47. | I27: 2040, 2050 | J27: Electricity | K27: Fuel Cell | L27: Hydrogen fueled | M27: Conversion
A28: ConvTech | B28: CH4_Fuelcell | C28: T_C_Conv_Elec_FuelcellCH4_El47 | D28: Elec_FuelcellCH4_El47 | E28: Electricity Generation | F28: Fuel cell | H28: Methane-fueled fuel cell electricity generation at El47. | I28: 2030 | J28: Electricity | K28: Fuel Cell | L28: Methane fueled | M28: Conversion
A29: ConvTech | B29: CH4_Fuelcell_Buildings | C29: T_C_Conv_Elec_FuelcellCH4_ElBdg | D29: Elec_FuelcellCH4_ElBdg | E29: Electricity Generation | F29: Fuel cell | H29: Methane-fueled fuel cell electricity generation in buildings. | I29: 2030 | J29: Electricity | K29: Fuel Cell | L29: Methane fueled | M29: Conversion
A30: ConvTech | B30: Geothermal_CHP | C30: T_C_Conv_Elec_Geothermal_Chp | D30: Elec_Geothermal_Chp | E30: CHP Generation | F30: Geothermal power plant | H30: Geothermal-based CHP generation. | I30: 2050 | J30: Electricity, Heat | K30: Geothermal | L30: General | M30: Conversion
A31: ConvTech | B31: H2_CCGT | C31: T_C_Conv_Elec_H2_Ccgt | D31: Elec_H2_Ccgt | E31: Electricity Generation | F31: CCGT | H31: Hydrogen-fueled combined cycle gas turbine (CCGT) electricity generation. | I31: 2050 | J31: Electricity | K31: Gas Turbine | L31: Hydrogen fueled | M31: Conversion
A32: ConvTech | B32: H2_OCGT | C32: T_C_Conv_Elec_H2_Ocgt | D32: Elec_H2_Ocgt | E32: Electricity Generation | F32: OCGT | H32: Hydrogen-fueled open cycle gas turbine (OCGT) electricity generation. | I32: 2050 | J32: Electricity | K32: Gas Turbine | L32: Hydrogen fueled | M32: Conversion
A33: ConvTech | B33: MunicipalSolidWaste_Incinerator_Electricity | C33: T_C_Conv_Elec_Msw_Incinerator | D33: Elec_Msw_Incinerator | E33: Thermal Powerplant | F33: Incineration Plant | H33: Electricity generation from municipal solid waste (MSW) incineration. | I33: 2020, 2030, 2040, 2050 | J33: Electricity | K33: Incinerator | L33: Waste | M33: Conversion
A34: ConvTech | B34: U235_NuclearReactor_Electricity | C34: T_C_Conv_Elec_Nuclear_U235_El13 | D34: Elec_Nuclear_U235_El13 | E34: Electricity Generation | F34: Nuclear power Plant | G34: http://openenergy-platform.org/ontology/oeo/OEO_00020053 | H34: Electricity generation from nuclear power (U235) at node El13. | I34: 2050 | J34: Electricity | K34: Nuclear | L34: U235 | M34: Conversion
A35: ConvTech | B35: Wood_CHP | C35: T_C_Conv_Elec_Wood_Chp | D35: Elec_Wood_Chp | E35: CHP Generation | F35: Heat and power co-generation unit | H35: Combined heat and power (CHP) generation using wood. | I35: 2020, 2030, 2040, 2050 | J35: Electricity, Heat | K35: CHP | L35: Wood | M35: Conversion
A36: ConvTech | B36: Hydro_Pumped_Pump | C36: T_C_Conv_Hydro_HydroPumped_Pump | D36: Hydro_HydroPumped_Pump | E36: Electricity Generation | F36: Hydropower Plant | H36: Pumped hydroelectric energy storage (pump mode). | I36: 2020, 2030, 2040, 2050 | J36: Electricity | K36: Hydro | L36: Pumped | M36: Conversion
A37: ConvTech | B37: Hydro_Pumped_Turbine | C37: T_C_Conv_Hydro_HydroPumped_Turbine | D37: Hydro_HydroPumped_Turbine | E37: Electricity Generation | F37: Hydropower Plant | H37: Pumped hydroelectric power generation (turbine mode). | I37: 2020, 2030, 2040, 2050 | J37: Electricity | K37: Hydro | L37: Pumped | M37: Conversion
A38: ConvTech | B38: Hydro_Run-of-river | C38: T_C_Conv_Hydro_HydroRor_Plant | D38: Hydro_HydroRor_Plant | E38: Electricity Generation | F38: Hydropower Plant | H38: Run-of-river hydroelectric power plant. | I38: 2020, 2030, 2040, 2050 | J38: Electricity | K38: Hydro | L38: Run-of-river | M38: Conversion
A39: ConvTech | B39: Hydro_Storage_Turbine | C39: T_C_Conv_Hydro_HydroS_Turbine | D39: Hydro_HydroS_Turbine | E39: Electricity Generation | F39: Hydropower Plant | H39: Hydroelectric power generation from storage reservoirs. | I39: 2020, 2030, 2040, 2050 | J39: Electricity | K39: Hydro | L39: Storage resevoirs | M39: Conversion
A40: ConvTech | B40: Hydro_Storage_Must-run_Turbine | C40: T_C_Conv_Hydro_HydroSMustrun_Turbine | D40: Hydro_HydroSMustrun_Turbine | E40: Electricity Generation | F40: Hydropower Plant | H40: Must-run hydroelectric power generation from storage reservoirs. | I40: 2020, 2050 | J40: Electricity | K40: Hydro | L40: Mustrun Turbine | M40: Conversion
A41: ConvTech | B41: H2_FischerTropsch_C12 | C41: T_C_Conv_Hydrocarbons_FischerTropsch_C12 | D41: Hydrocarbons_FischerTropsch_C12 | E41: Hydrocarbon Synthesis | F41: Fischer Tropsch unit | H41: Hydrocarbon (C12) synthesis via Fischer-Tropsch process. | I41: 2020, 2030, 2040, 2050 | J41: Hydrocarbons | K41: Synfuels | L41: Kerosine | M41: Conversion
A42: ConvTech | B42: H2_FischerTropsch_C8 | C42: T_C_Conv_Hydrocarbons_FischerTropsch_C8 | D42: Hydrocarbons_FischerTropsch_C8 | E42: Hydrocarbon Synthesis | F42: Fischer Tropsch unit | H42: Hydrocarbon (C8) synthesis via Fischer-Tropsch process. | I42: 2020, 2030, 2040, 2050 | J42: Hydrocarbons | K42: Synfuels | L42: Gasoline | M42: Conversion
A43: ConvTech | B43: H2_FischerTroptsch_VSE_C12 | C43: T_C_Conv_Hydrocarbons_FischerTropsch_VSA | D43: Hydrocarbons_FischerTropsch_VSA | E43: Hydrocarbon Synthesis | F43: Fischer Tropsch unit | H43: Hydrocarbon (C12) synthesis via Fischer-Tropsch process. | I43: 2050 | J43: Hydrocarbons | K43: Synfuels | L43: Kerosine | M43: Conversion
A44: ConvTech | B44: H2_Electrolysis | C44: T_C_Conv_Hydrogen_Electrolysis_El47_H2 | D44: Hydrogen_Electrolysis_El47_H2 | E44: Hydrogen Production | F44: Electrolyzer | H44: Electrolysis, Alkaline technology (10 MW) from Danish Energy Reports 2025 is the benchmark | I44: 2030, 2040, 2050 | J44: Hydrogen | K44: Electrolysis | L44: AEC | M44: Conversion
A45: ConvTech | B45: Waste_Waste_Hydrogen | C45: T_C_Conv_Hydrogen_Gasification_Msw_H2 | D45: Hydrogen_Gasification_Msw_H2 | E45: Hydrogen Production | F45: Fluidized Bed Gasifier | H45: Municipal solid waste gasification to hydrogen | I45: 2030 | J45: Hydrogen | K45: Gasification | L45: Waste | M45: Conversion
A46: ConvTech | B46: Waste_Gasification_Syngas | C46: T_C_Conv_Hydrogen_Gasification_Msw_Syngas | D46: Hydrogen_Gasification_Msw_Syngas | E46: Syngas Production | F46: Fluidized Bed Gasifier | H46: Municipal solid waste gasification to syngas | I46: 2030 | J46: Syngas | K46: Gasification | L46: Waste | M46: Conversion
A47: ConvTech | B47: Wood_Gasification_Hydrogen | C47: T_C_Conv_Hydrogen_Gasification_Wood_H2 | D47: Hydrogen_Gasification_Wood_H2 | E47: Hydrogen Production | F47: Fluidized Bed Gasifier | H47: Woody biomass gasification to hydrogen | I47: 2030 | J47: Hydrogen | K47: Gasification | L47: Wood | M47: Conversion
A48: ConvTech | B48: Wood_Gasification_Syngas | C48: T_C_Conv_Hydrogen_Gasification_Wood_Syngas | D48: Hydrogen_Gasification_Wood_Syngas | E48: Syngas Production | F48: Fluidized Bed Gasifier | H48: Woody biomass gasification to syngas | I48: 2030 | J48: Syngas | K48: Gasification | L48: Wood | M48: Conversion
A49: ConvTech | B49: CH4_Digestion | C49: T_C_Conv_Methane_Digestion_BioWet_CH4 | D49: Methane_Digestion_BioWet_CH4 | E49: Anaerobic Digestion | F49: Anaerobic Digestion plant | H49: Wet biomass anaerobic digestion with gas upgrading | I49: 2030, 2040, 2050 | J49: Methane | K49: Digestion | L49: Waste | M49: Conversion
A50: ConvTech | B50: CH4_Hydrogenation | C50: T_C_Conv_Methane_Hydrogenation_CO2_Ch4 | D50: Methane_Hydrogenation_CO2_Ch4 | E50: Methane Synthesis | F50: Sabatier Reaction unit | H50: Methane synthesis from H2 and CO2 via the thermo catalytic Sabatier reaction. | I50: 2020, 2030, 2040, 2050 | J50: Methane | K50: Hydrogenation | L50: H2, CO2 | M50: Conversion
A51: ConvTech | B51: Syngas_Hydrogenation_CH4 | C51: T_C_Conv_Methane_Hydrogenation_Syngas_CH4 | D51: Methane_Hydrogenation_Syngas_CH4 | E51: Methane Synthesis | F51: Sabatier Reaction unit | H51: Methane synthesis from Syngas via the thermo catalytic CO hydrogenation. | I51: 2020, 2030, 2040, 2050 | J51: Methane | K51: Hydrogenation | L51: CO | M51: Conversion
A52: ConvTech | B52: H2_CO2_Hydrogenation_Methanol | C52: T_C_Conv_Methanol_Hydrogenation_H2_MeOH | D52: Methanol_Hydrogenation_H2_MeOH | E52: Methanol Synthesis | F52: Thermo-catalytic methanol synthesis reactor | H52: Methanol synthesis from CO2 hydrogenation | I52: 2020, 2030, 2040, 2050 | J52: Methanol | K52: Hydrogenation | L52: CO2 | M52: Conversion
A53: ConvTech | B53: Syngas_Hydrogenation_Methanol | C53: T_C_Conv_Methanol_Syngas_MeOH | D53: Methanol_Syngas_MeOH | E53: Methanol Synthesis | F53: Thermo-catalytic methanol synthesis reactor | H53: Methanol synthesis from Syngas via the thermo catalytic CO hydrogenation | I53: 2030, 2040, 2050 | J53: Methanol | K53: Hydrogenation | L53: CO | M53: Conversion
A54: ConvTech | B54: Coupled_Electricity | C54: T_C_NetCoupled_Net_Elec_El47_El13 | D54: Elec_El47_El13 | E54: Eletricity Transmission | F54: Grid | H54: Coupled electricity network between El47 and El13. | I54: 2020, 2050 | J54: Electricity | K54: Grid | L54: Transmission | M54: Transport
A55: ConvTech | B55: BioWet_Pyrolysis_CBio | C55: T_C_Conv_Pyrolysis_BioWet_CBio | D55: Pyrolysis_BioWet_CBio | E55: Carbon black Production | F55: Pyrolyser | H55: Biochar production via pyrolysis of wet biomass. | I55: 2025 | J55: Carbon Black | K55: Pyrolysis | L55: Wet Biomass | M55: Conversion
A56: ConvTech | B56: Methane_Tech_Description | C56: T_C_Conv_Pyrolysis_CH4_CCH4 | D56: Pyrolysis_CH4_CCH4 | E56: Carbon black Production | F56: Pyrolyser | H56: Not in Tech description | I56: 2030 | J56: Carbon Black | K56: Pyrolysis | L56: Methane | M56: Conversion
A57: ConvTech | B57: Wood_Pyrolysis_CBio | C57: T_C_Conv_Pyrolysis_Wood_CBio | D57: Pyrolysis_Wood_CBio | E57: Carbon black Production | F57: Pyrolyser | H57: Biochar production via pyrolysis of wood. | I57: 2025 | J57: Carbon Black | K57: Pyrolysis | L57: Wood | M57: Conversion
A58: ConvTech, SolarTech | B58: PV_Alpine_ETHZ | C58: T_C_Conv_Solar_Pv_Alpin_ETHZ | D58: Solar_Pv_Alpin_ETHZ | E58: Electricity Generation | F58: Photovoltaic Plant | H58: gound-mounted Alpine PV, from ETHZ study in 2024 | I58: 2025, 2030, 2040, 2050 | J58: Electricity | K58: Photovoltaic | L58: Ground-mounted Alpine | M58: Conversion
A59: ConvTech, SolarTech | B59: PV_Alpin | C59: T_C_Conv_Solar_Pv_Alpin_VSE | D59: Solar_Pv_Alpin_VSE | E59: Electricity Generation | F59: Photovoltaic Plant | H59: Alpine PV, from VSE | I59: 2025, 2030, 2040, 2050 | J59: Electricity | K59: Photovoltaic | L59: Alpine | M59: Conversion
A60: ConvTech, SolarTech | B60: PV_Roof_Flat | C60: T_C_Sol_Solar_Pv_Roof_SolFlat | D60: Solar_Pv_Roof_SolFlat | E60: Electricity Generation | F60: Photovoltaic Rooftop | H60: rooftop PV, small scale | I60: 2025, 2030, 2040, 2050 | J60: Electricity | K60: Photovoltaic | L60: Rooftop | M60: Conversion
A61: ConvTech | B61: Ventilation_Loss_Buildings | C61: T_C_Conv_ThBdg_Vent | D61: ThBdg_Vent | E61: Heat Loss | F61: Ventilator | H61: Ventilation heat loss in buildings. | I61: na | J61: Thermal | K61: Ventilation | L61: Building | M61: Conversion
A62: ConvTech | B62: CSW_Thermal | C62: T_C_Conv_Thermal_Csw_ThPhII | D62: Thermal_Csw_ThPhII | E62: Heat Generation | F62: Waste Incineration | H62: Waste-fueled thermal energy generation in power plants. | I62: 2020, 2050 | J62: Thermal | K62: Inceneration | L62: Waste | M62: Conversion
A63: ConvTech | B63: IndustrialHeatPump | C63: T_C_Conv_Thermal_ThAmb_ThHt | D63: Thermal_ThAmb_ThHt | E63: Heat Generation | F63: Heat Extractor | H63: Ambient heat extraction for heating. | I63: 2030, 2040 | J63: Thermal | K63: Extraction | L63: Ambient | M63: Conversion
A64: ConvTech | B64: Oil_Heating_Buildings | C64: T_C_Conv_Thermal_ThermalBdg_C12 | D64: Thermal_ThermalBdg_C12 | E64: Heat Generation | F64: Oil Boiler | H64: Hydrocarbon-fueled heating system for buildings. | I64: 2020, 2050 | J64: Thermal | K64: Boiler | L64: Building | M64: Conversion
A65: ConvTech | B65: CH4_Heating_Buildings | C65: T_C_Conv_Thermal_ThermalBdg_CH4 | D65: Thermal_ThermalBdg_CH4 | E65: Heat Generation | F65: Gas Boiler | H65: Methane-fueled heating system for buildings. | I65: 2020, 2030, 2040, 2050 | J65: Thermal | K65: Boiler | L65: Building | M65: Conversion
A66: ConvTech | B66: Electric_Heating_Buildings | C66: T_C_Conv_Thermal_ThermalBdg_El | D66: Thermal_ThermalBdg_El | E66: Heat Generation | F66: Heat Pump | H66: Electric heating system for buildings. | I66: 2020, 2030, 2040, 2050 | J66: Thermal | K66: Electric heating | L66: Building | M66: Conversion
A67: ConvTech | B67: Electro_Acs | C67: T_C_Conv_Thermal_ThermalBdg_ElBdg_ThSc | D67: Thermal_ThermalBdg_ElBdg_ThSc | E67: Heat Generation | F67: Heat Pump | H67: Electric heating system for buildings with thermal storage. | I67: 2020, 2030, 2040, 2050 | J67: Thermal | K67: Electric heating | L67: Building | M67: Conversion
A68: ConvTech | B68: Heatpump_Residential | C68: T_C_Conv_Thermal_ThermalBdg_Hp | D68: Thermal_ThermalBdg_Hp | E68: Heat Generation | F68: Heat Pump | H68: Generic heat pump for residential heating, fixed COP 4 | I68: 2020, 2030, 2040, 2050 | J68: Thermal | K68: Electric heating | L68: Building | M68: Conversion
A69: ConvTech | B69: Heatpump_Coupled_Buildings | C69: T_C_Coupled_Thermal_ThermalBdg_HpSc | D69: Thermal_ThermalBdg_HpSc | E69: Heat Generation | F69: Heat Pump | H69: Coupled heat pump system for buildings. | I69: 2020, 2050 | J69: Thermal | K69: Electric heating | L69: Building | M69: Conversion
... A73: ConvTech | B73: Electric_Heating_ThermalPowerPlants | C73: T_C_Conv_Thermal_ThermalPhII_El | D73: Thermal_ThermalPhII_El | E73: Heat Generation | F73: Heat Pump | H73: Electric heating system for thermal power plants. | I73: 2020, 2030, 2040, 2050 | J73: Thermal | K73: Electric heating | L73: Thermal Power Plants | M73: Conversion
A74: ConvTech | B74: H2_Heating_ThermalPowerPlants | C74: T_C_Conv_Thermal_ThermalPhII_H2 | D74: Thermal_ThermalPhII_H2 | E74: Heat Generation | F74: Gas Boiler | H74: Hydrogen-fueled heating system for thermal power plants. | I74: 2050 | J74: Thermal | K74: Boiler | L74: Thermal Power Plants | M74: Conversion
A75: ConvTech | B75: Wood_Heating_ThermalPowerPlants | C75: T_C_Conv_Thermal_ThermalPhII_Wood | D75: Thermal_ThermalPhII_Wood | E75: Heat Generation | F75: Furnace | H75: Wood-fueled heating system for thermal power plants. | I75: 2020, 2030, 2040, 2050 | J75: Thermal | K75: Furnace | L75: Thermal Power Plants | M75: Conversion
A76: ConvTech | B76: Thermal_Network_DistrictHeating-Buildings | C76: T_C_Net_Thermal_ThHt_ThBdg | D76: Thermal_ThHt_ThBdg | E76: Heat Transport | F76: District Heating Network | H76: Thermal network connection between district heating and buildings. | I76: 2020 | J76: Thermal | K76: Grid | L76: District Heating | M76: Transport
A77: ConvTech | B77: IndustrialHeatPump | C77: T_C_Conv_Thermal_ThLt_ThHt | D77: Thermal_ThLt_ThHt | E77: Heat Generation | F77: Heat Extractor | H77: Low-temperature heat upgrade for district heating. | I77: 2020, 2030, 2040, 2050 | J77: Thermal | K77: Extraction | L77: District Heating | M77: Conversion
A78: ConvTech | B78: Thermal_Network_HeatSource_DistrictHeating | C78: T_C_Net_Thermal_ThPhII_ThHt | D78: Thermal_ThPhII_ThHt | E78: Heat Transport | F78: District Heating Network | H78: Thermal network connection between heat sources and district heating. | I78: 2020 | J78: Thermal | K78: Grid | L78: District Heating | M78: Transport
A79: ConvTech | B79: Ventilation_Loss_HighTemp_HeatNodes | C79: T_C_Conv_ThHt_Vent | D79: ThHt_Vent | E79: Heat Loss | F79: Ventilator | H79: Ventilation heat loss at high-temperature heat nodes. | I79: na | J79: Thermal | K79: Ventilation | L79: Losses | M79: Conversion
A80: ConvTech | B80: Ventilation_Loss_LowTemp_HeatNodes | C80: T_C_Conv_ThLt_Vent | D80: ThLt_Vent | E80: Heat Loss | F80: Ventilator | H80: Ventilation heat loss at low-temperature heat nodes. | I80: na | J80: Thermal | K80: Ventilation | L80: Losses | M80: Conversion
A81: ConvTech | B81: Ventilation_Loss_ThermalPowerPlants | C81: T_C_Conv_ThPh_Vent | D81: ThPh_Vent | E81: Heat Loss | F81: Ventilator | H81: Ventilation heat loss at thermal power plants. | I81: na | J81: Thermal | K81: Ventilation | L81: Losses | M81: Conversion
A82: ConvTech | B82: Wind_Turbine | C82: T_C_Conv_Wind_Turbine_Generic | D82: Wind_Turbine_Generic | E82: Electricity Generation | F82: Wind Turbine | H82: Generic wind turbine electricity generation. | I82: 2020, 2030, 2040, 2050 | J82: Electricity | K82: Wind | L82: General | M82: Conversion
A83: StorTech | B83: Elec_Battery_ElBdg | C83: T_S_Stor_Elec_Battery_ElBdg | E83: Storage | F83: Battery | H83: Electric battery storage at home, 2025 | I83: 2025, 2030, 2040, 2050 | J83: Electricity | M83: Storage
A84: StorTech | B84: Elec_Battery_El47 | C84: T_S_Stor_Elec_Battery_El47 | E84: Storage | F84: Battery | H84: Electric battery storage at the grid, 2020 | I84: 2020, 2030, 2040, 2050 | J84: Electricity | M84: Storage
A85: StorTech | B85: Hydro_HydroS_Reservoir | C85: T_S_Stor_Hydro_HydroS_Reservoir | E85: Storage | F85: Reservoir | H85: Hydro reservoir, without pump and generator | I85: na | J85: Electricity | K85: Hydro | M85: Storage
A86: StorTech | B86: Hydro_HydroPumped_Reservoir | C86: T_S_Stor_Hydro_HydroPumped_Reservoir | E86: Storage | F86: Reservoir | H86: Pumped hydro reservoir, without pump and generator | I86: na | J86: Electricity | K86: Hydro | M86: Storage
A87: StorTech | B87: Thermal_ThermalBdg_ThDhw | C87: T_S_Stor_Thermal_ThermalBdg_ThDhw | E87: Storage | H87: Hot water storage tank at home | I87: na | J87: Thermal | M87: Storage
A88: StorTech | B88: Thermal_Generic_ThDh | C88: T_S_Stor_Thermal_Generic_ThDh | E88: Storage | H88: Thermal storage for district heating, seasonal storage | I88: na | J88: Thermal | M88: Storage
A89: StorTech | B89: Thermal_Generic_ThHt | C89: T_S_Stor_Thermal_Generic_ThHt | E89: Storage | I89: na | J89: Thermal | M89: Storage
A90: StorTech | B90: Hydrogen_Tank_Generic | C90: T_S_Stor_Hydrogen_Tank_Generic | E90: Storage | F90: Tank | I90: 2030 | J90: Hydrogen | M90: Storage
A91: StorTech | B91: Methane_Tank_Ch4 | C91: T_S_Stor_Methane_Tank_Ch4 | E91: Storage | F91: Tank | I91: na | J91: Methane | M91: Storage
A92: StorTech | B92: Methane_Grid_Ch4 | C92: T_S_Stor_Methane_Grid_Ch4 | E92: Storage | I92: na | J92: Methane | M92: Storage
A93: StorTech | B93: Methane_Ug_Ch4 | C93: T_S_Stor_Methane_Ug_Ch4 | E93: Storage | I93: 2030 | J93: Methane | M93: Storage
A94: StorTech | B94: CarbonDioxide_Tank | C94: T_S_CarbonDioxide_Tank | E94: Storage | F94: Tank | I94: na | J94: Carbo Dioxide | M94: Storage
A95: StorTech | B95: CarbonMonoxide_Tank | C95: T_S_CarbonMonoxide_Tank | E95: Storage | F95: Tank | I95: na | J95: Carbon Monoxide | M95: Storage
A96: StorTech | B96: C8_Hydrocarbons_Tank | C96: T_S_C8_Hydrocarbons_Tank | E96: Storage | F96: Tank | I96: na | J96: Hydrocarbons | M96: Storage
A97: StorTech | B97: C12_Hydrocarbons_Tank | C97: T_S_C12_Hydrocarbons_Tank | E97: Storage | F97: Tank | I97: na | J97: Hydrocarbons | M97: Storage
A98: StorTech | B98: NH3_Tank_Generic | C98: T_S_Stor_NH3_Tank_Generic | E98: Storage | F98: Tank | H98: Tank storage for ammonia | I98: na | J98: Ammonia | M98: Storage

Sheet LCA ID
A1: LCA Classification
A2: [ehubX Tech ID] | B2: [LCA ID] | C2: [Reference product] | D2: [LCA unit] | E2: [Location] | J2: [LCA Scenario]
A3: ehubX tech ID | B3: lca_id | C3: ref_product | D3: lca_unit | E3: Location | F3: SSP2-NDC_2025 | G3: SSP2-NDC_2030 | H3: SSP2-NDC_2040 | I3: SSP2-NDC_2050 | J3: SSP2-PkBudg1000_2025 | K3: SSP2-PkBudg1000_2030 | L3: SSP2-PkBudg1000_2040 | M3: SSP2-PkBudg1000_2050
A4: T_C_CarbonMonoxide_ElecRR_CO2_CO | B4: electrolyzer production, 1MWe, SOEC, Stack | C4: electrolyzer, 1MWe, SOEC, Stack | D4: kgCO2eq/kW | E4: RER | F4: 71.799597 | G4: 49.732848 | H4: 34.110871 | I4: 25.663843 | J4: 71.796199 | K4: 47.918464 | L4: 29.577507 | M4: 21.820759
A5: T_C_Conv_Ammonia_CCGT | B5: market for gas power plant, combined cycle, 400MW electrical | C5: gas power plant, combined cycle, 400MW electrical | D5: kgCO2eq/kW | E5: GLO | F5: 150.31334 | G5: 134.0643 | H5: 104.15643 | I5: 81.927221 | J5: 150.30541 | K5: 133.59069 | L5: 99.517999 | M5: 72.892403
A6: T_C_Conv_Ammonia_HaberBosch | B6: ammonia synthesis catalyst production | C6: ammonia synthesis catalyst | D6: kgCO2eq/kg | E6: GLO | F6: 0.000127 | G6: 9e-05 | H6: 4.2e-05 | I6: 3.1e-05 | J6: 0.000127 | K6: 9.3e-05 | L6: 4.1e-05 | M6: 2.7e-05
A7: T_C_Conv_Ammonia_OCGT | B7: micro gas turbine production, 100kW electrical | C7: micro gas turbine, 100kW electrical | D7: kgCO2eq/kW | E7: CH | F7: 147.72442 | G7: 122.83063 | H7: 92.419966 | I7: 78.201541 | J7: 147.71588 | K7: 121.58915 | L7: 85.641046 | M7: 62.633809
A8: T_C_Conv_CarbonCapture_Amine | B8: market for monoethanolamine | C8: monoethanolamine | D8: kgCO2eq/kg | E8: GLO | F8: 0.004459 | G8: 0.004009 | H8: 0.00342 | I8: 0.00316 | J8: 0.004459 | K8: 0.004016 | L8: 0.003404 | M8: 0.003121
A9: T_C_Conv_CarbonCapture_DacAbs | B9: direct air capture system, solvent-based, 1MtCO2 | C9: direct air capture system | D9: kgCO2eq/kg | E9: RER | F9: 0.007578 | G9: 0.006763 | H9: 0.005611 | I9: 0.004653 | J9: 0.007577 | K9: 0.006763 | L9: 0.005468 | M9: 0.004061
A10: T_C_Conv_CarbonCapture_DacAds | B10: direct air capture system, sorbent-based, 100ktCO2 | C10: direct air capture system | D10: kgCO2eq/kg | E10: RER | F10: 0.005743 | G10: 0.005003 | H10: 0.003832 | I10: 0.003016 | J10: 0.005743 | K10: 0.00498 | L10: 0.003655 | M10: 0.002608
A11: T_C_Conv_CarbonCapture_Hpc | B11: potassium carbonate production, from potassium hydroxide | C11: potassium carbonate | D11: kgCO2eq/kg | E11: GLO | F11: 0.001517 | G11: 0.001096 | H11: 0.000544 | I11: 0.000348 | J11: 0.001517 | K11: 0.001113 | L11: 0.00049 | M11: 0.000277
A12: T_C_Conv_CarbonMonoxide_Rwgs_H2_CO | B12: RWGS tank construction | C12: RWGS tank construction | D12: kgCO2eq/kg | E12: GLO | F12: 0.006293 | G12: 0.005231 | H12: 0.003517 | I12: 0.002569 | J12: 0.006293 | K12: 0.005251 | L12: 0.00314 | M12: 0.002094
A13: T_C_Conv_CatalyticHydropyrolysis_syngas | B13: chemical factory construction, organics | C13: chemical factory, organics | D13: kgCO2eq/kg | E13: RER | F13: 0.040275 | G13: 0.031371 | H13: 0.022305 | I13: 0.018086 | J13: 0.040271 | K13: 0.030886 | L13: 0.020787 | M13: 0.01612
A14: T_C_Conv_Coelectrolysis | B14: electrolyzer production, 1MWe, SOEC, BoP / Stack | C14: electrolyzer, 1MWe, SOEC, Stack | D14: kgCO2eq/kW | E14: RER | F14: 285.98691 | G14: 211.77497 | H14: 146.96989 | I14: 112.83659 | J14: 285.97094 | K14: 206.90486 | L14: 130.78391 | M14: 95.18833
A15: T_C_Conv_EL3_RWG | B15: RWGS tank construction | C15: RWGS tank construction | D15: kgCO2eq/kg | E15: GLO | F15: 0.006293 | G15: 0.005231 | H15: 0.003517 | I15: 0.002569 | J15: 0.006293 | K15: 0.005251 | L15: 0.00314 | M15: 0.002094
... A76: T_C_Sol_Solar_Pv_Roof_SolFlat | B76: photovoltaic flat-roof installation, 3kWp, multi-Si, on roof | C76: photovoltaic flat-roof installation, 3kWp, multi-Si, on roof | D76: kgCO2eq/kW | E76: CH | F76: 1273.5988 | G76: 938.12588 | H76: 529.67294 | I76: 400.06301 | J76: 1273.5568 | K76: 944.30206 | L76: 508.46186 | M76: 376.99505
A77: T_C_Conv_Pyrolysis_BioWet_CBio
A78: T_C_Conv_Pyrolysis_Wood_CBio
A79: T_C_Net_Elec_El47_ElRest_2020

Sheet Reference ID
A1: Reference ID | B1: Reference Description | C1: Reference Type | D1: DOI or Link | E1: Access Date | F1: PDF in server
A2: source_id | D2: doi_or_url
A3: report_VSE_2022 | B3: VSE Energiezukunft 2050, Studie 2022 | C3: BibTex | D3: https://www.strom.ch/de/energiezukunft-2050/download | E3: 45175 | F3: TRUE
A4: assumption_Empa_2022 | B4: Expert Assumption | C4: Assumption | D4: na | F4: TRUE
A5: paper_mutschler_2018 | C5: DOI | D5: https://doi.org/10.1016/j.jcat.2018.08.002 | F5: TRUE
A6: assumption_reFuelWP3_2025 | B6: Expert Assumption | C6: Assumption | D6: na | F6: TRUE
A7: report_VSE_2025 | B7: VSE Energiezukunft 2050, Update 2025 | C7: BibTex | D7: https://www.strom.ch/de/energiezukunft-2050/download | E7: 45803 | F7: TRUE
A8: paper_müller_PowerX_2025 | B8: The costs of future energy technologies: A comprehensive review of power-to-X processes | C8: DOI | D8: https://doi.org/10.1016/j.jcou.2025.103019 | F8: TRUE
A9: assumption_Empa_2025 | B9: Expert assumptions and calculations by Empa | C9: Assumption | D9: na | F9: TRUE
A10: paper_alpinePV_2024 | B10: ETHZ paper on Alpine PV cost and financial viability | C10: DOI | D10: https://doi.org/10.1016/j.apenergy.2024.124019 | F10: TRUE
A11: paper_PVcostProjection_2025 | B11: review the cost projection of PV, wind, battery | C11: DOI | D11: https://doi.org/10.1016/j.apenergy.2025.125856 | F11: TRUE
A12: assumption_PVcostProjection | B12: 4/3/2% cost reduction per year in 2030/2040/2050, see ref_id "paper_PVcostProjection_2025" | D12: na | F12: TRUE
A13: assumption_Empa_PV_OM | B13: currently FOM is 15-25 CHF/kW.year, may reduce to 10 in 2050 | D13: na | F13: TRUE
A14: web_BatteryCH_2023 | B14: article about market price of home batteries in CH, in 2023 | C14: BibTex | D14: https://alpvolt.com/en/news/solar-batteries-in-switzerland | F14: TRUE
A15: assumption_Empa_battery_capex_2025 | B15: assumption based on various info | D15: na | F15: TRUE
A16: web_Battery_OM_2025 | B16: FOM costs are estimated at 2.5% of the capital costs | C16: BibTex | D16: https://atb.nrel.gov/electricity/2024/utility-scale_battery_storage | F16: TRUE
A17: Allgoewer_2024 | B17: Paper by ETH from PATHFNDR | C17: DOI | D17: https://doi.org/10.1021/acs.iecr.4c01287 | F17: TRUE
A18: Rheintal_2025 | B18: Rheintal paper of Empa, submitted 2025 | C18: DOI | D18: https://dx.doi.org/10.2139/ssrn.5291581 | F18: TRUE
A19: book_hydropower_2020 | B19: Future Energy (Third Edition) | C19: DOI | D19: https://doi.org/10.1016/B978-0-08-102886-5.00015-3 | F19: TRUE
A20: report_danish_energy_2025 | B20: Report from Danish Energy Agency | D20: https://ens.dk/technologydata | E20: 45919 | F20: TRUE
A21: assumption_Empa_danish_energy_OE | B21: Overall Efficiency estimatin of biogas plants: Average(Efficiency values for different input carrieres) | D21: na | F21: TRUE
A22: paper_CCGT_2024 | B22: Modeling combined-cycle power plants in a detailed electricity market | C22: DOI | D22: https://doi.org/10.1016/j.energy.2024.131246 | F22: TRUE
A23: paper_CCGT+CCS_2016 | B23: Off-design point modelling of a 420 MW CCGT power plant integrated with an amine-based post-combustion CO2 capture and compression process | C23: DOI | D23: https://doi.org/10.1016/j.apenergy.2016.06.087 | F23: TRUE
A24: report_global_hydrogen_review_2024 | B24: he Global Hydrogen Review 2024 systematically monitors the global hydrogen sector, reporting that demand reached 97 Mt in 2023—mostly supplied by unabated fossil fuels—despite accelerating policy action, growing low-emissions project announcements, and almost USD 100 billion in public funding allocated to support the clean energy transition. | D24: https://iea.blob.core.windows.net/assets/89c1e382-dc59-46ca-aa47-9f7d41531ab5/GlobalHydrogenReview2024.pdf | F24: TRUE
A25: report_jrc_2021 | D25: https://doi.org/10.2760/527879 | F25: TRUE
A26: report_power_to_ammonia_2018 | B26: Power-to-ammonia in future North European 100 % renewable power and heat system | C26: DOI | D26: https://doi.org/10.1016/j.ijhydene.2018.06.121 | F26: TRUE
A27: conversion_parametrization | B27: Calculating Input Output Ratios of Reactions | D27: na
A28: paper_e-fuel production | B28: Forging a sustainable sky: Unveiling the pillars of aviation e-fuel production for carbon emission circularity | C28: DOI | D28: https://doi.org/10.1016/j.isci.2024.109154
A29: paper_wood to syngas | B29: Cutting-edge biomass gasification technologies for renewable energy generation and achieving net zero emissions | C29: DOI | D29: https://doi.org/10.1016/j.enconman.2024.119213
A30: report_wood to hydrogen | B30: Biomass gasification for hydrogen production | C30: URL | D30: https://www.ieabioenergy.com/wp-content/uploads/2025/03/IEA-Bioenergy_T33_Bio-H2_Final_v2.pdf
A31: paper_Msw to syngas | B31: Municipal Solid Waste Gasification: Technologies, Process Parameters, and Sustainable Valorization of By-Products in a Circular Economy | C31: DOI | D31: https://doi.org/10.3390/su17156704
A32: paper_RWGS | B32: Technology Readiness and Emerging Prospects of CoupledCatalytic Reactions for Sustainable Chemical Value Chains | C32: DOI | D32: https://doi.org/10.1002/cssc.202400865
A33: source_shares | B33: Temporary reference ID for input and output shares | D33: na
A34: paper_biogas | B34: Biogas-to-biomethane upgrading: A comparative review and assessment in a life cycle perspective | C34: DOI | D34: https://doi.org/10.1016/j.rser.2020.110588
A35: parameters_lca | B35: LCA Parameters
A36: assumption_
A37: Paper_Postcom_2021 | B37: Postcombustion CO2 Capture: A Comparative Techno-Economic Assessment of Three Technologies Using a Solvent, an Adsorbent, and a Membrane | D37: Postcombustion CO2 Capture: A Comparative Techno-Economic Assessment of Three Technologies Using a Solvent, an Adsorbent, and a Membrane | ACS Engineering Au
A38: AECOM_2022 | B38: AECOM 2022: Next Generation Carbon Capture Technology Technoeconomic Analysis Work Package 6
A39: biochar_jcp_2025 | B39: Financial feasibility of biochar production: A comparative analysis of business scenarios | C39: DOI | D39: https://doi.org/10.1016/j.jclepro.2025.147167
A40: EP2050+Exkurs | B40: Energieperspektiven 2050+ Exkurs Negativemissionstechnologien und CCS Potenziale, Kosten und Einsatz | C40: Link | D40: https://www.bfe.admin.ch/bfe/en/home/politik/energieperspektiven-2050-plus.exturl.html/aHR0cHM6Ly9wdWJkYi5iZmUuYWRtaW4uY2gvZGUvcHVibGljYX/Rpb24vZG93bmxvYWQvMTA2MjA=.html
A41: report_ASSET_2018 | B41: ASSET: Technology pathways in decarbonisation scenarios (July 2018) | C41: Link | D41: https://build-up.ec.europa.eu/sites/default/files/content/2018_06_27_technology_pathways_-_finalreportmain2.pdf
A42: report_gas_compression_2014 | B42: Energieaufwand für Gaskomprimierung (November 2014) | C42: Link | D42: https://www.ost.ch/fileadmin/dateiliste/3_forschung_dienstleistung/technik/3.7.1_erneuerbare_energien_und_umwelttechnik/iet/power-to-x/06_energie_fuer_gaskomprimierung.pdf
A43: report_gas_storage_2017 | B43: Speicherkapazität von Erdgas in der Schweiz (24 Feb 2017) | D43: cannot find the link of the report
A44: report_danish_energy_2026 | B44: Report from Danish Energy Agency

Sheet SolarTech
A1: Review | E1: Classification | N1: Attributes | T1: Conversion Parameterization | AG1: Economic Parameterization | AO1: Uncertainty | AQ1: CO2 emissions | AU1: References
A2: [boolean] | B2: [Author] | C2: [Author] | D2: [boolean] | E2: [ehubX Tech ID] | F2: [Ontology IRI] | G2: [ProcessType] | H2: [Description] | I2: [MainSector] | J2: [MainCategory] | K2: [CategorySpec] | L2: [TechType] | M2: kW | N2: [Year] | O2: [Location] | P2: [Currency] | Q2: Year | R2: [TechMaturity] | S2: [TechBoundary] | T2: [boolean] | U2: [float] | V2: [float] | W2: [list of Carriers] | X2: [Carrier] | Y2: [list of floats, comma separated] | Z2: [list of units in kWh and kg] | AA2: [list of Carriers] | AB2: [Carrier] | AC2: [list of float, comma separated] | AD2: [list of units, comma separated] | AE2: kW | AF2: [float] | AG2: Years | AH2: Currency | AI2: Currency/kW | AJ2: Currency/year | AK2: % | AL2: Currency/kW/Year | AM2: Currency/kWh/Year | AN2: [float] | AO2: [boolean] | AP2: [str] | AQ2: [LCA ID] | AR2: [LCA Unit] | AS2: [Embedded Carbon] | AT2: [LCA Scenario] | AU2: [dict of ReferenceID]
A3: Review done | B3: 1st Review responsible | C3: 2nd Review responsible | D3: Review approved (Robin) | E3: ehubX Tech ID | F3: Tech Ontology IRI | G3: Process Type | H3: Description | I3: Main Sector | J3: Main Category | K3: Category Specification | L3: Tech Type | M3: Reference Unit Size | N3: Technology Year | O3: Cost Base | P3: Currency | Q3: Data Reference Year | R3: Technology Maturity Evaluation | S3: Technology Boundary | T3: Tech drawing added? | U3: Overall Efficiency | V3: Input, Output for Overall Efficiency | W3: Input Carriers | X3: Main Input Carrier | Y3: Input Shares | Z3: Input Units | AA3: Output Carriers | AB3: Main Output Carrier | AC3: Output Shares | AD3: Output Unit | AE3: Minimum Installation | AF3: Maximum Curtailment Fraction | AG3: Economic Lifetime | AH3: CAPEX One Time | AI3: CAPEX Power Capacity | AJ3: OPEX One Time | AK3: OPEX Power Capacity as Percentage of CAPEX | AL3: OPEX Power Capacity | AM3: OPEX Energy | AN3: Discount Rate | AO3: Value Range Check | AP3: Uncertainty Rating | AQ3: LCA ID | AR3: LCA Unit | AS3: Embedded Carbon | AT3: LCA Scenario | AU3: References
A4: TRUE | B4: Barton | C4: Gianfranco | D4: FALSE | E4: T_C_Sol_Solar_Pv_Roof_2025_SolFlat | H4: rooftop PV, small scale, in 2025 | I4: Electricity | J4: New Renewable | K4: PV | L4: Conversion | N4: 2025 | O4: CH | P4: CHF | Q4: 2022 | R4: Mature | T4: FALSE | V4: 1 | W4: SolFlat | Y4: 1 | AA4: ElBdg | AB4: ElBdg | AC4: 0.21 | AE4: 0 | AF4: 1 | AG4: 25 | AH4: 0 | AI4: 2647 | AJ4: 0 | AK4: 0.015 | AL4: 41 | AM4: 0 | AN4: 0.05 | AO4: FALSE | AU4: "CAPEX", "Opex Power Capacity": report_VSE_2025; "Output Shares": paper_alpinePV_2024; | AV4: Check source
A5: TRUE | B5: Barton | C5: Gianfranco | D5: FALSE | E5: T_C_Sol_Solar_Pv_Roof_2030_SolFlat | H5: rooftop PV, small scale, in 2030 | I5: Electricity | J5: New Renewable | K5: PV | L5: Conversion | N5: 2030 | O5: CH | P5: CHF | Q5: 2022 | R5: Mature | T5: FALSE | V5: 1 | W5: SolFlat | Y5: 1 | AA5: ElBdg | AB5: ElBdg | AC5: 0.23 | AE5: 0 | AF5: 1 | AG5: 25 | AH5: 0 | AI5: 1880 | AJ5: 0 | AK5: 0.0175 | AL5: =AI5*AK5 -> 32.9 | AM5: 0 | AN5: 0.05 | AO5: FALSE | AU5: "CAPEX", "Opex Power Capacity": report_VSE_2025; "Output Shares": paper_alpinePV_2024;
A6: TRUE | B6: Barton | C6: Gianfranco | D6: FALSE | E6: T_C_Sol_Solar_Pv_Roof_2040_SolFlat | H6: rooftop PV, small scale, in 2040 | I6: Electricity | J6: New Renewable | K6: PV | L6: Conversion | N6: 2040 | O6: CH | P6: CHF | Q6: 2022 | R6: Mature | T6: FALSE | V6: 1 | W6: SolFlat | Y6: 1 | AA6: ElBdg | AB6: ElBdg | AC6: 0.25 | AE6: 0 | AF6: 1 | AG6: 25 | AH6: 0 | AI6: 1400 | AJ6: 0 | AK6: 0.0175 | AL6: =AI6*AK6 -> 24.5 | AM6: 0 | AN6: 0.05 | AO6: FALSE | AU6: "CAPEX", "Opex Power Capacity": report_VSE_2025; "Output Shares": paper_alpinePV_2024;
A7: TRUE | B7: Barton | C7: Gianfranco | D7: FALSE | E7: T_C_Sol_Solar_Pv_Roof_2050_SolFlat | H7: rooftop PV, small scale, in 2050 | I7: Electricity | J7: New Renewable | K7: PV | L7: Conversion | N7: 2050 | O7: CH | P7: CHF | Q7: 2022 | R7: Mature | T7: FALSE | V7: 1 | W7: SolFlat | Y7: 1 | AA7: ElBdg | AB7: ElBdg | AC7: 0.27 | AE7: 0 | AF7: 1 | AG7: 25 | AH7: 0 | AI7: 1020 | AJ7: 0 | AK7: 0.02 | AL7: 21 | AM7: 0 | AN7: 0.05 | AO7: FALSE | AU7: "CAPEX", "Opex Power Capacity": report_VSE_2025; "Output Shares": paper_alpinePV_2024;
A8: TRUE | B8: Barton | C8: Gianfranco | D8: FALSE | E8: T_C_Conv_Solar_Pv_Alpin_VSE_2030 | H8: Alpine PV, from VSE, 2030 | I8: Electricity | J8: New Renewable | K8: PV | L8: Conversion | N8: 2030 | O8: CH | P8: CHF | Q8: 2022 | R8: Mature | S8: Complete installation | T8: FALSE | W8: ElPvAlpin | X8: na | Y8: 1 | AA8: El13 | AB8: na | AC8: 1 | AD8: kWh | AE8: 0 | AG8: 25 | AH8: 0 | AI8: 2300 | AJ8: 0 | AL8: 46 | AM8: 0 | AO8: FALSE | AQ8: photovoltaic plant construction, 570kWp, multi-Si, on open ground | AR8: kW | AS8: 989.0563 | AT8: SSP2-PkBudg1150_2030 | AU8: "all": report_VSE_2022
A9: TRUE | B9: Barton | C9: Gianfranco | D9: FALSE | E9: T_C_Conv_Solar_Pv_Alpin_VSE_2040 | H9: Alpine PV, from VSE, 2030 | I9: Electricity | J9: New Renewable | K9: PV | L9: Conversion | N9: 2040 | O9: CH | P9: CHF | Q9: 2022 | R9: Mature | S9: Complete installation | T9: FALSE | W9: ElPvAlpin | X9: na | Y9: 1 | AA9: El13 | AB9: na | AC9: 1 | AD9: kWh | AE9: 0 | AG9: 25 | AH9: 0 | AI9: 2000 | AJ9: 0 | AL9: 40 | AM9: 0 | AO9: FALSE | AQ9: photovoltaic plant construction, 570kWp, multi-Si, on open ground | AR9: kW | AS9: 574.01378 | AT9: SSP2-PkBudg1150_2040 | AU9: "all": report_VSE_2022
A10: TRUE | B10: Barton | C10: Gianfranco | D10: FALSE | E10: T_C_Conv_Solar_Pv_Alpin_VSE_2050 | H10: Alpine PV, from VSE, 2030 | I10: Electricity | J10: New Renewable | K10: PV | L10: Conversion | N10: 2050 | O10: CH | P10: CHF | Q10: 2022 | R10: Mature | S10: Complete installation | T10: FALSE | W10: ElPvAlpin | X10: na | Y10: 1 | AA10: El13 | AB10: na | AC10: 1 | AD10: kWh | AE10: 0 | AG10: 25 | AH10: 0 | AI10: 1800 | AJ10: 0 | AL10: 36 | AM10: 0 | AO10: FALSE | AQ10: photovoltaic plant construction, 570kWp, multi-Si, on open ground | AR10: kW | AS10: 483.62623 | AT10: SSP2-PkBudg1150_2050 | AU10: "all": report_VSE_2022
A11: TRUE | B11: Barton | C11: Gianfranco | D11: FALSE | E11: T_C_Conv_Solar_Pv_Alpin_ETHZ_2024 | H11: gound-mounted Alpine PV, from ETHZ study in 2024 | I11: Electricity | J11: New Renewable | K11: PV | L11: Conversion | N11: 2024 | O11: CH | P11: EUR | Q11: 2024 | R11: Mature | S11: Complete installation | T11: FALSE | W11: ElPvAlpin | X11: na | Y11: 1 | AA11: El13 | AB11: na | AC11: 0.21 | AD11: kWh | AE11: 0 | AG11: 25 | AH11: 0 | AI11: =3207 -> 3207 | AJ11: 0 | AL11: 20 | AM11: 0 | AO11: FALSE | AU11: "CAPEX": paper_alpinePV_2024; "Opex Power Capacity": assumption_Empa_PV_OM;
A12: TRUE | B12: Barton | C12: Gianfranco | D12: FALSE | E12: T_C_Conv_Solar_Pv_Alpin_ETHZ_2030 | H12: gound-mounted Alpine PV, from ETHZ study in 2024, project to 2030 | I12: Electricity | J12: New Renewable | K12: PV | L12: Conversion | N12: 2030 | O12: CH | P12: EUR | Q12: 2024 | R12: Mature | S12: Complete installation | T12: FALSE | W12: ElPvAlpin | X12: na | Y12: 1 | AA12: El13 | AB12: na | AC12: 0.23 | AD12: kWh | AE12: 0 | AG12: 25 | AH12: 0 | AI12: =AI11*(1-0.04)^5 -> 2614.9002 | AJ12: 0 | AL12: 20 | AM12: 0 | AO12: FALSE | AU12: "CAPEX": assumption_PVcostProjection; "Opex Power Capacity": assumption_Empa_PV_OM;
A13: TRUE | B13: Barton | C13: Gianfranco | D13: FALSE | E13: T_C_Conv_Solar_Pv_Alpin_ETHZ_2040 | H13: gound-mounted Alpine PV, from ETHZ study in 2024, project to 2040 | I13: Electricity | J13: New Renewable | K13: PV | L13: Conversion | N13: 2040 | O13: CH | P13: EUR | Q13: 2024 | R13: Mature | S13: Complete installation | T13: FALSE | W13: ElPvAlpin | X13: na | Y13: 1 | AA13: El13 | AB13: na | AC13: 0.25 | AD13: kWh | AE13: 0 | AG13: 25 | AH13: 0 | AI13: =AI12*(1-0.03)^10 -> 1928.2905 | AJ13: 0 | AL13: 15 | AM13: 0 | AO13: FALSE | AU13: "CAPEX": assumption_PVcostProjection; "Opex Power Capacity": assumption_Empa_PV_OM;
A14: TRUE | B14: Barton | C14: Gianfranco | D14: FALSE | E14: T_C_Conv_Solar_Pv_Alpin_ETHZ_2050 | H14: gound-mounted Alpine PV, from ETHZ study in 2024, project to 2050 | I14: Electricity | J14: New Renewable | K14: PV | L14: Conversion | N14: 2050 | O14: CH | P14: EUR | Q14: 2024 | R14: Mature | S14: Complete installation | T14: FALSE | W14: ElPvAlpin | X14: na | Y14: 1 | AA14: El13 | AB14: na | AC14: 0.27 | AD14: kWh | AE14: 0 | AG14: 25 | AH14: 0 | AI14: =AI13*(1-0.02)^10 -> 1575.5538 | AJ14: 0 | AL14: 10 | AM14: 0 | AO14: FALSE | AU14: "CAPEX": assumption_PVcostProjection; "Opex Power Capacity": assumption_Empa_PV_OM;

Sheet ConvTech
A1: Review | F1: Classification | Q1: Attributes | Y1: Simplified Conversion Efficiency | AA1: Conversion Parameterization | AR1: Economic Parameterization | AZ1: Uncertainty | BB1: CO2 emissions | BF1: Mass Flows | BH1: Balance Summary | BK1: Reference | BL1: Include in Datastructures | BM1: Reference Check
A2: [boolean] | B2: [str] | C2: [str] | D2: [boolean] | E2: [boolean] | F2: [ehubX Tech ID] | G2: [Datapaper Tech ID] | H2: [Ontology IRI] | I2: [ProcessType] | J2: [str] | K2: [str] | L2: [MainSector] | M2: [MainCategory] | N2: [CategorySpec] | O2: [TechType] | P2: [MWh/h] or [t/h] | Q2: [Year] | R2: [Location] | S2: [Currency] | T2: [Year] | U2: [TRL 1-9] | V2: [TechMaturity] | W2: [TechBoundary] | X2: [boolean] | Y2: [0-1] | Z2: [Input Carrier, Output Carrier] | AA2: [list of Carriers] | AB2: [Carrier] | AC2: [list of floats, comma separated] | AD2: [list of units in kWh and kg] | AE2: [list of float, comma separated] | AF2: [list of units, comma separated] | AG2: [list of Carriers] | AH2: [list of Carriers] | AI2: [Carrier] | AJ2: [list of float, comma separated] | AK2: [list of float, comma separated] | AL2: [list of units, comma separated] | AM2: [list of float, comma separated] | AN2: [list of units, comma separated] | AO2: [0-1] | AP2: °C | AQ2: kW, kg/hr | AR2: Years | AS2: Currency | AT2: Currency/OutputUnit/Hour | AU2: Currency | AV2: % | AW2: Currency/OutputUnit/Year. Excl. fuels! | AX2: Currency/kWh or Currency/kg | AY2: [float] | AZ2: [boolean] | BA2: [UncertaintyLevel] | BB2: [lca_id] | BC2: [unit] | BD2: [kgCO2-eq/lca_unit] | BE2: [LCA Scenario] | BF2: [list of float, comma separated] | BG2: [list of float, comma separated] | BK2: [dict of ReferenceID] | BL2: [boolean] | BP2: CAPEX/OPEX VSE 2025 and difference from tabulated | BT2: CAPEX/OPEX VSE 2022 and difference from tabulated
A3: Review done | B3: 1st Review responsible | C3: 2nd Review responsible | D3: Review approved (Arash) | E3: Review approved (Robin) | F3: ehubX Tech ID | G3: Datapaper Tech ID | H3: Tech Ontology IRI | I3: Process Type | J3: Description | K3: Unit Operation | L3: Main Sector | M3: Main Category | N3: Category Specification | O3: Tech Type | P3: Reference Unit Size | Q3: Technology Year | R3: Cost Base | S3: Currency | T3: Data Reference Year | U3: Technology Readiness Level | V3: tech_maturity | W3: Technology Boundary | X3: Tech Drawing Added? | Y3: Overall Efficiency | Z3: Input, Output for Overall Efficiency | AA3: Input Carriers | AB3: Main Input Carrier | AC3: Input Shares | AD3: Input Units - Shares | AE3: Input Ratios | AF3: Input Units - Ratios | AG3: Output Carriers | AH3: Output Carriers | AI3: Main Output Carrier | AJ3: ratios_out | AK3: ratios_out | AL3: Output Units - Ratios | AM3: Output Shares | AN3: Output Units - Shares | AO3: Theoretical Efficiency | AP3: Operating Temperature | AQ3: Minimum Installation | AR3: Economic Lifetime | AS3: CAPEX One Time | AT3: CAPEX Power Capacity | AU3: OPEX One Time | AV3: OPEX Power Capacity as percentage of CAPEX | AW3: OPEX Power Capacity | AX3: OPEX Energy | AY3: Discount Rate | AZ3: Value Range Check | BA3: Uncertainty Rating | BB3: lca_id | BC3: lca_unit | BD3: embedded_carbon_kgco2e_per_lca_unit | BE3: LCA Scenario | BF3: Mass Inflows | BG3: Mass Outflows | BK3: References | BM3: Review Comment | BN3: Note | BO3: Status (VSE 2025) | BP3: CAPEX Value (VSE 2025) | BQ3: CAPEX Change % (VSE 2025) | BR3: OPEX New Value (VSE 2025) | BS3: OPEX (FOM) Change % (VSE 2025) | BT3: CAPEX Value (VSE 2022) | BU3: CAPEX Change % (VSE 2022) | BV3: OPEX New Value (VSE 2022) | BW3: OPEX (FOM) Change % (VSE 2025) | BX3: Lifetime / Amortisation VSE2025 | BY3: Difference | BZ3: Efficiency | CA3: Difference
A4: Review done | B4: 1st Review responsible | C4: 2nd Review responsible | D4: Review approved (Arash) | E4: Review approved (Robin) | F4: ehubX Tech ID | G4: tech_id | H4: Tech Ontology IRI | I4: process_type | J4: description | K4: unit_operation | L4: main_sector | M4: main_category | N4: category_spec | O4: tech_type | P4: reference_unit_size | Q4: cost_base_year | R4: Cost Base | S4: Currency | T4: Data Reference Year | U4: trl_(1-9) | V4: tech_maturity | W4: tech_boundary | X4: Tech Drawing Added? | Y4: overall_efficiency | Z4: Input, Output for Overall Efficiency | AA4: carriers_in | AB4: main_input | AC4: Input Shares | AD4: Input Units - Shares | AE4: ratios_in | AF4: units_in | AG4: carriers_out | AH4: SwissX_carriers_out | AI4: main_out | AJ4: ratios_out | AK4: SwissX_ratios_out | AL4: units_out | AM4: Output Shares | AN4: Output Units - Shares | AO4: theoretical_efficiency | AP4: operating_temperature_c | AQ4: min_installation_size | AR4: lifetime_yr | AS4: capex_one_time_eur | AT4: capex_power_capacity_eur_per_kw | AU4: opex_one_time_eur | AV4: opex_fix_pct_of_capex | AW4: opex_fix_power_capacity_eur_per_kw_yr | AX4: opex_energy_eur_per_unit | AY4: discount_rate_pct | AZ4: Value Range Check | BA4: uncertainty_rating | BB4: lca_id | BC4: lca_unit | BD4: embedded_carbon_kgco2e_per_lca_unit | BE4: lca_scenario | BF4: Mass Inflows | BG4: Mass Outflows | BH4: energy_balance_error_pct | BI4: mass_balance_error_pct | BJ4: balance_pass_flag | BK4: list_of_source_id | BL4: includedInDatastructures_flag | BM4: Review Comment | BN4: Note | BO4: Status (VSE 2025) | BP4: CAPEX Value (VSE 2025) | BQ4: CAPEX Change % (VSE 2025) | BR4: OPEX New Value (VSE 2025) | BS4: OPEX (FOM) Change % (VSE 2025) | BT4: CAPEX Value (VSE 2022) | BU4: CAPEX Change % (VSE 2022) | BV4: OPEX New Value (VSE 2022) | BW4: OPEX (FOM) Change % (VSE 2025) | BX4: Lifetime / Amortisation VSE2025 | BY4: Difference | BZ4: Efficiency | CA4: Difference
A5: FALSE | B5: Robin | C5: Partha | D5: FALSE | E5: FALSE | F5: T_C_Conv_CarbonCapture_Amine_2030 | G5: Amine_Washing_CO2_2030 | I5: CO2 capture | J5: CO2 post combustion capture via Amine washing. Temperature swing process. 2030 reference based on an approx. 150 ktCO2/a plant size. | K5: Amine Absorber | L5: CO2 capture | M5: Point source capture | N5: Amine washing | O5: Conversion | P5: 20 | Q5: 2030 | R5: CH | S5: CHF | T5: 2025 | U5: 9 | V5: =IF(U5="", "", IF(VALUE(LEFT(U5, 1))>=9, "Mature", IF(VALUE(LEFT(U5, 1))>=7, "Emerging", "Prototype"))) -> Mature | W5: Plant ready to operate | X5: FALSE | AA5: CO2Fluegas, El13, ThHt | AB5: CO2Fluegas | AE5: 1, 0.303, 0.71 | AF5: kg, kWh, kWh | AG5: CO2Sys | AH5: CO2Sys | AI5: CO2Sys | AJ5: 0.95 | AK5: 0.95 | AL5: kg | AO5: na | AQ5: 20000 kg/h | AR5: 25 | AS5: 0 | AT5: 2800 CHF/kg/h | AU5: 0 | AV5: =151/2800*100 -> 5.3928571 | AW5: 151 CHF/kg/h | AX5: 0.0056 CHF/kg | AZ5: FALSE | BA5: Medium | BB5: market for monoethanolamine; GLO | BC5: kgCO2eq/kg | BD5: 0.0040161 | BE5: SSP2-PkBudg1000_2030 | BF5: na | BG5: na | BH5: na | BI5: na | BJ5: na | BK5: "capex_power_capacity_eur_per_kw", "opex_one_time_eur", "overall_efficiency", "opex_energy_eur_per_unit", "lifetime_yr", "ratios_in", "ratios_out": AECOM_2022; "lca_id", "lca_unit", "embedded_carbon_kgco2e_per_lca_unit", "lca_scenario": parameters_lca | BL5: True | BM5: Other Values in danish_power_agency
A6: FALSE | B6: Robin | C6: Partha | D6: FALSE | E6: FALSE | F6: T_C_Conv_CarbonCapture_Amine_2040 | G6: Amine_Washing_CO2_2040 | I6: CO2 capture | J6: CO2 post combustion capture via Amine washing. Temperature swing process. 2040 reference based on an approx. 150 ktCO2/a plant size. | K6: Amine Absorber | L6: CO2 capture | M6: Point source capture | N6: Amine washing | O6: Conversion | P6: 20 | Q6: 2040 | R6: CH | S6: CHF | T6: 2025 | U6: 9 | V6: =IF(U6="", "", IF(VALUE(LEFT(U6, 1))>=9, "Mature", IF(VALUE(LEFT(U6, 1))>=7, "Emerging", "Prototype"))) -> Mature | W6: Plant ready to operate | X6: FALSE | AA6: CO2Fluegas, El13, ThHt | AB6: CO2Fluegas | AE6: 1, 0.303, 0.71 | AF6: kg, kWh, kWh | AG6: CO2Sys | AH6: CO2Sys | AI6: CO2Sys | AJ6: 0.95 | AK6: 0.95 | AL6: kg | AO6: na | AQ6: 20000 kg/h | AR6: 25 | AS6: 0 | AT6: 2800 CHF/kg/h | AU6: 0 | AV6: =151/2800*100 -> 5.3928571 | AW6: 151 CHF/kg/h | AX6: 0.0056 CHF/kg | AZ6: FALSE | BA6: Medium | BB6: market for monoethanolamine; GLO | BC6: kgCO2eq/kg | BD6: 0.0034035 | BE6: SSP2-PkBudg1000_2040 | BF6: na | BG6: na | BH6: na | BI6: na | BJ6: na | BK6: "capex_power_capacity_eur_per_kw", "opex_one_time_eur", "overall_efficiency", "opex_energy_eur_per_unit", "lifetime_yr", "ratios_in", "ratios_out": AECOM_2022; "lca_id", "lca_unit", "embedded_carbon_kgco2e_per_lca_unit", "lca_scenario": parameters_lca | BL6: True | BM6: Other Values in danish_power_agency | BO6: Not in VSE
A7: TRUE | B7: Robin | C7: Partha | D7: FALSE | E7: FALSE | F7: T_C_Conv_CarbonCapture_Amine_2050 | G7: Amine_Washing_CO2_2050 | I7: CO2 capture | J7: CO2 post combustion capture via Amine washing. Temperature swing process. 2050 reference based on an approx. 150 ktCO2/a plant size. | K7: Amine Absorber | L7: CO2 capture | M7: Point source capture | N7: Amine washing | O7: Conversion | P7: 20 | Q7: 2050 | R7: CH | S7: CHF | T7: 2025 | U7: 9 | V7: =IF(U7="", "", IF(VALUE(LEFT(U7, 1))>=9, "Mature", IF(VALUE(LEFT(U7, 1))>=7, "Emerging", "Prototype"))) -> Mature | W7: Plant ready to operate | X7: FALSE | AA7: CO2Fluegas, El13, ThHt | AB7: CO2Fluegas | AE7: 1, 0.303, 0.71 | AF7: kg, kWh, kWh | AG7: CO2Sys | AH7: CO2Sys | AI7: CO2Sys | AJ7: 0.95 | AK7: 0.95 | AL7: kg | AO7: na | AQ7: 20000 kg/h | AR7: 25 | AS7: 0 | AT7: 2800 CHF/kg/h | AU7: 0 | AV7: =151/2800*100 -> 5.3928571 | AW7: 151 CHF/kg/h | AX7: 0.0056 CHF/kg | AZ7: FALSE | BA7: Medium | BB7: market for monoethanolamine; GLO | BC7: kgCO2eq/kg | BD7: 0.0031206 | BE7: SSP2-PkBudg1000_2050 | BF7: na | BG7: na | BH7: na | BI7: na | BJ7: na | BK7: "capex_power_capacity_eur_per_kw", "opex_one_time_eur", "overall_efficiency", "opex_energy_eur_per_unit", "lifetime_yr", "ratios_in", "ratios_out": AECOM_2022; "lca_id", "lca_unit", "embedded_carbon_kgco2e_per_lca_unit", "lca_scenario": parameters_lca | BL7: True | BM7: Completed | BO7: Not in VSE
A8: TRUE | B8: Christian | D8: FALSE | E8: FALSE | F8: T_C_Conv_Ammonia_CCGT_2050 | G8: Ammonia_CCGT_2050 | K8: CCGT | L8: Ammonia | O8: Conversion | Q8: 2050 | R8: CH | S8: CHF | U8: 8 | V8: =IF(U8="", "", IF(VALUE(LEFT(U8, 1))>=9, "Mature", IF(VALUE(LEFT(U8, 1))>=7, "Emerging", "Prototype"))) -> Emerging | W8: Complete installation | Y8: 0.58 | AA8: NH3 | AB8: NH3 | AE8: 1 | AF8: kWh | AG8: El13 | AH8: El13 | AI8: El13 | AJ8: 0.58 | AK8: 0.58 | AL8: kWh | AO8: 0 | AP8: 0 | AQ8: 0 | AR8: 35 | AS8: 0 | AT8: 1200 | AU8: 0 | AW8: 35 | AX8: 0.002 | BB8: market for gas power plant, combined cycle, 400MW electrical; GLO | BC8: kgCO2eq/kW | BD8: 72.892403 | BE8: SSP2-PkBudg1000_2050 | BF8: 1216,1714 | BG8: 1000 | BH8: -0.6906 | BI8: 0.0122 | BJ8: YES | BK8: "capex_power_capacity_eur_per_kw", "opex_one_time_eur", "overall_efficiency", "opex_energy_eur_per_unit", "lifetime_yr": report_power_to_ammonia_2018; "ratios_in", "ratios_out": conversion_parametrization; "operating_temperature_c": report_danish_energy_2025; "ratios_in", "ratios_out": conversion_parametrization; "lca_id", "lca_unit", "embedded_carbon_kgco2e_per_lca_unit", "lca_scenario": parameters_lca | BL8: True
A9: TRUE | B9: Eleonora | D9: FALSE | E9: FALSE | F9: T_C_Conv_Ammonia_HaberBosch_2050 | G9: Ammonia_HaberBosch_2050 | I9: Haberbosch | J9: Ammonia synthesis (Haber Bosch process) | K9: Haber Bosch | L9: Ammonia | O9: Conversion | Q9: 2050 | R9: CH | S9: CHF | T9: 2025 | U9: 9 | V9: =IF(U9="", "", IF(VALUE(LEFT(U9, 1))>=9, "Mature", IF(VALUE(LEFT(U9, 1))>=7, "Emerging", "Prototype"))) -> Mature | W9: Complete installation | Y9: 0.25 | AA9: H2, N2 | AB9: H2 | AE9: 1, 0.139 | AF9: kWh, kg | AG9: NH3, ThPhII | AH9: NH3, ThPhII | AI9: NH3 | AJ9: 0.879, 0.127 | AK9: 0.879, 0.127 | AL9: kWh, kWh | AO9: 0.879 | AP9: 550 | AQ9: 0 | AR9: 20 | AT9: 870 | AU9: 0 | AW9: 17 | AX9: 0 | BB9: ammonia synthesis catalyst production; GLO | BC9: kgCO2eq/kg | BD9: 2.73e-05 | BE9: SSP2-PkBudg1000_2050 | BF9: 178, 822 | BG9: 1000 | BH9: 0.6853 | BI9: 0.0059 | BJ9: YES | BK9: "capex_power_capacity_eur_per_kw", "opex_one_time_eur", "overall_efficiency", "opex_energy_eur_per_unit", "lifetime_yr":report_power_to_ammonia_2018; "ratios_in", "ratios_out": conversion_parametrization; "operating_temperature_c": report_danish_energy_2025; "ratios_in", "ratios_out": conversion_parametrization; "lca_id", "lca_unit", "embedded_carbon_kgco2e_per_lca_unit", "lca_scenario": parameters_lca | BL9: True
A10: 1 | D10: FALSE | E10: FALSE | F10: T_C_Conv_Ammonia_OCGT_2050 | G10: Ammonia_OCGT_2050 | K10: OCGT | L10: Ammonia | O10: Conversion | Q10: 2050 | R10: CH | S10: CHF | U10: 8 | V10: =IF(U10="", "", IF(VALUE(LEFT(U10, 1))>=9, "Mature", IF(VALUE(LEFT(U10, 1))>=7, "Emerging", "Prototype"))) -> Emerging | W10: Complete installation | Y10: 0.4 | AA10: NH3 | AB10: NH3 | AE10: 1 | AF10: kWh | AG10: El13 | AH10: El13 | AI10: El13 | AJ10: 0.4 | AK10: 0.4 | AL10: kWh | AO10: 0 | AP10: 0 | AQ10: 0 | AR10: 30 | AS10: 0 | AT10: 750 | AU10: 0 | AW10: 20 | AX10: 0.002 | BB10: micro gas turbine production, 100kW electrical; CH | BC10: kgCO2eq/kW | BD10: 62.633809 | BE10: SSP2-PkBudg1000_2050 | BF10: 1216, 1714 | BG10: 1000 | BH10: -0.6906 | BI10: 0.0122 | BJ10: YES | BK10: "capex_power_capacity_eur_per_kw", "opex_one_time_eur", "overall_efficiency", "opex_energy_eur_per_unit", "lifetime_yr":report_power_to_ammonia_2018; "ratios_in", "ratios_out": conversion_parametrization; "operating_temperature_c": report_danish_energy_2025; "ratios_in", "ratios_out": conversion_parametrization; "lca_id", "lca_unit", "embedded_carbon_kgco2e_per_lca_unit", "lca_scenario": parameters_lca | BL10: True
A11: FALSE | B11: Robin | C11: Gianfranco | D11: FALSE | E11: FALSE | F11: T_C_Conv_Pyrolysis_BioWet_CBio | G11: BioWet_Pyrolysis_CBio | I11: Carbon black production | J11: Biochar production via pyrolysis of wet biomass. | K11: Pyrolyser | L11: Carbon Black | M11: Pyrolysis | N11: Wet Biomass | O11: Conversion | P11: 0.05 | Q11: 2025 | R11: CH | S11: CHF | T11: 2025 | U11: 7 | V11: =IF(U11="", "", IF(VALUE(LEFT(U11, 1))>=9, "Mature", IF(VALUE(LEFT(U11, 1))>=7, "Emerging", "Prototype"))) -> Emerging | X11: FALSE | AA11: BioWet | AB11: na | AE11: 1 | AF11: kWh | AG11: Cbio | AH11: Cbio | AI11: CBio | AJ11: 0.063 | AK11: 0.063 | AL11: kg | AO11: na | AP11: 700 | AQ11: 0 | AR11: 20 | AS11: 0 | AT11: 8000 CHF/kg/h | AU11: 0 | AV11: 2.5 | AW11: 200 CHF/kg/h | AX11: 0 | AZ11: FALSE | BA11: High | BF11: na | BG11: na | BK11: "capex_power_capacity_eur_per_kw", "opex_one_time_eur", "lifetime_yr": biochar_jcp_2025 "overall_efficiency": missing; "ratios_in", "ratios_out": EP2050+Exkurs; "lca_id", "lca_unit", "embedded_carbon_kgco2e_per_lca_unit", "lca_scenario": missing | BM11: CAPEX, OPEX Values different in Danish Energy report | BO11: Not in VSE
A12: TRUE | B12: Christian | D12: FALSE | E12: FALSE | F12: T_C_Conv_CarbonCapture_DacAds_2030 | G12: CarbonCapture_Direct_2030 | I12: CO2 capture | J12: Direct air capture using adsorption technology (2030 and 2040). | K12: DAC | L12: Carbon Capture | M12: DAC | N12: Adsorption | O12: Conversion | Q12: 2030 | R12: CH | S12: CHF | U12: 7 | V12: =IF(U12="", "", IF(VALUE(LEFT(U12, 1))>=9, "Mature", IF(VALUE(LEFT(U12, 1))>=7, "Emerging", "Prototype"))) -> Emerging | X12: FALSE | AA12: ThHt, El47 | AB12: El47 | AE12: 1, 0.19 | AF12: kWh, kWh | AG12: CO2Sys | AH12: CO2Sys | AI12: CO2Sys | AJ12: 0.395 | AK12: 0.395 | AL12: kg | AO12: na | AP12: 0 | AQ12: 0 | AR12: 25 | AS12: 0 | AT12: 9600 CHF/kg/h | AU12: 0 | AV12: =+AW12/AT12% -> #VALUE! | AW12: 2120 | AX12: 0 | AZ12: FALSE | BA12: High | BB12: direct air capture system, sorbent-based, 100ktCO2; RER | BC12: kgCO2eq/kg | BD12: 0.0049796 | BE12: SSP2-PkBudg1000_2030 | BF12: na | BG12: na | BH12: na | BI12: na | BJ12: na | BK12: "capex_power_capacity_eur_per_kw", "opex_one_time_eur", "overall_efficiency", "opex_energy_eur_per_unit", "lifetime_yr": Allgoewer_2024 ; "ratios_in", "ratios_out": Allgoewer_2024; "lca_id", "lca_unit", "embedded_carbon_kgco2e_per_lca_unit", "lca_scenario": parameters_lca | BL12: True | BM12: In 2030-2040, I would assume you need per each ton of CO2, 0.48 MWh of electricity and 2.53 MWh of heat (100 °C). In 2050, I would assume them to be respectively 0.38 and 1.5. For what regards the CAPEX costs. The CAPEX of the plant for a size of 360 kt/y is 362 MEur for 2030-2040 and reduces to as low as 84 MEur for 2050. These are all the average values from Allgower et al. 2024. Important to add a sorbent replacement opex cost: 7.5 kg of sorbent are disposed of per t of CO2 in 2030-2040 and become 3 kg per t in 2050. The cost of the sorbent is 21.5 eur/kg in 2030-2040 and reduces to 7.6 eur/kg in 2050 | BO12: Value from Review: Value from VSE on the right "CCS DAC Schweiz"
A13: TRUE | B13: Christian | D13: FALSE | E13: FALSE | F13: T_C_Conv_CarbonCapture_DacAds_2040 | G13: CarbonCapture_Direct_2040 | I13: CO2 capture | J13: Direct air capture using adsorption technology (2040). | K13: DAC | O13: Conversion | Q13: 2040 | R13: CH | S13: CHF | V13: =IF(U13="", "", IF(VALUE(LEFT(U13, 1))>=9, "Mature", IF(VALUE(LEFT(U13, 1))>=7, "Emerging", "Prototype"))) | X13: FALSE | AA13: ThHt, El47 | AB13: El47 | AE13: 1, 0.19 | AF13: kWh, kWh | AG13: CO2Sys | AH13: CO2Sys | AI13: CO2Sys | AJ13: 0.395 | AK13: 0.395 | AL13: kg | AO13: na | AP13: 0 | AQ13: 0 | AR13: 25 | AS13: 0 | AT13: 8800 | AU13: 0 | AV13: =+AW13/AT13% -> 12.045455 | AW13: 1060 | AX13: 0 | AZ13: FALSE | BA13: High | BB13: direct air capture system, sorbent-based, 100ktCO2; RER | BC13: kgCO2eq/kg | BD13: 0.0036549 | BE13: SSP2-PkBudg1000_2040 | BF13: na | BG13: na | BH13: na | BI13: na | BJ13: na | BK13: "capex_power_capacity_eur_per_kw", "opex_one_time_eur", "overall_efficiency", "opex_energy_eur_per_unit", "lifetime_yr": Allgoewer_2024 ; "ratios_in", "ratios_out": Allgoewer_2024; "lca_id", "lca_unit", "embedded_carbon_kgco2e_per_lca_unit", "lca_scenario": parameters_lca | BL13: False | BM13: In 2030-2040, I would assume you need per each ton of CO2, 0.48 MWh of electricity and 2.53 MWh of heat (100 °C). In 2050, I would assume them to be respectively 0.38 and 1.5. For what regards the CAPEX costs. The CAPEX of the plant for a size of 360 kt/y is 362 MEur for 2030-2040 and reduces to as low as 84 MEur for 2050. These are all the average values from Allgower et al. 2024. Important to add a sorbent replacement opex cost: 7.5 kg of sorbent are disposed of per t of CO2 in 2030-2040 and become 3 kg per t in 2050. The cost of the sorbent is 21.5 eur/kg in 2030-2040 and reduces to 7.6 eur/kg in 2050 | BO13: Value from Review: Value from VSE on the right "CCS DAC Schweiz"
A14: TRUE | B14: Christian | D14: FALSE | E14: FALSE | F14: T_C_Conv_CarbonCapture_DacAds_2050 | G14: CarbonCapture_Direct_2050 | I14: CO2 capture | J14: Direct air capture using adsorption technology (2050). | K14: DAC | O14: Conversion | Q14: 2050 | R14: CH | S14: CHF | U14: 7 | V14: =IF(U14="", "", IF(VALUE(LEFT(U14, 1))>=9, "Mature", IF(VALUE(LEFT(U14, 1))>=7, "Emerging", "Prototype"))) -> Emerging | X14: FALSE | AA14: ThHt, El47 | AB14: El47 | AE14: 1, 0.25 | AF14: kWh, kWh | AG14: CO2Sys | AH14: CO2Sys | AI14: CO2Sys | AJ14: 0.67 | AK14: 0.67 | AL14: kg | AO14: na | AP14: 0 | AQ14: 0 | AR14: 25 | AS14: 0 | AT14: 6600 | AU14: 0 | AV14: =AW14/AT14 -> 0.12045455 | AW14: 795 | AX14: 0 | AZ14: FALSE | BA14: High | BB14: direct air capture system, sorbent-based, 100ktCO2; RER | BC14: kgCO2eq/kg | BD14: 0.0026084 | BE14: SSP2-PkBudg1000_2050 | BF14: na | BG14: na | BH14: na | BI14: na | BJ14: na | BK14: "capex_power_capacity_eur_per_kw", "opex_one_time_eur", "overall_efficiency", "opex_energy_eur_per_unit", "lifetime_yr": Allgoewer_2024 ; "ratios_in", "ratios_out": Allgoewer_2024; "lca_id", "lca_unit", "embedded_carbon_kgco2e_per_lca_unit", "lca_scenario": parameters_lca | BL14: True | BM14: In 2030-2040, I would assume you need per each ton of CO2, 0.48 MWh of electricity and 2.53 MWh of heat (100 °C). In 2050, I would assume them to be respectively 0.38 and 1.5. For what regards the CAPEX costs. The CAPEX of the plant for a size of 360 kt/y is 362 MEur for 2030-2040 and reduces to as low as 84 MEur for 2050. These are all the average values from Allgower et al. 2024. Important to add a sorbent replacement opex cost: 7.5 kg of sorbent are disposed of per t of CO2 in 2030-2040 and become 3 kg per t in 2050. The cost of the sorbent is 21.5 eur/kg in 2030-2040 and reduces to 7.6 eur/kg in 2050 | BO14: Value from Review: Value from VSE on the right "CCS DAC Schweiz"
A15: FALSE | B15: Robin | C15: Partha | D15: FALSE | E15: FALSE | F15: T_C_Conv_CarbonCapture_Hpc_2030 | G15: CarbonCapture_PressureSwing_2030 | I15: CO2 capture | J15: CO2 post combustion capture via Hot-Potassium Carbonate cycling. Pressure swing process. 2030 reference based on an approx. 150 ktCO2/a plant size. | K15: Carbonate Cycling | L15: CO2 capture | M15: Point source capture | N15: HPC cycling | O15: Conversion | P15: 20 | Q15: 2030 | R15: CH | S15: CHF | T15: 2025 | U15: 8 | V15: =IF(U15="", "", IF(VALUE(LEFT(U15, 1))>=9, "Mature", IF(VALUE(LEFT(U15, 1))>=7, "Emerging", "Prototype"))) -> Emerging | W15: Plant ready to operate | X15: FALSE | AA15: CO2Fluegas, El13, ThHt | AB15: CO2Fluegas | AE15: 1, 0.52, 0.024 | AF15: kg, kWh, kWh | AG15: CO2Sys | AH15: CO2Sys | AI15: CO2Sys | AJ15: 0.95 | AK15: 0.95 | AL15: kg | AO15: na | AQ15: 20000 kg/h | AR15: 25 | AS15: 0 | AT15: 2500 CHF/kg/h | AU15: 0 | AV15: =139/2500*100 -> 5.56 | AW15: 139 CHF/kg/h | AX15: 0.0022 CHF/kg | AZ15: FALSE | BA15: High | BB15: potassium carbonate production, from potassium hydroxide; GLO | BC15: kgCO2eq/kg | BD15: 0.0011127 | BE15: SSP2-PkBudg1000_2030 | BF15: na | BG15: na | BH15: na | BI15: na | BJ15: na | BK15: "capex_power_capacity_eur_per_kw", "opex_one_time_eur", "overall_efficiency", "opex_energy_eur_per_unit", "lifetime_yr", "ratios_in", "ratios_out": AECOM_2022; "lca_id", "lca_unit", "embedded_carbon_kgco2e_per_lca_unit", "lca_scenario": parameters_lca | BL15: True | BO15: Not in VSE
A16: TRUE | B16: Robin | C16: Partha | D16: FALSE | E16: FALSE | F16: T_C_Conv_CarbonCapture_Hpc_2040 | G16: CarbonCapture_PressureSwing_2040 | I16: CO2 capture | J16: CO2 post combustion capture via Hot-Potassium Carbonate cycling. Pressure swing process. 2030 reference based on an approx. 150 ktCO2/a plant size. | K16: Carbonate Cycling | L16: CO2 capture | M16: Point source capture | N16: HPC cycling | O16: Conversion | P16: 20 | Q16: 2040 | R16: CH | S16: CHF | T16: 2025 | U16: 9 | V16: =IF(U16="", "", IF(VALUE(LEFT(U16, 1))>=9, "Mature", IF(VALUE(LEFT(U16, 1))>=7, "Emerging", "Prototype"))) -> Mature | W16: Plant ready to operate | X16: FALSE | AA16: CO2Fluegas, El13, ThHt | AB16: CO2Fluegas | AE16: 1, 0.52, 0.024 | AF16: kg, kWh, kWh | AG16: CO2Sys | AH16: CO2Sys | AI16: CO2Sys | AJ16: 0.95 | AK16: 0.95 | AL16: kg | AO16: na | AQ16: 20000 kg/h | AR16: 25 | AS16: 0 | AT16: 2500 CHF/kg/h | AU16: 0 | AV16: =139/2500*100 -> 5.56 | AW16: 139 CHF/kg/h | AX16: 0.0022 CHF/kg | AZ16: FALSE | BA16: High | BB16: potassium carbonate production, from potassium hydroxide; GLO | BC16: kgCO2eq/kg | BD16: 0.0004904 | BE16: SSP2-PkBudg1000_2040 | BF16: na | BG16: na | BH16: na | BI16: na | BJ16: na | BK16: "capex_power_capacity_eur_per_kw", "opex_one_time_eur", "overall_efficiency", "opex_energy_eur_per_unit", "lifetime_yr", "ratios_in", "ratios_out": AECOM_2022; "lca_id", "lca_unit", "embedded_carbon_kgco2e_per_lca_unit", "lca_scenario": parameters_lca | BL16: True | BO16: Not in VSE
A17: FALSE | B17: Robin | C17: Partha | D17: FALSE | E17: FALSE | F17: T_C_Conv_CarbonCapture_Hpc_2050 | G17: CarbonCapture_PressureSwing_2050 | I17: CO2 capture | J17: CO2 post combustion capture via Hot-Potassium Carbonate cycling. Pressure swing process. 2050 reference based on an approx. 150 ktCO2/a plant size. | K17: Carbonate Cycling | L17: CO2 capture | M17: Point source capture | N17: HPC cycling | O17: Conversion | P17: 20 | Q17: 2050 | R17: CH | S17: CHF | T17: 2025 | U17: 9 | V17: =IF(U17="", "", IF(VALUE(LEFT(U17, 1))>=9, "Mature", IF(VALUE(LEFT(U17, 1))>=7, "Emerging", "Prototype"))) -> Mature | W17: Plant ready to operate | X17: FALSE | AA17: CO2, El13, ThHt | AB17: CO2Waste | AE17: 1, 0.52, 0.024 | AF17: kg, kWh, kWh | AG17: CO2Sys | AH17: CO2Sys | AI17: CO2Sys | AJ17: 0.95 | AK17: 0.95 | AL17: kg | AO17: na | AQ17: 20000 kg/h | AR17: 25 | AS17: 0 | AT17: 2500 CHF/kg/h | AU17: 0 | AV17: =139/2500*100 -> 5.56 | AW17: 139 CHF/kg/h | AX17: 0.0022 CHF/kg | AZ17: FALSE | BA17: High | BB17: potassium carbonate production, from potassium hydroxide; GLO | BC17: kgCO2eq/kg | BD17: 0.0002767 | BE17: SSP2-PkBudg1000_2050 | BF17: na | BG17: na | BH17: na | BI17: na | BJ17: na | BK17: "capex_power_capacity_eur_per_kw", "opex_one_time_eur", "overall_efficiency", "opex_energy_eur_per_unit", "lifetime_yr", "ratios_in", "ratios_out": AECOM_2022; "lca_id", "lca_unit", "embedded_carbon_kgco2e_per_lca_unit", "lca_scenario": parameters_lca | BL17: True | BM17: Completed | BO17: Not in VSE
A18: FALSE | B18: Gianfranco | D18: FALSE | E18: FALSE | F18: T_C_Conv_Elec_CH4_Ccgt_2050 | G18: CH4_CCGT_2050 | I18: Gas Turbine | J18: Methane-fueled CCGT with carbon capture and storage (CCS) (2030). | K18: CCGT | O18: Conversion | Q18: 2030 | R18: CH | S18: CHF | U18: 9 | V18: =IF(U18="", "", IF(VALUE(LEFT(U18, 1))>=9, "Mature", IF(VALUE(LEFT(U18, 1))>=7, "Emerging", "Prototype"))) -> Mature | X18: FALSE | Y18: 0.64 | AA18: CH4 | AB18: na | AE18: 1 | AF18: kWh | AG18: El13 | AH18: El13 | AI18: El13 | AJ18: 0.61 | AK18: 0.61 | AL18: kWh | AO18: na | AP18: 1500 | AQ18: 400000 | AR18: 23 | AS18: 0 | AT18: 890 | AU18: 0 | AV18: =+AW18/AT18% -> 2.3595506 | AW18: 21 | AX18: 0.002 | AZ18: FALSE | BA18: Low | BB18: market for gas power plant, combined cycle, 400MW electrical; GLO | BC18: kgCO2eq/kW | BD18: 72.892403 | BE18: SSP2-PkBudg1000_2050 | BF18: na | BG18: na | BH18: 0.06 | BI18: 0 | BJ18: YES | BK18: "overall_efficiency": paper_CCGT_2024; "capex_power_capacity_eur_per_kw", "opex_one_time_eur", "opex_energy_eur_per_unit": report_VSE_2025; "lifetime_yr", "overall_efficiency": report_VSE_2022;; "lca_id", "lca_unit", "embedded_carbon_kgco2e_per_lca_unit", "lca_scenario": parameters_lca | BL18: True | BO18: Confirmed in VSE 2025
A19: FALSE | B19: Arash | C19: Robin | D19: TRUE | E19: FALSE | F19: T_C_Conv_Elec_CH4_CCGT + CCS Combo_2050 | G19: CH4_CCGT_CCS_2050 | I19: Gas Turbine | J19: Methane-fueled CCGT with carbon capture and storage (CCS). | K19: CCGT + CCS | Q19: 2050 | S19: CHF | V19: =IF(U19="", "", IF(VALUE(LEFT(U19, 1))>=9, "Mature", IF(VALUE(LEFT(U19, 1))>=7, "Emerging", "Prototype"))) | X19: FALSE | Y19: 0.52 | AA19: CH4 | AB19: na | AE19: 1 | AF19: kWh | AG19: El13, CO2Sys | AH19: El13, CO2Sys | AI19: El13 | AJ19: 0.52, 0.19 | AK19: 0.52, 0.19 | AL19: kWh, kg | AO19: na | AP19: 1500 | AQ19: 400000 | AR19: 23 | AT19: 1183 | AV19: =+AW19/AT19% -> 2.2823331 | AW19: 27 | AX19: 0.003 | AZ19: FALSE | BA19: Low | BB19: market for gas power plant, combined cycle, 400MW electrical; GLO | BC19: kgCO2eq/kW | BD19: 72.892403 | BE19: SSP2-PkBudg1000_2050 | BF19: na | BG19: na | BH19: 0.06 | BI19: 0 | BJ19: YES | BK19: "capex_power_capacity_eur_per_kw", "opex_one_time_eur", "overall_efficiency", "opex_energy_eur_per_unit": report_VSE_2025; "lifetime_yr": report_VSE_2022; "ratios_in", "ratios_out": source_share; "lca_id", "lca_unit", "embedded_carbon_kgco2e_per_lca_unit", "lca_scenario": parameters_lca | BL19: False | BO19: Confirmed in VSE 2025
A20: FALSE | B20: Gianfranco | D20: FALSE | E20: FALSE | F20: T_C_Conv_Elec_CH4_Chp_2050 | G20: CH4_CHP_2050 | I20: Heat and Electricity generation | J20: Combined heat and power (CHP) generation using methane (CH₄). | K20: General process unit | O20: Conversion | Q20: 2050 | R20: CH | S20: CHF | U20: 9 | V20: =IF(U20="", "", IF(VALUE(LEFT(U20, 1))>=9, "Mature", IF(VALUE(LEFT(U20, 1))>=7, "Emerging", "Prototype"))) -> Mature | X20: FALSE | Y20: 0.3 | AA20: CH4 | AB20: na | AE20: 1 | AF20: kWh | AG20: El47, ThHt | AH20: El47, ThHt | AI20: El47 | AJ20: 0.3, 0.6 | AK20: 0.3, 0.6 | AL20: kWh, kWh | AO20: na | AP20: 0 | AQ20: 1000 | AR20: 15 | AS20: 0 | AT20: 1000 | AU20: 0 | AV20: =+AW20/AT20% -> 1.2 | AW20: 12 | AX20: 0.004 | AZ20: FALSE | BA20: Low | BB20: heat and power co-generation unit construction, 160kW electrical, common components for heat+electricity; RER | BC20: kgCO2eq/kW | BD20: 109.80485 | BE20: SSP2-PkBudg1000_2050 | BF20: na | BG20: na | BH20: 0.06 | BI20: 0 | BJ20: YES | BK20: "capex_power_capacity_eur_per_kw", "opex_one_time_eur", "overall_efficiency", "opex_energy_eur_per_unit": report_VSE_2025; "lifetime_yr": report_VSE_2022; "ratios_in", "ratios_out": source_share; "lca_id", "lca_unit", "embedded_carbon_kgco2e_per_lca_unit", "lca_scenario": parameters_lca | BL20: True | BM20: What size do the numbers refer to? | BO20: Confirmed in VSE 2025
A21: FALSE | B21: Arash | D21: FALSE | E21: FALSE | F21: T_C_Conv_Methane_Digestion_BioWet_CH4_2030 | G21: CH4_Digestion_2030 | I21: Digestion | J21: Wet biomass anaerobic digestion with gas upgrading | K21: Anaerobic Digester | L21: Methane | M21: Digestion | N21: Waste | O21: Conversion | Q21: 2030 | R21: CH | S21: CHF | T21: 2021 | U21: 9 | V21: =IF(U21="", "", IF(VALUE(LEFT(U21, 1))>=9, "Mature", IF(VALUE(LEFT(U21, 1))>=7, "Emerging", "Prototype"))) -> Mature | W21: Plant ready to operate | X21: FALSE | Y21: 0.458 | AA21: BioWet, H2 | AB21: BioWet | AE21: 1, 0.378 | AF21: kWh, kWh | AG21: Ch4 | AH21: Ch4 | AI21: Ch4 | AJ21: =AVERAGE(0.66,0.64,0.68,0.55) -> 0.6325 | AK21: =AVERAGE(0.66,0.64,0.68,0.55) -> 0.6325 | AL21: kWh | AO21: 0.63 | AP21: 0 | AQ21: 0 | AR21: 20 | AS21: 0 | AT21: 1130 | AU21: 0 | AV21: =+AW21/AT21% -> 9.1150442 | AW21: 103 | AX21: 0.003672 | AZ21: FALSE | BB21: anaerobic digestion plant construction, agricultural; CH | BC21: kgCO2eq/kW | BD21: 0.0003328 | BE21: SSP2-PkBudg1000_2030 | BF21: =IF(AE21="na","na","needs value") -> needs value | BG21: =IF(AJ21="na","na","needs value") -> needs value | BH21: na | BI21: na | BJ21: na | BK21: "tech_maturity":paper_biogas; "capex_power_capacity_eur_per_kw", "opex_one_time_eur": report_danish_energy_2025; "lifetime_yr":report_VSE_2022; "overall_efficiency": report_danish_energy_2025; "ratios_in", "ratios_out": source_share; "lca_id", "lca_unit", "embedded_carbon_kgco2e_per_lca_unit", "lca_scenario": parameters_lca | BL21: True | BM21: "overall_efficiency": Values for maize =0.66, green beet =0.64 , strass=0.68 , straw = 0.55 . Average taken for value | BO21: Confirmed in VSE 2025
A22: FALSE | B22: Arash | D22: FALSE | E22: FALSE | F22: T_C_Conv_Methane_Digestion_BioWet_CH4_2040 | G22: CH4_Digestion_2040 | I22: Digestion | J22: Wet biomass anaerobic digestion with gas upgrading | K22: Anaerobic Digester | L22: Methane | M22: Digestion | N22: Waste | O22: Conversion | Q22: 2040 | R22: CH | S22: CHF | T22: 2021 | U22: 9 | V22: =IF(U22="", "", IF(VALUE(LEFT(U22, 1))>=9, "Mature", IF(VALUE(LEFT(U22, 1))>=7, "Emerging", "Prototype"))) -> Mature | W22: Plant ready to operate | X22: FALSE | Y22: 0.458 | AA22: BioWet, H2 | AB22: BioWet | AE22: 1, 0.378 | AF22: kWh, kWh | AG22: Ch4 | AH22: Ch4 | AI22: Ch4 | AJ22: =AVERAGE(0.66,0.64,0.68,0.55) -> 0.6325 | AK22: =AVERAGE(0.66,0.64,0.68,0.55) -> 0.6325 | AL22: kWh | AO22: 0.63 | AP22: 0 | AQ22: 0 | AR22: 20 | AS22: 0 | AT22: 1056 | AU22: 0 | AV22: =+AW22/AT22% -> 9.0909091 | AW22: 96 | AX22: 0.00306 | AZ22: FALSE | BB22: anaerobic digestion plant construction, agricultural; CH | BC22: kgCO2eq/kW | BD22: 0.0002654 | BE22: SSP2-PkBudg1000_2040 | BF22: =IF(AE22="na","na","needs value") -> needs value | BG22: =IF(AJ22="na","na","needs value") -> needs value | BH22: na | BI22: na | BJ22: na | BK22: "tech_maturity":paper_biogas; "capex_power_capacity_eur_per_kw", "opex_one_time_eur": report_danish_energy_2025; "lifetime_yr":report_VSE_2022; "overall_efficiency": report_danish_energy_2025; "ratios_in", "ratios_out": source_share; "lca_id", "lca_unit", "embedded_carbon_kgco2e_per_lca_unit", "lca_scenario": parameters_lca | BL22: True | BM22: "overall_efficiency": Values for maize =0.66, green beet =0.64 , strass=0.68 , straw = 0.55 . Average taken for value | BO22: Confirmed in VSE 2025
A23: FALSE | B23: Arash | D23: FALSE | E23: FALSE | F23: T_C_Conv_Methane_Digestion_BioWet_CH4_2050 | G23: CH4_Digestion_2050 | I23: Digestion | J23: Wet biomass anaerobic digestion with gas upgrading | K23: Anaerobic Digester | L23: Methane | M23: Digestion | N23: Waste | O23: Conversion | Q23: 2050 | R23: CH | S23: CHF | T23: 2021 | U23: 9 | V23: =IF(U23="", "", IF(VALUE(LEFT(U23, 1))>=9, "Mature", IF(VALUE(LEFT(U23, 1))>=7, "Emerging", "Prototype"))) -> Mature | W23: Plant ready to operate | X23: FALSE | Y23: 0.458 | AA23: BioWet, H2 | AB23: BioWet | AE23: 1, 0.378 | AF23: kWh, kWh | AG23: Ch4 | AH23: Ch4 | AI23: Ch4 | AJ23: =AVERAGE(0.66,0.64,0.68,0.55) -> 0.6325 | AK23: =AVERAGE(0.66,0.64,0.68,0.55) -> 0.6325 | AL23: kWh | AO23: 0.63 | AP23: 0 | AQ23: 0 | AR23: 20 | AS23: 0 | AT23: 995 | AU23: 0 | AV23: =+AW23/AT23% -> 8.9447236 | AW23: 89 | AX23: 0.0027 | AZ23: FALSE | BB23: anaerobic digestion plant construction, agricultural; CH | BC23: kgCO2eq/kW | BD23: 0.000189 | BE23: SSP2-PkBudg1000_2050 | BF23: =IF(AE23="na","na","needs value") -> needs value | BG23: =IF(AJ23="na","na","needs value") -> needs value | BH23: na | BI23: na | BJ23: na | BK23: "tech_maturity":paper_biogas; "capex_power_capacity_eur_per_kw", "opex_one_time_eur": report_danish_energy_2025; "lifetime_yr":report_VSE_2022; "overall_efficiency": report_danish_energy_2025; "ratios_in", "ratios_out": source_share; "lca_id", "lca_unit", "embedded_carbon_kgco2e_per_lca_unit", "lca_scenario": parameters_lca | BL23: True | BM23: "overall_efficiency": Values for maize =0.66, green beet =0.64 , strass=0.68 , straw = 0.55 . Average taken for value | BO23: Confirmed in VSE 2025 | BT23: 8000 | BU23: =BT23/AT23-1 -> 7.040201 | BV23: 120 | BW23: =BV23/AW23-1 -> 0.34831461 | BX23: Not in VSE
A24: TRUE | B24: Eleonora | D24: FALSE | E24: FALSE | F24: T_C_Conv_Elec_FuelcellCH4_El47_2030 | G24: CH4_Fuelcell_2030 | I24: Electricity production / Hydrogen use | J24: Methane-fueled fuel cell electricity generation at El47 (2030). | K24: Fuelcell | L24: Methane | M24: Fuelcell | O24: Conversion | Q24: 2030 | R24: CH | S24: CHF | U24: 9 | V24: =IF(U24="", "", IF(VALUE(LEFT(U24, 1))>=9, "Mature", IF(VALUE(LEFT(U24, 1))>=7, "Emerging", "Prototype"))) -> Mature | X24: FALSE | Y24: 0.64 | AA24: CH4 | AB24: na | AE24: 1 | AF24: kWh | AG24: El47, ThHt | AH24: El47, ThHt | AI24: El47 | AJ24: 0.58, 0.28 | AK24: 0.58, 0.28 | AL24: kWh, kWh | AO24: na | AP24: 1000 | AQ24: 0 | AR24: 16 | AS24: 0 | AT24: 6000 | AU24: 0 | AV24: =+AW24/AT24% -> 1.0333333 | AW24: 62 | AX24: 0 | AZ24: FALSE | BA24: Medium | BB24: fuel cell production, solid oxide, 125kW electrical, future; CH | BC24: kgCO2eq/kW | BD24: 753.19028 | BE24: SSP2-PkBudg1000_2030 | BF24: na | BG24: na | BH24: na | BI24: na | BJ24: na | BK24: "capex_power_capacity_eur_per_kw", "opex_one_time_eur", "overall_efficiency", "lifetime_yr": report_jrc_2021; "ratios_in", "ratios_out": source_share ; "lca_id", "lca_unit", "embedded_carbon_kgco2e_per_lca_unit", "lca_scenario": parameters_lca | BL24: True | BM24: What's the difference with line 46 (ID=T_C_Conv_Elec_FuelCell_ElBdg_2030)? Useful ref: https://publications.jrc.ec.europa.eu/repository/bitstream/JRC125018/stationary_kpi_report_-_18052021_-_public_version_with_identifiers.pdf | BO24: VALUE FROM REVIEW | BP24: 4600 | BQ24: - | BR24: 96 | BS24: - | BX24: 40 | BY24: =BX24/AR24-1 -> 1.5 | BZ24: 0.2
A25: TRUE | B25: Eleonora | D25: FALSE | E25: FALSE | F25: T_C_Conv_Elec_FuelcellCH4_ElBdg_2030 | G25: CH4_Fuelcell_Buildings_2030 | I25: Electricity production / Hydrogen use | J25: Methane-fueled fuel cell electricity generation in buildings (2030). | K25: Fuelcell | L25: Electricity / Hydrogen | M25: Grid / Hydrogen | O25: Conversion | Q25: 2030 | R25: CH | S25: CHF | U25: 9 | V25: =IF(U25="", "", IF(VALUE(LEFT(U25, 1))>=9, "Mature", IF(VALUE(LEFT(U25, 1))>=7, "Emerging", "Prototype"))) -> Mature | X25: FALSE | Y25: 0.64 | AA25: CH4 | AB25: na | AE25: 1 | AF25: kWh | AG25: ElBdg, ThBdg | AH25: ElBdg, ThBdg | AI25: ElBdg | AJ25: 0.45, 0.43 | AK25: 0.45, 0.43 | AL25: kWh, kWh | AO25: na | AP25: 1000 | AQ25: 0 | AR25: 16 | AS25: 0 | AT25: 10000 | AU25: 0 | AV25: =+AW25/AT25% -> 2.82 | AW25: 282 | AX25: 0 | AZ25: FALSE | BA25: Medium | BB25: fuel cell production, solid oxide, 125kW electrical, future; CH | BC25: kgCO2eq/kW | BD25: 753.19028 | BE25: SSP2-PkBudg1000_2030 | BF25: na | BG25: na | BH25: na | BI25: na | BJ25: na | BK25: "capex_power_capacity_eur_per_kw", "opex_one_time_eur", "overall_efficiency", "opex_energy_eur_per_unit", "lifetime_yr": report_jrc_2021; "ratios_in", "ratios_out": source_share ; "lca_id", "lca_unit", "embedded_carbon_kgco2e_per_lca_unit", "lca_scenario": parameters_lca | BL25: True | BM25: What's the difference with line 37 (ID=T_C_Conv_Elec_FuelCell_ElBdg_2030)? Useful ref: https://publications.jrc.ec.europa.eu/repository/bitstream/JRC125018/stationary_kpi_report_-_18052021_-_public_version_with_identifiers.pdf | BO25: VALUE FROM REVIEW No specific value for electricity generation via methane fuel cell in VSA | BP25: 4600 | BQ25: - | BR25: 96 | BS25: - | BX25: 40 | BY25: =BX25/AR25-1 -> 1.5 | BZ25: 0.2
A26: FALSE | D26: FALSE | E26: FALSE | F26: T_C_Conv_Thermal_ThermalBdg_CH4_2020 | G26: CH4_Heating_Buildings_2020 | I26: Gas Boiler | J26: Methane-fueled heating system for buildings. | K26: Heatpump | L26: Thermal | M26: Building | N26: Methane | O26: Conversion | Q26: 2020 | R26: CH | S26: CHF | U26: 9 | V26: =IF(U26="", "", IF(VALUE(LEFT(U26, 1))>=9, "Mature", IF(VALUE(LEFT(U26, 1))>=7, "Emerging", "Prototype"))) -> Mature | X26: FALSE | Y26: 0.93 | AA26: CH4 | AB26: na | AE26: 1 | AF26: kWh | AG26: ThBdg | AH26: ThBdg | AI26: ThBdg | AJ26: 0.93 | AK26: 0.93 | AL26: kWh | AO26: na | AP26: 0 | AQ26: 0 | AR26: 20 | AS26: 0 | AT26: 1900 | AU26: 0 | AV26: =+AW26/AT26% -> 6 | AW26: 114 | AX26: 0 | AZ26: FALSE | BA26: Low | BB26: market for gas boiler; GLO | BC26: kgCO2eq/kW | BD26: 45.141525 | BE26: SSP2-PkBudg1000_2025 | BF26: na | BG26: na | BH26: na | BI26: na | BJ26: na | BK26: "capex_power_capacity_eur_per_kw", "opex_one_time_eur", "lifetime_yr": report_VSE_2022; "overall_efficiency", "opex_energy_eur_per_unit": report_VSE_2025; "ratios_in", "ratios_out": source_share; "lca_id", "lca_unit", "embedded_carbon_kgco2e_per_lca_unit", "lca_scenario": parameters_lca | BL26: True | BO26: No value in VSA | BP26: 4600 | BQ26: - | BR26: 96 | BS26: - | BX26: 40 | BY26: =BX26/AR26-1 -> 1 | BZ26: 0.2
A27: FALSE | D27: FALSE | E27: FALSE | F27: T_C_Conv_Thermal_ThermalBdg_CH4_2030 | G27: CH4_Heating_Buildings_2030 | I27: Gas Boiler | J27: Methane-fueled heating system for buildings. | K27: Heatpump | L27: Thermal | M27: Building | N27: Methane | O27: Conversion | Q27: 2030 | R27: CH | S27: CHF | U27: 9 | V27: =IF(U27="", "", IF(VALUE(LEFT(U27, 1))>=9, "Mature", IF(VALUE(LEFT(U27, 1))>=7, "Emerging", "Prototype"))) -> Mature | X27: FALSE | Y27: 0.93 | AA27: CH4 | AB27: na | AE27: 1 | AF27: kWh | AG27: ThBdg | AH27: ThBdg | AI27: ThBdg | AJ27: 0.93 | AK27: 0.93 | AL27: kWh | AO27: na | AP27: 0 | AQ27: 0 | AR27: 20 | AS27: 0 | AT27: 1900 | AU27: 0 | AV27: =+AW27/AT27% -> 6 | AW27: 114 | AX27: 0 | AZ27: FALSE | BA27: Low | BB27: market for gas boiler; GLO | BC27: kgCO2eq/kW | BD27: 37.919543 | BE27: SSP2-PkBudg1000_2030 | BF27: na | BG27: na | BH27: na | BI27: na | BJ27: na | BK27: "capex_power_capacity_eur_per_kw", "opex_one_time_eur", "lifetime_yr": report_VSE_2022; "overall_efficiency", "opex_energy_eur_per_unit": report_VSE_2025; "ratios_in", "ratios_out": source_share; "lca_id", "lca_unit", "embedded_carbon_kgco2e_per_lca_unit", "lca_scenario": parameters_lca | BL27: True | BO27: No value in VSA | BP27: 4600 | BQ27: - | BR27: 96 | BS27: - | BX27: 40 | BY27: =BX27/AR27-1 -> 1 | BZ27: 0.2
A28: FALSE | D28: FALSE | E28: FALSE | F28: T_C_Conv_Thermal_ThermalBdg_CH4_2040 | G28: CH4_Heating_Buildings_2040 | I28: Gas Boiler | J28: Methane-fueled heating system for buildings. | K28: Heatpump | L28: Thermal | M28: Building | N28: Methane | O28: Conversion | Q28: 2040 | R28: CH | S28: CHF | U28: 9 | V28: =IF(U28="", "", IF(VALUE(LEFT(U28, 1))>=9, "Mature", IF(VALUE(LEFT(U28, 1))>=7, "Emerging", "Prototype"))) -> Mature | X28: FALSE | Y28: 0.93 | AA28: CH4 | AB28: na | AE28: 1 | AF28: kWh | AG28: ThBdg | AH28: ThBdg | AI28: ThBdg | AJ28: 0.93 | AK28: 0.93 | AL28: kWh | AO28: na | AP28: 0 | AQ28: 0 | AR28: 20 | AS28: 0 | AT28: 1900 | AU28: 0 | AV28: =+AW28/AT28% -> 6 | AW28: 114 | AX28: 0 | AZ28: FALSE | BA28: Low | BB28: market for gas boiler; GLO | BC28: kgCO2eq/kW | BD28: 25.279029 | BE28: SSP2-PkBudg1000_2040 | BF28: na | BG28: na | BH28: na | BI28: na | BJ28: na | BK28: "capex_power_capacity_eur_per_kw", "opex_one_time_eur", "lifetime_yr","overall_efficiency", "opex_energy_eur_per_unit": report_VSE_2025; "ratios_in", "ratios_out": source_share; "lca_id", "lca_unit", "embedded_carbon_kgco2e_per_lca_unit", "lca_scenario": parameters_lca | BL28: True | BO28: No value in VSA | BX28: 23
A29: FALSE | D29: FALSE | E29: FALSE | F29: T_C_Conv_Thermal_ThermalBdg_CH4_2050 | G29: CH4_Heating_Buildings_2050 | I29: Gas Boiler | J29: Methane-fueled heating system for buildings. | K29: Heatpump | L29: Thermal | M29: Building | N29: Methane | O29: Conversion | Q29: 2050 | R29: CH | S29: CHF | U29: 9 | V29: =IF(U29="", "", IF(VALUE(LEFT(U29, 1))>=9, "Mature", IF(VALUE(LEFT(U29, 1))>=7, "Emerging", "Prototype"))) -> Mature | X29: FALSE | Y29: 0.93 | AA29: CH4 | AB29: na | AE29: 1 | AF29: kWh | AG29: ThBdg | AH29: ThBdg | AI29: ThBdg | AJ29: 0.93 | AK29: 0.93 | AL29: kWh | AO29: na | AP29: 0 | AQ29: 0 | AR29: 20 | AS29: 0 | AT29: 1900 | AU29: 0 | AV29: =+AW29/AT29% -> 6 | AW29: 114 | AX29: 0 | AZ29: FALSE | BA29: Low | BB29: market for gas boiler; GLO | BC29: kgCO2eq/kW | BD29: 18.382648 | BE29: SSP2-PkBudg1000_2050 | BF29: na | BG29: na | BH29: na | BI29: na | BJ29: na | BK29: "capex_power_capacity_eur_per_kw", "opex_one_time_eur", "lifetime_yr","overall_efficiency", "opex_energy_eur_per_unit": report_VSE_2025, linear_interpolation_2020_2050; "ratios_in", "ratios_out": source_share; "lca_id", "lca_unit", "embedded_carbon_kgco2e_per_lca_unit", "lca_scenario": parameters_lca | BL29: True | BO29: No value in VSA | BX29: 23
A30: FALSE | D30: FALSE | E30: FALSE | F30: T_C_Conv_Thermal_ThermalPhII_CH4_2020 | G30: CH4_Heating_ThermalPowerPlants_2020 | I30: Heat generation | J30: Methane-fueled heating system for thermal power plants. | K30: Gasfired Boiler | L30: Thermal | O30: Conversion | Q30: 2020 | R30: CH | S30: CHF | U30: 9 | V30: =IF(U30="", "", IF(VALUE(LEFT(U30, 1))>=9, "Mature", IF(VALUE(LEFT(U30, 1))>=7, "Emerging", "Prototype"))) -> Mature | X30: FALSE | Y30: 0.85 | AA30: CH4 | AB30: na | AE30: 1 | AF30: kWh | AG30: ThPhII | AH30: ThPhII | AI30: ThPhII | AJ30: 0.85 | AK30: 0.85 | AL30: kWh | AO30: na | AP30: 0 | AQ30: 0 | AR30: 25 | AS30: 0 | AT30: 300 | AU30: 0 | AV30: =+AW30/AT30% -> 3 | AW30: 9 | AX30: 0 | AZ30: FALSE | BA30: Low | BB30: market for gas boiler; GLO | BC30: kgCO2eq/kW | BD30: 45.141525 | BE30: SSP2-PkBudg1000_2025 | BF30: na | BG30: na | BH30: na | BI30: na | BJ30: na | BK30: "capex_power_capacity_eur_per_kw", "opex_one_time_eur", "overall_efficiency", "opex_energy_eur_per_unit" : report_VSE_2025; "lifetime_yr": report_VSE_2022; "ratios_in", "ratios_out": source_share; "lca_id", "lca_unit", "embedded_carbon_kgco2e_per_lca_unit", "lca_scenario": parameters_lca | BL30: True | BO30: Confirmed in VSE 2025 | BX30: 15
A31: FALSE | D31: FALSE | E31: FALSE | F31: T_C_Conv_Thermal_ThermalPhII_CH4_2030 | G31: CH4_Heating_ThermalPowerPlants_2030 | I31: Heat generation | J31: Methane-fueled heating system for thermal power plants. | K31: Gasfired Boiler | L31: Thermal | O31: Conversion | Q31: 2030 | R31: CH | S31: CHF | U31: 9 | V31: =IF(U31="", "", IF(VALUE(LEFT(U31, 1))>=9, "Mature", IF(VALUE(LEFT(U31, 1))>=7, "Emerging", "Prototype"))) -> Mature | X31: FALSE | Y31: 0.85 | AA31: CH4 | AB31: na | AE31: 1 | AF31: kWh | AG31: ThPhII | AH31: ThPhII | AI31: ThPhII | AJ31: 0.85 | AK31: 0.85 | AL31: kWh | AO31: na | AP31: 0 | AQ31: 0 | AR31: 25 | AS31: 0 | AT31: 300 | AU31: 0 | AV31: =+AW31/AT31% -> 3 | AW31: 9 | AX31: 0 | AZ31: FALSE | BA31: Low | BB31: market for gas boiler; GLO | BC31: kgCO2eq/kW | BD31: 37.919543 | BE31: SSP2-PkBudg1000_2030 | BF31: na | BG31: na | BH31: na | BI31: na | BJ31: na | BK31: "capex_power_capacity_eur_per_kw", "opex_one_time_eur", "overall_efficiency", "opex_energy_eur_per_unit" : report_VSE_2025, linear_interpolation_2020_2050; "lifetime_yr": report_VSE_2022; "ratios_in", "ratios_out": source_share; "lca_id", "lca_unit", "embedded_carbon_kgco2e_per_lca_unit", "lca_scenario": parameters_lca | BL31: True | BO31: Confirmed in VSE 2025 | BX31: 23 | CB31: =68+2*394.4+2*229 -> 1314.8
A32: FALSE | D32: FALSE | E32: FALSE | F32: T_C_Conv_Thermal_ThermalPhII_CH4_2040 | G32: CH4_Heating_ThermalPowerPlants_2040 | I32: Heat generation | J32: Methane-fueled heating system for thermal power plants. | K32: Gasfired Boiler | L32: Thermal | O32: Conversion | Q32: 2040 | R32: CH | S32: CHF | U32: 9 | V32: =IF(U32="", "", IF(VALUE(LEFT(U32, 1))>=9, "Mature", IF(VALUE(LEFT(U32, 1))>=7, "Emerging", "Prototype"))) -> Mature | X32: FALSE | Y32: 0.85 | AA32: CH4 | AB32: na | AE32: 1 | AF32: kWh | AG32: ThPhII | AH32: ThPhII | AI32: ThPhII | AJ32: 0.85 | AK32: 0.85 | AL32: kWh | AO32: na | AP32: 0 | AQ32: 0 | AR32: 25 | AS32: 0 | AT32: 300 | AU32: 0 | AV32: =+AW32/AT32% -> 3 | AW32: 9 | AX32: 0 | AZ32: FALSE | BA32: Low | BB32: market for gas boiler; GLO | BC32: kgCO2eq/kW | BD32: 25.279029 | BE32: SSP2-PkBudg1000_2040 | BF32: na | BG32: na | BH32: na | BI32: na | BJ32: na | BK32: "capex_power_capacity_eur_per_kw", "opex_one_time_eur", "overall_efficiency", "opex_energy_eur_per_unit" : report_VSE_2025, linear_interpolation_2020_2050; "lifetime_yr": report_VSE_2022; "ratios_in", "ratios_out": source_share; "lca_id", "lca_unit", "embedded_carbon_kgco2e_per_lca_unit", "lca_scenario": parameters_lca | BL32: True | BO32: Confirmed in VSE 2025 | BX32: 23
A33: FALSE | D33: FALSE | E33: FALSE | F33: T_C_Conv_Thermal_ThermalPhII_CH4_2050 | G33: CH4_Heating_ThermalPowerPlants_2050 | I33: Heat generation | J33: Methane-fueled heating system for thermal power plants. | K33: Gasfired Boiler | L33: Thermal | O33: Conversion | Q33: 2050 | R33: CH | S33: CHF | U33: 9 | V33: =IF(U33="", "", IF(VALUE(LEFT(U33, 1))>=9, "Mature", IF(VALUE(LEFT(U33, 1))>=7, "Emerging", "Prototype"))) -> Mature | X33: FALSE | Y33: 0.85 | AA33: CH4 | AB33: na | AE33: 1 | AF33: kWh | AG33: ThPhII | AH33: ThPhII | AI33: ThPhII | AJ33: 0.85 | AK33: 0.85 | AL33: kWh | AO33: na | AP33: 0 | AQ33: 0 | AR33: 25 | AS33: 0 | AT33: 300 | AU33: 0 | AV33: =+AW33/AT33% -> 3 | AW33: 9 | AX33: 0 | AZ33: FALSE | BA33: Low | BB33: market for gas boiler; GLO | BC33: kgCO2eq/kW | BD33: 18.382648 | BE33: SSP2-PkBudg1000_2050 | BF33: na | BG33: na | BH33: na | BI33: na | BJ33: na | BK33: "capex_power_capacity_eur_per_kw", "opex_one_time_eur", "overall_efficiency", "opex_energy_eur_per_unit" : report_VSE_2025; "lifetime_yr": report_VSE_2022; "ratios_in", "ratios_out": source_share; "lca_id", "lca_unit", "embedded_carbon_kgco2e_per_lca_unit", "lca_scenario": parameters_lca | BL33: True | BO33: Confirmed in VSE 2025
A34: FALSE | B34: Robin | C34: Eleonora | D34: FALSE | E34: FALSE | F34: T_C_Conv_Methane_Hydrogenation_CO2_Ch4_2020 | G34: CH4_Hydrogenation_2020 | I34: Methane synthesis | J34: Methane synthesis from H2 and CO2 via the thermo catalytic Sabatier reaction. | K34: Thermo-catalytic methanation reactor | L34: Methane | M34: Hydrogenation | N34: CO2 hydrogenation | O34: Conversion | P34: 5 | Q34: 2020 | R34: CH | S34: CHF | T34: 2025 | U34: 8 | V34: =IF(U34="", "", IF(VALUE(LEFT(U34, 1))>=9, "Mature", IF(VALUE(LEFT(U34, 1))>=7, "Emerging", "Prototype"))) -> Emerging | W34: Plant ready to operate | X34: TRUE | Y34: 0.78 | Z34: H2, CH4 | AA34: H2, CO2Sys | AB34: H2 | AE34: 1, 0.164 | AF34: kWh, kg | AG34: Ch4, ThHt, H2O | AH34: CH4, ThHt | AI34: Ch4 | AJ34: 0.83, 0.171, 0.134 | AK34: 0.83, 0.171 | AL34: kWh, kWh, kg | AM34: 0.83 | AN34: 300 | AO34: 0.83 | AQ34: 0 | AR34: 25 | AS34: 0 | AT34: 960 | AU34: 0 | AV34: 4 | AW34: =AT34*AV34% -> 38.4 | AX34: 0 | AZ34: FALSE | BA34: Medium | BB34: chemical factory construction, organics; RER | BC34: kgCO2eq/kg | BD34: 0.0402712 | BE34: SSP2-PkBudg1000_2025 | BF34: 377, 1746 | BG34: 1000, 0.1123 | BH34: 0.1257 | BI34: 0.0059 | BJ34: YES | BK34: "tech_maturity" ,"overall_efficiency", "lifetime_yr", "capex_power_capacity_eur_per_kw", "opex_one_time_eur", "reference_unit_size": paper_müller_PowerX_2025; "ratios_in", "ratios_out": conversion_parametrization;; "lca_id", "lca_unit", "embedded_carbon_kgco2e_per_lca_unit", "lca_scenario": parameters_lca | BL34: True | BM34: Completed | BO34: Differernt from VSE 2025 | BP34: 1400 | BQ34: =BP34/AT34-1 -> 0.45833333 | BR34: 135 | BS34: =BR34/AW34-1 -> 2.515625 | BX34: 15
A35: FALSE | B35: Robin | C35: Eleonora | D35: FALSE | E35: FALSE | F35: T_C_Conv_Methane_Hydrogenation_CO2_Ch4_2030 | G35: CH4_Hydrogenation_2030 | I35: Methane synthesis | J35: Methane synthesis from H2 and CO2 via the thermo catalytic Sabatier reaction. | K35: Thermo-catalytic methanation reactor | L35: Methane | M35: Hydrogenation | N35: CO2 hydrogenation | O35: Conversion | P35: 5 | Q35: 2030 | R35: CH | S35: CHF | T35: 2025 | U35: 8 | V35: =IF(U35="", "", IF(VALUE(LEFT(U35, 1))>=9, "Mature", IF(VALUE(LEFT(U35, 1))>=7, "Emerging", "Prototype"))) -> Emerging | W35: Plant ready to operate | X35: TRUE | Y35: 0.78 | Z35: H2, CH4 | AA35: H2, CO2Sys | AB35: H2 | AE35: 1, 0.164 | AF35: kWh, kg | AG35: Ch4, ThHt, H2O | AH35: CH4, ThHt | AI35: Ch4 | AJ35: 0.83, 0.171, 0.134 | AK35: 0.83, 0.171 | AL35: kWh, kWh, kg | AM35: 0.83 | AN35: 300 | AO35: 0.83 | AQ35: 0 | AR35: 25 | AS35: 0 | AT35: 750 | AU35: 0 | AV35: 4 | AW35: =AT35*AV35% -> 30 | AX35: 0 | AZ35: FALSE | BA35: Medium | BB35: chemical factory construction, organics; RER | BC35: kgCO2eq/kg | BD35: 0.0308859 | BE35: SSP2-PkBudg1000_2030 | BF35: 377, 1746 | BG35: 1000, 0.1123 | BH35: 0.1257 | BI35: 0.0059 | BJ35: YES | BK35: "tech_maturity", "overall_efficiency", "lifetime_yr", "capex_power_capacity_eur_per_kw", "opex_one_time_eur", "reference_unit_size": paper_müller_PowerX_2025; "ratios_in", "ratios_out": conversion_parametrization;; "lca_id", "lca_unit", "embedded_carbon_kgco2e_per_lca_unit", "lca_scenario": parameters_lca | BL35: True | BM35: Completed | BO35: Differernt from VSE 2025 | BP35: 1400 | BQ35: =BP35/AT35-1 -> 0.86666667 | BR35: 135 | BS35: =BR35/AW35-1 -> 3.5 | BX35: 15
A36: FALSE | B36: Robin | C36: Eleonora | D36: FALSE | E36: FALSE | F36: T_C_Conv_Methane_Hydrogenation_CO2_Ch4_2040 | G36: CH4_Hydrogenation_2040 | I36: Methane synthesis | J36: Methane synthesis from H2 and CO2 via the thermo catalytic Sabatier reaction. | K36: Thermo-catalytic methanation reactor | L36: Methane | M36: Hydrogenation | N36: CO2 hydrogenation | O36: Conversion | P36: 50 | Q36: 2040 | R36: CH | S36: CHF | T36: 2025 | U36: 8 | V36: =IF(U36="", "", IF(VALUE(LEFT(U36, 1))>=9, "Mature", IF(VALUE(LEFT(U36, 1))>=7, "Emerging", "Prototype"))) -> Emerging | W36: Plant ready to operate | X36: TRUE | Y36: 0.78 | Z36: H2, CH4 | AA36: H2, CO2Sys | AB36: H2 | AE36: 1, 0.164 | AF36: kWh, kg | AG36: Ch4, ThHt, H2O | AH36: CH4, ThHt | AI36: Ch4 | AJ36: 0.83, 0.171, 0.134 | AK36: 0.83, 0.171 | AL36: kWh, kWh, kg | AM36: 0.83 | AN36: 300 | AO36: 0.83 | AQ36: 0 | AR36: 25 | AS36: 0 | AT36: 560 | AU36: 0 | AV36: 4 | AW36: =AT36*AV36% -> 22.4 | AX36: 0 | AZ36: FALSE | BA36: Medium | BB36: chemical factory construction, organics; RER | BC36: kgCO2eq/kg | BD36: 0.0207865 | BE36: SSP2-PkBudg1000_2040 | BF36: 377, 1746 | BG36: 1000, 0.1123 | BH36: 0.1257 | BI36: 0.0059 | BJ36: YES | BK36: "tech_maturity", "overall_efficiency", "lifetime_yr", "capex_power_capacity_eur_per_kw", "opex_one_time_eur", "reference_unit_size": paper_müller_PowerX_2025; "ratios_in", "ratios_out": conversion_parametrization;; "lca_id", "lca_unit", "embedded_carbon_kgco2e_per_lca_unit", "lca_scenario": parameters_lca | BL36: True | BM36: Completed | BO36: Differernt from VSE 2025 | BP36: 1400 | BQ36: =BP36/AT36-1 -> 1.5 | BR36: 135 | BS36: =BR36/AW36-1 -> 5.0267857 | BX36: 15
A37: FALSE | B37: Robin | C37: Eleonora | D37: FALSE | E37: FALSE | F37: T_C_Conv_Methane_Hydrogenation_CO2_Ch4_2050 | G37: CH4_Hydrogenation_2050 | I37: Methane synthesis | J37: Methane synthesis from H2 and CO2 via the thermo catalytic Sabatier reaction. | K37: Thermo-catalytic methanation reactor | L37: Methane | M37: Hydrogenation | N37: CO2 hydrogenation | O37: Conversion | P37: 100 | Q37: 2050 | R37: CH | S37: CHF | T37: 2025 | U37: 8 | V37: =IF(U37="", "", IF(VALUE(LEFT(U37, 1))>=9, "Mature", IF(VALUE(LEFT(U37, 1))>=7, "Emerging", "Prototype"))) -> Emerging | W37: Plant ready to operate | X37: TRUE | Y37: 0.78 | Z37: H2, CH4 | AA37: H2, CO2Sys | AB37: H2 | AE37: 1, 0.164 | AF37: kWh, kg | AG37: Ch4, ThHt, H2O | AH37: CH4, ThHt | AI37: Ch4 | AJ37: 0.83, 0.171, 0.134 | AK37: 0.83, 0.171 | AL37: kWh, kWh, kg | AM37: 0.83 | AN37: 300 | AO37: 0.83 | AQ37: 0 | AR37: 25 | AS37: 0 | AT37: 450 | AU37: 0 | AV37: 4 | AW37: =AT37*AV37% -> 18 | AX37: 0 | AZ37: FALSE | BA37: Medium | BB37: chemical factory construction, organics; RER | BC37: kgCO2eq/kg | BD37: 0.0161196 | BE37: SSP2-PkBudg1000_2050 | BF37: 377, 1746 | BG37: 1000, 0.1123 | BH37: 0.1257 | BI37: 0.0059 | BJ37: YES | BK37: "tech_maturity", "overall_efficiency", "lifetime_yr", "capex_power_capacity_eur_per_kw", "opex_one_time_eur", "reference_unit_size": paper_müller_PowerX_2025; "ratios_in", "ratios_out": conversion_parametrization;; "lca_id", "lca_unit", "embedded_carbon_kgco2e_per_lca_unit", "lca_scenario": parameters_lca | BL37: True | BM37: Completed | BO37: Differernt from VSE 2025 | BP37: 1400 | BQ37: =BP37/AT37-1 -> 2.1111111 | BR37: 135 | BS37: =BR37/AW37-1 -> 6.5 | BX37: 15
A38: FALSE | B38: Gianfranco | D38: FALSE | E38: FALSE | F38: T_C_Conv_Elec_CH4_Ocgt_2050 | G38: CH4_OCGT_2050 | I38: Gas Turbine | J38: Methane-fueled open cycle gas turbine (OCGT) electricity generation (2030). | K38: OCGT | O38: Conversion | Q38: 2030 | R38: CH | S38: CHF | U38: 9 | V38: =IF(U38="", "", IF(VALUE(LEFT(U38, 1))>=9, "Mature", IF(VALUE(LEFT(U38, 1))>=7, "Emerging", "Prototype"))) -> Mature | X38: FALSE | Y38: 0.42 | AA38: CH4 | AB38: na | AE38: 1 | AF38: kWh | AG38: El13 | AH38: El13 | AI38: El13 | AJ38: 0.42 | AK38: 0.42 | AL38: kWh | AO38: na | AP38: 1500 | AQ38: 100000 | AR38: 23 | AS38: 0 | AT38: 489 | AU38: 0 | AV38: =+AW38/AT38% -> 4.2944785 | AW38: 21 | AX38: 0.002 | AZ38: FALSE | BA38: Low | BB38: micro gas turbine production, 100kW electrical; CH | BC38: kgCO2eq/kW | BD38: 62.633809 | BE38: SSP2-PkBudg1000_2050 | BF38: na | BG38: na | BH38: 0.06 | BI38: 0 | BJ38: YES | BK38: "capex_power_capacity_eur_per_kw", "opex_one_time_eur", "overall_efficiency", "opex_energy_eur_per_unit": report_VSE_2025; "lifetime_yr": report_VSE_2022; "ratios_in", "ratios_out": source_share; "lca_id", "lca_unit", "embedded_carbon_kgco2e_per_lca_unit", "lca_scenario": parameters_lca | BL38: True | BO38: Updated in line with VSE 2025 | BX38: 30
A39: FALSE | B39: na | D39: FALSE | E39: FALSE | F39: T_C_Conv_CarbonMonoxide_CO_Vent | G39: CO_Venting | J39: Carbon monoxide venting. | K39: Venitlator | O39: Conversion | R39: CH | S39: CHF | V39: =IF(U39="", "", IF(VALUE(LEFT(U39, 1))>=9, "Mature", IF(VALUE(LEFT(U39, 1))>=7, "Emerging", "Prototype"))) | X39: FALSE | AA39: CO | AB39: na | AE39: 1 | AF39: kWh | AG39: CO | AH39: CO | AI39: CO | AJ39: 0 | AK39: 0 | AL39: kg | AO39: na | AP39: 0 | AQ39: 0 | AR39: 25 | AS39: 0 | AT39: 1240 | AU39: 0 | AV39: 2.5 | AW39: =+AV39*AT39% -> 31 | AX39: 0.001 | AZ39: FALSE | BF39: na | BG39: na | BH39: na | BI39: na | BJ39: na | BK39: NO Sources Found; "ratios_in", "ratios_out": source_shares; "lca_id", "lca_unit", "embedded_carbon_kgco2e_per_lca_unit", "lca_scenario": parameters_lca | BL39: False | BO39: Not in VSE | BT39: 3000 | BU39: =BT39/AT39-1 -> 1.4193548 | BV39: 45 | BW39: =BV39/AW39-1 -> 0.4516129 | BX39: 45 | BY39: =BX39/AR39-1 -> 0.8
A40: FALSE | B40: Robin | C40: Gianfranco | D40: FALSE | E40: FALSE | F40: T_C_Net_CarbonDioxide_Pipeline_2050 (T_C_Net_CarbonDioxide_CO2Sys_CO2Exp) | G40: CO2_Pipeline_2050 | I40: CO2 transport | J40: Carbon Dioxide Pipeline | K40: Pipeline | L40: CO2 transport | M40: Pipeline | O40: Transport | P40: 2000 | Q40: 2050 | R40: CH | S40: CHF | T40: 2025 | V40: =IF(U40="", "", IF(VALUE(LEFT(U40, 1))>=9, "Mature", IF(VALUE(LEFT(U40, 1))>=7, "Emerging", "Prototype"))) | X40: FALSE | AA40: CO2Sys | AB40: CO2Sys | AE40: 1 | AF40: kg | AG40: CO2Exp | AH40: CO2Exp | AI40: CO2Exp | AJ40: 1 | AK40: 1 | AL40: kg | AO40: na | AP40: 0 | AQ40: 0 | AR40: 25 | AS40: 0 | AT40: 3300 | AU40: 0 | AV40: 12.045455 | AW40: 230 | AX40: 0.02 | AZ40: FALSE | BA40: High | BF40: na | BG40: na | BH40: na | BI40: na | BJ40: na | BK40: NO Sources Found; "ratios_in", "ratios_out": source_shares; "lca_id", "lca_unit", "embedded_carbon_kgco2e_per_lca_unit", "lca_scenario": parameters_lca | BL40: False | BT40: 3000 | BU40: =BT40/AT40-1 -> -0.090909091 | BV40: 45 | BW40: =BV40/AW40-1 -> -0.80434783 | BX40: 45 | BY40: =BX40/AR40-1 -> 0.8
A41: FALSE | B41: Jonas | C41: Robin | D41: FALSE | E41: FALSE | F41: T_C_Net_CarbonDioxide_RoadRail | G41: CO2_Roadrail | I41: CO2 transport | J41: Not in Tech description | K41: CO2 transport | L41: CO2 transport | M41: NonPipeline | O41: Transport | P41: 20 | R41: CHF | S41: CHF | T41: 2025 | V41: =IF(U41="", "", IF(VALUE(LEFT(U41, 1))>=9, "Mature", IF(VALUE(LEFT(U41, 1))>=7, "Emerging", "Prototype"))) | W41: FALSE | AB41: na | AE41: na | AF41: na | AI41: na | AJ41: na | AK41: na | AL41: na | AO41: na | AV41: =+AW41/AT41% -> #DIV/0! | AY41: FALSE | AZ41: Low | BF41: =IF(AE41="na","na","needs value") -> na | BG41: =IF(AF41="na","na","needs value") -> na | BH41: na | BI41: na | BJ41: na | BK41: NO Sources Found; "lca_id", "lca_unit", "embedded_carbon_kgco2e_per_lca_unit", "lca_scenario": parameters_lca | BL41: False | BO41: Not in VSE | BT41: 3000 | BU41: =BT41/AT41-1 -> #DIV/0! | BV41: 45 | BW41: =BV41/AW41-1 -> #DIV/0! | BX41: 45 | BY41: =BX41/AR41-1 -> #DIV/0!
A42: FALSE | B42: Jonas | C42: Robin | D42: FALSE | E42: FALSE | F42: T_C_Net_CarbonDioxide_RoadRail | G42: CO2_Roadrail | I42: CO2 transport | J42: Not in Tech description | K42: CO2 transport | L42: CO2 transport | M42: NonPipeline | O42: Transport | P42: 20 | R42: CHF | S42: CHF | T42: 2025 | V42: =IF(U42="", "", IF(VALUE(LEFT(U42, 1))>=9, "Mature", IF(VALUE(LEFT(U42, 1))>=7, "Emerging", "Prototype"))) | W42: FALSE | AB42: na | AE42: na | AF42: na | AI42: na | AJ42: na | AK42: na | AL42: na | AO42: na | AV42: =+AW42/AT42% -> #DIV/0! | AY42: FALSE | AZ42: Medium | BF42: =IF(AE42="na","na","needs value") -> na | BG42: =IF(AF42="na","na","needs value") -> na | BH42: na | BI42: na | BJ42: na | BK42: NO Sources Found; "lca_id", "lca_unit", "embedded_carbon_kgco2e_per_lca_unit", "lca_scenario": parameters_lca | BL42: False | BO42: Not in VSE
A43: TRUE | B43: Christian | C43: Robin | D43: FALSE | E43: FALSE | F43: T_C_CarbonMonoxide_ElecRR_CO2_CO | G43: CO2_RWGS_CO_ | I43: Electrochemical CO2 reduction | L43: Carbon Monoxide | M43: Electrochemical | O43: Conversion | R43: CH | S43: CHF | V43: =IF(U43="", "", IF(VALUE(LEFT(U43, 1))>=9, "Mature", IF(VALUE(LEFT(U43, 1))>=7, "Emerging", "Prototype"))) | X43: FALSE | AA43: CO2Sys, El47 | AB43: El47 | AE43: 1, 4 | AF43: kg, kWh | AG43: CO | AH43: CO | AI43: CO | AJ43: 0.625 | AK43: 0.625 | AL43: kg | AO43: na | AP43: 0 | AQ43: 0 | AR43: 30 | AS43: 0 | AT43: 3400 | AU43: 0 | AV43: =+AW43/AT43% -> 4 | AW43: 136 | AX43: 0 | AZ43: FALSE | BB43: electrolyzer production, 1MWe, SOEC, Stack; RER | BC43: kgCO2eq/kW | BD43: 71.796199 | BE43: SSP2-PkBudg1000_2025 | BF43: na | BG43: na | BK43: "capex_power_capacity_eur_per_kw", "opex_one_time_eur", "overall_efficiency", "opex_energy_eur_per_unit", "lifetime_yr": Allgoewer_2024 ; "ratios_in", "ratios_out": Allgoewer_2024; "lca_id", "lca_unit", "embedded_carbon_kgco2e_per_lca_unit", "lca_scenario": parameters_lca | BL43: True | BM43: CAPEX: 95.5 Meur for a capacity of 229.3 ktCO/y. It requires 6.3 kWh of electricity per t of CO. Efficiency: 0.625 kg CO/kg CO2 | BO43: VALUE FROM REVIEW VSE: Fischer Tropsch Reaction on the right
A44: FALSE | B44: na | D44: FALSE | E44: FALSE | F44: T_C_Conv_CarbonDioxide_CO2Sys_Vent | G44: CO2_Venting | J44: Carbon dioxide venting from the CO₂ system. | K44: General process unit | L44: na | O44: Conversion | Q44: na | R44: CH | S44: CHF | V44: =IF(U44="", "", IF(VALUE(LEFT(U44, 1))>=9, "Mature", IF(VALUE(LEFT(U44, 1))>=7, "Emerging", "Prototype"))) | X44: FALSE | AA44: CO2Sys | AB44: na | AE44: 1 | AF44: kg | AG44: CO2Sys | AH44: CO2Sys | AI44: CO2Sys | AJ44: 0 | AK44: 0 | AL44: kg | AO44: na | AP44: 0 | AQ44: 0 | AR44: 100 | AS44: 0 | AT44: 1 | AU44: 0 | AV44: =+AW44/AT44% -> 100 | AW44: 1 | AX44: 0.001 | AZ44: FALSE | BF44: na | BG44: na | BH44: na | BI44: na | BJ44: na | BK44: "ratios_in", "ratios_out": source_shares; "lca_id", "lca_unit", "embedded_carbon_kgco2e_per_lca_unit", "lca_scenario": parameters_lca | BL44: False | BO44: Not in VSE
A45: FALSE | B45: Partha | D45: FALSE | E45: FALSE | F45: T_C_NetCoupled_Net_Elec_El47_El13_2020 | G45: Coupled_Electricity_2020 | I45: Eletricity Transmission | J45: Coupled electricity network between El47 and El13. | K45: Grid | L45: Electricity | M45: Grid | N45: Transmission | O45: Transport | Q45: 2020 | R45: CH | S45: CHF | U45: 9 | V45: =IF(U45="", "", IF(VALUE(LEFT(U45, 1))>=9, "Mature", IF(VALUE(LEFT(U45, 1))>=7, "Emerging", "Prototype"))) -> Mature | X45: FALSE | Y45: 0.99 | AA45: El47 | AB45: na | AE45: 1 | AF45: kWh | AG45: El13 | AH45: El13 | AI45: =AG45 -> El13 | AJ45: 0.99 | AK45: 0.99 | AL45: kWh | AO45: na | AP45: 0 | AQ45: 0 | AR45: 35 | AS45: 0 | AT45: 0 | AU45: 0 | AW45: 0 | AX45: 0 | AZ45: FALSE | BA45: Low | BF45: na | BG45: na | BH45: na | BI45: na | BJ45: na | BK45: "capex_power_capacity_eur_per_kw", "opex_one_time_eur", "overall_efficiency", "opex_energy_eur_per_unit", "lifetime_yr", "trl_(1-9): report_VSE_2025; "ratios_in", "ratios_out": source_share; "lca_id", "lca_unit", "embedded_carbon_kgco2e_per_lca_unit", "lca_scenario": parameters_lca | BL45: False | BM45: From the data shared by Turhan previously range of transmission capacity (MVA): 216-100000. Range of line upgrade cost (CHF/MVA) 0.020954-1025600. Average line upgrade cost (CHF/MVA): 186072. | BO45: Not in VSE
A46: FALSE | B46: Partha | D46: FALSE | E46: FALSE | F46: T_C_NetCoupled_Net_Elec_El47_El13_2050 | G46: Coupled_Electricity_2050 | I46: Eletricity Transmission | J46: Coupled electricity network between El47 and El13. | K46: Grid | L46: Electricity | M46: Grid | N46: Transmission | O46: Transport | Q46: 2050 | R46: CH | S46: CHF | U46: 9 | V46: =IF(U46="", "", IF(VALUE(LEFT(U46, 1))>=9, "Mature", IF(VALUE(LEFT(U46, 1))>=7, "Emerging", "Prototype"))) -> Mature | X46: FALSE | Y46: 0.99 | AA46: El47 | AB46: na | AE46: 1 | AF46: kWh | AG46: El13 | AH46: El13 | AI46: =AG46 -> El13 | AJ46: 0.99 | AK46: 0.99 | AL46: kWh | AO46: na | AP46: 0 | AQ46: 0 | AR46: 35 | AS46: 0 | AT46: 0 | AU46: 0 | AW46: 0 | AX46: 0 | AZ46: FALSE | BA46: Low | BF46: na | BG46: na | BH46: na | BI46: na | BJ46: na | BK46: "capex_power_capacity_eur_per_kw", "opex_one_time_eur", "overall_efficiency", "opex_energy_eur_per_unit", "lifetime_yr", "trl_(1-9): report_VSE_2025; "ratios_in", "ratios_out": source_share; "lca_id", "lca_unit", "embedded_carbon_kgco2e_per_lca_unit", "lca_scenario": parameters_lca | BL46: False | BM46: From the data shared by Turhan previously range of transmission capacity (MVA): 216-100000. Range of line upgrade cost (CHF/MVA) 0.020954-1025600. Average line upgrade cost (CHF/MVA): 186072. | BO46: Not in VSE | BP46: 3000 | BQ46: =BP46/AT46-1 -> #DIV/0! | BR46: 30 | BS46: =BR46/AW46-1 -> #DIV/0! | BX46: 80 | BY46: =BX46/AR46-1 -> 1.2857143
A47: FALSE | B47: Partha | D47: FALSE | E47: FALSE | F47: T_C_NetCoupled_Elec_ElBdg_El47_2020 | G47: Coupled_Electricity_Buildings_2020 | I47: Eletricity Transmission | J47: Coupled electricity network between buildings and El47. | K47: Grid | L47: Electricity | M47: Grid | N47: Distribution | O47: Transport | Q47: 2020 | R47: CH | S47: CHF | U47: 9 | V47: =IF(U47="", "", IF(VALUE(LEFT(U47, 1))>=9, "Mature", IF(VALUE(LEFT(U47, 1))>=7, "Emerging", "Prototype"))) -> Mature | X47: FALSE | Y47: 0.96 | AA47: ElBdg | AB47: na | AE47: 1 | AF47: kWh | AG47: El47 | AH47: El47 | AI47: =AG47 -> El47 | AJ47: 0.96 | AK47: 0.96 | AL47: kWh | AO47: na | AQ47: 0 | AR47: 40 | AS47: 0 | AT47: 0 | AU47: 0 | AW47: 0 | AX47: 0 | AZ47: FALSE | BA47: Low | BF47: na | BG47: na | BH47: na | BI47: na | BJ47: na | BK47: "capex_power_capacity_eur_per_kw", "opex_one_time_eur", "overall_efficiency", "opex_energy_eur_per_unit", "lifetime_yr", "trl_(1-9): report_VSE_2025; "ratios_in", "ratios_out": source_share; "lca_id", "lca_unit", "embedded_carbon_kgco2e_per_lca_unit", "lca_scenario": parameters_lca | BL47: False | BM47: PSI does have any data to share for distribuition lines | BO47: Not in VSE | BP47: 3000 | BQ47: =BP47/AT47-1 -> #DIV/0! | BR47: 30 | BS47: =BR47/AW47-1 -> #DIV/0! | BX47: 80 | BY47: =BX47/AR47-1 -> 1
A48: FALSE | B48: Partha | D48: FALSE | E48: FALSE | F48: T_C_NetCoupled_Elec_ElBdg_El47_2050 | G48: Coupled_Electricity_Buildings_2050 | I48: Eletricity Transmission | J48: Coupled electricity network between buildings and El47. | K48: Grid | L48: Electricity | M48: Grid | N48: Distribution | O48: Transport | Q48: 2050 | R48: CH | S48: CHF | U48: 9 | V48: =IF(U48="", "", IF(VALUE(LEFT(U48, 1))>=9, "Mature", IF(VALUE(LEFT(U48, 1))>=7, "Emerging", "Prototype"))) -> Mature | X48: FALSE | Y48: 0.96 | AA48: ElBdg | AB48: na | AE48: 1 | AF48: kWh | AG48: El47 | AH48: El47 | AI48: =AG48 -> El47 | AJ48: 0.96 | AK48: 0.96 | AL48: kWh | AO48: na | AQ48: 0 | AR48: 40 | AS48: 0 | AT48: 0 | AU48: 0 | AW48: 0 | AX48: 0 | AZ48: FALSE | BA48: Low | BF48: na | BG48: na | BH48: na | BI48: na | BJ48: na | BK48: "capex_power_capacity_eur_per_kw", "opex_one_time_eur", "overall_efficiency", "opex_energy_eur_per_unit", "lifetime_yr", "trl_(1-9): report_VSE_2025; "ratios_in", "ratios_out": source_share; "lca_id", "lca_unit", "embedded_carbon_kgco2e_per_lca_unit", "lca_scenario": parameters_lca | BL48: False | BM48: PSI does have any data to share for distribuition lines | BO48: Not in VSE | BP48: 3000 | BQ48: =BP48/AT48-1 -> #DIV/0! | BR48: 30 | BS48: =BR48/AW48-1 -> #DIV/0! | BX48: 80 | BY48: =BX48/AR48-1 -> 1
A49: TRUE | B49: Partha | D49: FALSE | E49: FALSE | F49: T_C_NetCoupled_Elec_ElRest_El47_2020 | G49: Coupled_Electricity_Node47_ToRest_2050 | I49: Eletricity Transmission | J49: Coupled electricity network between other electricity nodes and El47. | K49: Grid | L49: Electricity | M49: Grid | N49: Distribution | O49: Transport | Q49: 2020 | R49: CH | S49: CHF | U49: 9 | V49: =IF(U49="", "", IF(VALUE(LEFT(U49, 1))>=9, "Mature", IF(VALUE(LEFT(U49, 1))>=7, "Emerging", "Prototype"))) -> Mature | W49: Plant ready to operate | X49: FALSE | Y49: 0.99 | AA49: ElRest | AB49: na | AE49: 1 | AF49: kWh | AG49: El47 | AH49: El47 | AI49: =AG49 -> El47 | AJ49: 0.99 | AK49: 0.99 | AL49: kWh | AO49: na | AP49: 0 | AQ49: 0 | AS49: 0 | AT49: 0 | AU49: 0 | AW49: 0 | AX49: 0 | AZ49: FALSE | BA49: Low | BF49: na | BG49: na | BH49: na | BI49: na | BJ49: na | BK49: "capex_power_capacity_eur_per_kw", "opex_one_time_eur", "overall_efficiency", "opex_energy_eur_per_unit", "lifetime_yr", "trl_(1-9): report_VSE_2025; "ratios_in", "ratios_out": source_share; "lca_id", "lca_unit", "embedded_carbon_kgco2e_per_lca_unit", "lca_scenario": parameters_lca | BL49: False | BM49: PSI does have any data to share for distribuition lines | BO49: Not in VSE | BP49: 3000 | BQ49: =BP49/AT49-1 -> #DIV/0! | BR49: 30 | BS49: =BR49/AW49-1 -> #DIV/0! | BX49: 80 | BY49: =BX49/AR49-1 -> #DIV/0!
A50: TRUE | B50: Partha | D50: FALSE | E50: FALSE | F50: T_C_NetCoupled_Elec_ElRest_El47_2050 | G50: Coupled_Electricity_Node47_ToRest_2050 | I50: Eletricity Transmission | J50: Coupled electricity network between other electricity nodes and El47. | K50: Grid | L50: Electricity | M50: Grid | N50: Distribution | O50: Transport | Q50: 2050 | R50: CH | S50: CHF | U50: 9 | V50: =IF(U50="", "", IF(VALUE(LEFT(U50, 1))>=9, "Mature", IF(VALUE(LEFT(U50, 1))>=7, "Emerging", "Prototype"))) -> Mature | W50: Plant ready to operate | X50: FALSE | Y50: 0.99 | AA50: ElRest | AB50: na | AE50: 1 | AF50: kWh | AG50: El47 | AH50: El47 | AI50: =AG50 -> El47 | AJ50: 0.99 | AK50: 0.99 | AL50: kWh | AO50: na | AP50: 0 | AQ50: 0 | AS50: 0 | AT50: 0 | AU50: 0 | AW50: 0 | AX50: 0 | AZ50: FALSE | BA50: Low | BF50: na | BG50: na | BH50: na | BI50: na | BJ50: na | BK50: "capex_power_capacity_eur_per_kw", "opex_one_time_eur", "overall_efficiency", "opex_energy_eur_per_unit", "lifetime_yr", "trl_(1-9): report_VSE_2025; "ratios_in", "ratios_out": source_share; "lca_id", "lca_unit", "embedded_carbon_kgco2e_per_lca_unit", "lca_scenario": parameters_lca | BL50: False | BM50: PSI does have any data to share for distribuition lines | BO50: Not in VSE
A51: FALSE | D51: FALSE | E51: FALSE | F51: T_C_Conv_Thermal_Csw_ThPhII_2020 | G51: CSW_Thermal_2020 | I51: Heat generation | J51: Waste-fueled thermal energy generation in power plants. | K51: Incineration Plant | L51: Thermal | M51: Process | N51: Waste | O51: Conversion | Q51: 2020 | R51: CH | S51: CHF | V51: =IF(U51="", "", IF(VALUE(LEFT(U51, 1))>=9, "Mature", IF(VALUE(LEFT(U51, 1))>=7, "Emerging", "Prototype"))) | X51: FALSE | Y51: 0.85 | AA51: Csw | AB51: na | AE51: 1 | AF51: kWh | AG51: ThPhII | AH51: ThPhII | AI51: ThPhII | AJ51: 0.85 | AK51: 0.85 | AL51: kWh | AO51: na | AP51: 0 | AQ51: 0 | AR51: 25 | AS51: 0 | AT51: 650 | AU51: 0 | AV51: =+AW51/AT51% -> 2 | AW51: 13 | AX51: 0 | AZ51: FALSE | BA51: Low | BF51: na | BG51: na | BH51: na | BI51: na | BJ51: na | BK51: "capex_power_capacity_eur_per_kw", "opex_one_time_eur", "opex_energy_eur_per_unit": report_VSE_2025; "lifetime_yr", "overall_efficiency": report_VSE_2022; "ratios_in", "ratios_out": source_share; "lca_id", "lca_unit", "embedded_carbon_kgco2e_per_lca_unit", "lca_scenario": parameters_lca | BL51: False | BO51: Confirmed in VSE 2025
A52: FALSE | D52: FALSE | E52: FALSE | F52: T_C_Conv_Thermal_Csw_ThPhII_2050 | G52: CSW_Thermal_2050 | I52: Heat generation | J52: Waste-fueled thermal energy generation in power plants. | K52: Incineration Plant | L52: Thermal | M52: Process | N52: Waste | O52: Conversion | Q52: 2050 | R52: CH | S52: CHF | V52: =IF(U52="", "", IF(VALUE(LEFT(U52, 1))>=9, "Mature", IF(VALUE(LEFT(U52, 1))>=7, "Emerging", "Prototype"))) | X52: FALSE | Y52: 0.85 | AA52: Csw | AB52: na | AE52: 1 | AF52: kWh | AG52: ThPhII | AH52: ThPhII | AI52: ThPhII | AJ52: 0.85 | AK52: 0.85 | AL52: kWh | AO52: na | AP52: 0 | AQ52: 0 | AR52: 25 | AS52: 0 | AT52: 650 | AU52: 0 | AV52: =+AW52/AT52% -> 2 | AW52: 13 | AX52: 0 | AZ52: FALSE | BA52: Low | BF52: na | BG52: na | BH52: na | BI52: na | BJ52: na | BK52: "capex_power_capacity_eur_per_kw", "opex_one_time_eur", "opex_energy_eur_per_unit": report_VSE_2025; "lifetime_yr", "overall_efficiency": report_VSE_2022; "ratios_in", "ratios_out": source_share; "lca_id", "lca_unit", "embedded_carbon_kgco2e_per_lca_unit", "lca_scenario": parameters_lca | BL52: False | BO52: Confirmed in VSE 2025
A53: FALSE | D53: FALSE | E53: FALSE | F53: T_C_Conv_Thermal_ThermalBdg_El_2020 | G53: Electric_Heating_Buildings_2020 | I53: Heat generation | J53: Electric heating system for buildings. | K53: Heatpump | L53: Thermal | O53: Conversion | Q53: 2020 | R53: CH | S53: CHF | U53: 9 | V53: =IF(U53="", "", IF(VALUE(LEFT(U53, 1))>=9, "Mature", IF(VALUE(LEFT(U53, 1))>=7, "Emerging", "Prototype"))) -> Mature | X53: FALSE | AA53: ElBdg | AB53: na | AE53: 1 | AF53: kWh | AG53: ThBdg | AH53: ThBdg | AI53: ThBdg | AJ53: 1 | AK53: 1 | AL53: kWh | AO53: na | AP53: 5 | AQ53: 5 | AR53: 25 | AS53: 0 | AT53: 65 | AU53: 0 | AV53: =+AW53/AT53% -> 1.5384615 | AW53: 1 | AX53: 0.001 | AZ53: FALSE | BA53: Low | BB53: auxiliary heating unit production, electric, 5kW; CH | BC53: kgCO2eq/kW | BD53: 1.2863636 | BE53: SSP2-PkBudg1000_2025 | BF53: na | BG53: na | BH53: na | BI53: na | BJ53: na | BK53: "capex_power_capacity_eur_per_kw", "opex_one_time_eur", "opex_energy_eur_per_unit": report_VSE_2025; "lifetime_yr": report_VSE_2022; "ratios_in", "ratios_out": source_share; "lca_id", "lca_unit", "embedded_carbon_kgco2e_per_lca_unit", "lca_scenario": parameters_lca | BL53: True | BO53: Confirmed in VSE 2025
A54: FALSE | D54: FALSE | E54: FALSE | F54: T_C_Conv_Thermal_ThermalBdg_El_2030 | G54: Electric_Heating_Buildings_2030 | I54: Heat generation | J54: Electric heating system for buildings. | K54: Heatpump | L54: Thermal | O54: Conversion | Q54: 2030 | R54: CH | S54: CHF | U54: 9 | V54: =IF(U54="", "", IF(VALUE(LEFT(U54, 1))>=9, "Mature", IF(VALUE(LEFT(U54, 1))>=7, "Emerging", "Prototype"))) -> Mature | X54: FALSE | AA54: ElBdg | AB54: na | AE54: 1 | AF54: kWh | AG54: ThBdg | AH54: ThBdg | AI54: ThBdg | AJ54: 1 | AK54: 1 | AL54: kWh | AO54: na | AP54: 5 | AQ54: 5 | AR54: 25 | AS54: 0 | AT54: 65 | AU54: 0 | AV54: =+AW54/AT54% -> 1.5384615 | AW54: 1 | AX54: 0.001 | AZ54: FALSE | BA54: Low | BB54: auxiliary heating unit production, electric, 5kW; CH | BC54: kgCO2eq/kW | BD54: 1.0836896 | BE54: SSP2-PkBudg1000_2030 | BF54: na | BG54: na | BH54: na | BI54: na | BJ54: na | BK54: "capex_power_capacity_eur_per_kw", "opex_one_time_eur", "opex_energy_eur_per_unit": report_VSE_2025, linear_interpolation_2020_2050; "lifetime_yr": report_VSE_2022; "ratios_in", "ratios_out": source_share; "lca_id", "lca_unit", "embedded_carbon_kgco2e_per_lca_unit", "lca_scenario": parameters_lca | BL54: True | BO54: Confirmed in VSE 2025
A55: FALSE | D55: FALSE | E55: FALSE | F55: T_C_Conv_Thermal_ThermalBdg_El_2040 | G55: Electric_Heating_Buildings_2040 | I55: Heat generation | J55: Electric heating system for buildings. | K55: Heatpump | L55: Thermal | O55: Conversion | Q55: 2040 | R55: CH | S55: CHF | U55: 9 | V55: =IF(U55="", "", IF(VALUE(LEFT(U55, 1))>=9, "Mature", IF(VALUE(LEFT(U55, 1))>=7, "Emerging", "Prototype"))) -> Mature | X55: FALSE | AA55: ElBdg | AB55: na | AE55: 1 | AF55: kWh | AG55: ThBdg | AH55: ThBdg | AI55: ThBdg | AJ55: 1 | AK55: 1 | AL55: kWh | AO55: na | AP55: 5 | AQ55: 5 | AR55: 25 | AS55: 0 | AT55: 65 | AU55: 0 | AV55: =+AW55/AT55% -> 1.5384615 | AW55: 1 | AX55: 0.001 | AZ55: FALSE | BA55: Low | BB55: auxiliary heating unit production, electric, 5kW; CH | BC55: kgCO2eq/kW | BD55: 0.7311175 | BE55: SSP2-PkBudg1000_2040 | BF55: na | BG55: na | BH55: na | BI55: na | BJ55: na | BK55: "capex_power_capacity_eur_per_kw", "opex_one_time_eur", "opex_energy_eur_per_unit": report_VSE_2025, linear_interpolation_2020_2050; "lifetime_yr": report_VSE_2022; "ratios_in", "ratios_out": source_share; "lca_id", "lca_unit", "embedded_carbon_kgco2e_per_lca_unit", "lca_scenario": parameters_lca | BL55: True | BO55: Confirmed in VSE 2025
A56: FALSE | D56: FALSE | E56: FALSE | F56: T_C_Conv_Thermal_ThermalBdg_El_2050 | G56: Electric_Heating_Buildings_2050 | I56: Heat generation | J56: Electric heating system for buildings. | K56: Heatpump | L56: Thermal | O56: Conversion | Q56: 2050 | R56: CH | S56: CHF | U56: 9 | V56: =IF(U56="", "", IF(VALUE(LEFT(U56, 1))>=9, "Mature", IF(VALUE(LEFT(U56, 1))>=7, "Emerging", "Prototype"))) -> Mature | X56: FALSE | AA56: ElBdg | AB56: na | AE56: 1 | AF56: kWh | AG56: ThBdg | AH56: ThBdg | AI56: ThBdg | AJ56: 1 | AK56: 1 | AL56: kWh | AO56: na | AP56: 5 | AQ56: 5 | AR56: 25 | AS56: 0 | AT56: 65 | AU56: 0 | AV56: =+AW56/AT56% -> 1.5384615 | AW56: 1 | AX56: 0.001 | AZ56: FALSE | BA56: Low | BB56: auxiliary heating unit production, electric, 5kW; CH | BC56: kgCO2eq/kW | BD56: 0.5678847 | BE56: SSP2-PkBudg1000_2050 | BF56: na | BG56: na | BH56: na | BI56: na | BJ56: na | BK56: "capex_power_capacity_eur_per_kw", "opex_one_time_eur", "opex_energy_eur_per_unit": report_VSE_2025; "lifetime_yr": report_VSE_2022; "ratios_in", "ratios_out": source_share; "lca_id", "lca_unit", "embedded_carbon_kgco2e_per_lca_unit", "lca_scenario": parameters_lca | BL56: True | BO56: Confirmed in VSE 2025
A57: FALSE | D57: FALSE | E57: FALSE | F57: T_C_Conv_Thermal_ThermalPhII_El_2020 | G57: Electric_Heating_ThermalPowerPlants_2020 | I57: Heat generation | J57: Electric heating system for thermal power plants. | K57: Heat Pump | L57: Thermal | O57: Conversion | Q57: 2020 | R57: CH | S57: CHF | U57: 9 | V57: =IF(U57="", "", IF(VALUE(LEFT(U57, 1))>=9, "Mature", IF(VALUE(LEFT(U57, 1))>=7, "Emerging", "Prototype"))) -> Mature | X57: FALSE | Y57: 0.85 | AA57: ElRest | AB57: na | AE57: 1 | AF57: kWh | AG57: ThPhII | AH57: ThPhII | AI57: ThPhII | AJ57: 0.85 | AK57: 0.85 | AL57: kWh | AO57: na | AP57: 0 | AQ57: 0 | AR57: 30 | AS57: 0 | AT57: 275 | AU57: 0 | AV57: =+AW57/AT57% -> 0.50909091 | AW57: 1.4 | AX57: 0 | AZ57: FALSE | BA57: Low | BB57: auxiliary heating unit production, electric, 5kW; CH | BC57: kgCO2eq/kW | BD57: 1.2863636 | BE57: SSP2-PkBudg1000_2025 | BF57: na | BG57: na | BH57: na | BI57: na | BJ57: na | BK57: "capex_power_capacity_eur_per_kw", "opex_one_time_eur", "lifetime_yr", "opex_energy_eur_per_unit": report_VSE_2025; "overall_efficiency": report_VSE_2022; "ratios_in", "ratios_out": source_share; "lca_id", "lca_unit", "embedded_carbon_kgco2e_per_lca_unit", "lca_scenario": parameters_lca | BL57: True | BO57: Confirmed in VSE 2025
A58: FALSE | D58: FALSE | E58: FALSE | F58: T_C_Conv_Thermal_ThermalPhII_El_2030 | G58: Electric_Heating_ThermalPowerPlants_2030 | I58: Heat generation | J58: Electric heating system for thermal power plants. | K58: Heat Pump | L58: Thermal | O58: Conversion | Q58: 2030 | R58: CH | S58: CHF | U58: 9 | V58: =IF(U58="", "", IF(VALUE(LEFT(U58, 1))>=9, "Mature", IF(VALUE(LEFT(U58, 1))>=7, "Emerging", "Prototype"))) -> Mature | X58: FALSE | Y58: 0.85 | AA58: ElRest | AB58: na | AE58: 1 | AF58: kWh | AG58: ThPhII | AH58: ThPhII | AI58: ThPhII | AJ58: 0.85 | AK58: 0.85 | AL58: kWh | AO58: na | AP58: 0 | AQ58: 0 | AR58: 30 | AS58: 0 | AT58: 275 | AU58: 0 | AV58: =+AW58/AT58% -> 0.50909091 | AW58: 1.4 | AX58: 0 | AZ58: FALSE | BA58: Low | BB58: auxiliary heating unit production, electric, 5kW; CH | BC58: kgCO2eq/kW | BD58: 1.0836896 | BE58: SSP2-PkBudg1000_2030 | BF58: na | BG58: na | BH58: na | BI58: na | BJ58: na | BK58: "capex_power_capacity_eur_per_kw", "opex_one_time_eur", "lifetime_yr", "opex_energy_eur_per_unit": report_VSE_2025, linear_interpolation_2020_2050; "overall_efficiency": report_VSE_2022; "ratios_in", "ratios_out": source_share; "lca_id", "lca_unit", "embedded_carbon_kgco2e_per_lca_unit", "lca_scenario": parameters_lca | BL58: True | BO58: Confirmed in VSE 2025
A59: FALSE | D59: FALSE | E59: FALSE | F59: T_C_Conv_Thermal_ThermalPhII_El_2040 | G59: Electric_Heating_ThermalPowerPlants_2040 | I59: Heat generation | J59: Electric heating system for thermal power plants. | K59: Heat Pump | L59: Thermal | O59: Conversion | Q59: 2040 | R59: CH | S59: CHF | U59: 9 | V59: =IF(U59="", "", IF(VALUE(LEFT(U59, 1))>=9, "Mature", IF(VALUE(LEFT(U59, 1))>=7, "Emerging", "Prototype"))) -> Mature | X59: FALSE | Y59: 0.85 | AA59: ElRest | AB59: na | AE59: 1 | AF59: kWh | AG59: ThPhII | AH59: ThPhII | AI59: ThPhII | AJ59: 0.85 | AK59: 0.85 | AL59: kWh | AO59: na | AP59: 0 | AQ59: 0 | AR59: 30 | AS59: 0 | AT59: 275 | AU59: 0 | AV59: =+AW59/AT59% -> 0.50909091 | AW59: 1.4 | AX59: 0 | AZ59: FALSE | BA59: Low | BB59: auxiliary heating unit production, electric, 5kW; CH | BC59: kgCO2eq/kW | BD59: 0.7311175 | BE59: SSP2-PkBudg1000_2040 | BF59: na | BG59: na | BH59: na | BI59: na | BJ59: na | BK59: "capex_power_capacity_eur_per_kw", "opex_one_time_eur", "lifetime_yr", "opex_energy_eur_per_unit": report_VSE_2025, linear_interpolation_2020_2050; "overall_efficiency": report_VSE_2022; "ratios_in", "ratios_out": source_share; "lca_id", "lca_unit", "embedded_carbon_kgco2e_per_lca_unit", "lca_scenario": parameters_lca | BL59: True | BO59: Confirmed in VSE 2025
A60: FALSE | D60: FALSE | E60: FALSE | F60: T_C_Conv_Thermal_ThermalPhII_El_2050 | G60: Electric_Heating_ThermalPowerPlants_2050 | I60: Heat generation | J60: Electric heating system for thermal power plants. | K60: Heat Pump | L60: Thermal | O60: Conversion | Q60: 2050 | R60: CH | S60: CHF | U60: 9 | V60: =IF(U60="", "", IF(VALUE(LEFT(U60, 1))>=9, "Mature", IF(VALUE(LEFT(U60, 1))>=7, "Emerging", "Prototype"))) -> Mature | X60: FALSE | Y60: 0.85 | AA60: ElRest | AB60: na | AE60: 1 | AF60: kWh | AG60: ThPhII | AH60: ThPhII | AI60: ThPhII | AJ60: 0.85 | AK60: 0.85 | AL60: kWh | AO60: na | AP60: 0 | AQ60: 0 | AR60: 30 | AS60: 0 | AT60: 275 | AU60: 0 | AV60: =+AW60/AT60% -> 0.50909091 | AW60: 1.4 | AX60: 0 | AZ60: FALSE | BA60: Low | BB60: auxiliary heating unit production, electric, 5kW; CH | BC60: kgCO2eq/kW | BD60: 0.5678847 | BE60: SSP2-PkBudg1000_2050 | BF60: na | BG60: na | BH60: na | BI60: na | BJ60: na | BK60: "capex_power_capacity_eur_per_kw", "opex_one_time_eur", "lifetime_yr", "opex_energy_eur_per_unit": report_VSE_2025; "overall_efficiency": report_VSE_2022; "ratios_in", "ratios_out": source_share; "lca_id", "lca_unit", "embedded_carbon_kgco2e_per_lca_unit", "lca_scenario": parameters_lca | BL60: True | BO60: Confirmed in VSE 2025
A61: FALSE | B61: Partha | D61: FALSE | E61: FALSE | F61: T_C_Net_Elec_El13_El47_2020 | G61: Electrical_Transmission_2020 | I61: Eletricity Transmission | J61: =IFERROR(VLOOKUP(F61,#REF!,2,FALSE),"Not in Tech description") -> Not in Tech description | K61: Transformer | L61: Electricity | M61: Grid | N61: Transmission | O61: Transport | Q61: 2020 | R61: CH | S61: CHF | U61: 9 | V61: =IF(U61="", "", IF(VALUE(LEFT(U61, 1))>=9, "Mature", IF(VALUE(LEFT(U61, 1))>=7, "Emerging", "Prototype"))) -> Mature | X61: FALSE | Y61: 0.99 | AA61: El13 | AB61: na | AE61: 1 | AF61: kWh | AG61: El47 | AH61: El47 | AI61: =AG61 -> El47 | AJ61: =Y61 -> 0.99 | AK61: =Z61 -> 0 | AL61: kWh | AO61: na | AP61: 0 | AQ61: 0 | AR61: 35 | AS61: 0 | AT61: 354 | AU61: 10 | AV61: =AU61/AT61*100 -> 2.8248588 | AW61: 0 | AX61: 0.001 | AZ61: FALSE | BA61: Low | BB61: transformer production, high voltage use; GLO | BC61: kgCO2eq/kg | BD61: 1.4215357 | BE61: SSP2-PkBudg1000_2025 | BF61: na | BG61: na | BH61: na | BI61: na | BJ61: na | BK61: "capex_power_capacity_eur_per_kw", "opex_one_time_eur", "overall_efficiency", "opex_energy_eur_per_unit", "lifetime_yr", "trl_(1-9): report_VSE_2025; "ratios_in", "ratios_out": source_share; "lca_id", "lca_unit", "embedded_carbon_kgco2e_per_lca_unit", "lca_scenario": parameters_lca | BL61: True | BM61: From the data shared by Turhan previously range of transmission line capacity (MVA): 216-100000. Range of line upgrade cost (CHF/MVA) 0.020954-1025600. Average line upgrade cost (CHF/MVA): 186072. | BO61: Not in VSE
A62: FALSE | B62: Partha | D62: FALSE | E62: FALSE | F62: T_C_Net_Elec_El13_El47_2040 | G62: Electrical_Transmission_2030 | I62: Eletricity Transmission | J62: =IFERROR(VLOOKUP(F62,#REF!,2,FALSE),"Not in Tech description") -> Not in Tech description | K62: Transformer | L62: Electricity | M62: Grid | N62: Transmission | O62: Transport | Q62: 2030 | R62: CH | S62: CHF | U62: 9 | V62: =IF(U62="", "", IF(VALUE(LEFT(U62, 1))>=9, "Mature", IF(VALUE(LEFT(U62, 1))>=7, "Emerging", "Prototype"))) -> Mature | X62: FALSE | Y62: 0.99 | AA62: El13 | AB62: na | AE62: 1 | AF62: kWh | AG62: El47 | AH62: El47 | AI62: =AG62 -> El47 | AJ62: =Y62 -> 0.99 | AK62: =Z62 -> 0 | AL62: kWh | AO62: na | AP62: 0 | AQ62: 0 | AR62: 35 | AS62: 0 | AT62: =AT61+(AT64-AT61)/30*10 -> 472.33333 | AU62: =+$AU$5+($AU$8-$AU$5)/30*10 -> 0 | AV62: =AU62/AT62*100 -> 0 | AW62: 0 | AX62: 0.001 | AZ62: FALSE | BA62: Low | BB62: transformer production, high voltage use; GLO | BC62: kgCO2eq/kg | BD62: 1.0527592 | BE62: SSP2-PkBudg1000_2040 | BF62: na | BG62: na | BH62: na | BI62: na | BJ62: na | BK62: "capex_power_capacity_eur_per_kw", "opex_one_time_eur", "overall_efficiency", "opex_energy_eur_per_unit", "lifetime_yr", "trl_(1-9): report_VSE_2025, linear_interpolation_2020_2050; "ratios_in", "ratios_out": source_share; "lca_id", "lca_unit", "embedded_carbon_kgco2e_per_lca_unit", "lca_scenario": parameters_lca | BL62: True | BM62: From the data shared by Turhan previously range of transmission line capacity (MVA): 216-100000. Range of line upgrade cost (CHF/MVA) 0.020954-1025600. Average line upgrade cost (CHF/MVA): 186072. | BO62: Not in VSE
A63: FALSE | B63: Partha | D63: FALSE | E63: FALSE | F63: T_C_Net_Elec_El13_El47_2030 | G63: Electrical_Transmission_2040 | I63: Eletricity Transmission | J63: =IFERROR(VLOOKUP(F63,#REF!,2,FALSE),"Not in Tech description") -> Not in Tech description | K63: Transformer | L63: Electricity | M63: Grid | N63: Transmission | O63: Transport | Q63: 2040 | R63: CH | S63: CHF | U63: 9 | V63: =IF(U63="", "", IF(VALUE(LEFT(U63, 1))>=9, "Mature", IF(VALUE(LEFT(U63, 1))>=7, "Emerging", "Prototype"))) -> Mature | X63: FALSE | Y63: 0.99 | AA63: El13 | AB63: na | AE63: 1 | AF63: kWh | AG63: El47 | AH63: El47 | AI63: =AG63 -> El47 | AJ63: =Y63 -> 0.99 | AK63: =Z63 -> 0 | AL63: kWh | AO63: na | AP63: 0 | AQ63: 0 | AR63: 35 | AS63: 0 | AT63: =AT61+(AT64-AT61)/30*20 -> 590.66667 | AU63: =+$AU$5+($AU$8-$AU$5)/30*20 -> 0 | AV63: =AU63/AT63*100 -> 0 | AW63: 0 | AX63: 0.001 | AZ63: FALSE | BA63: Low | BB63: transformer production, high voltage use; GLO | BC63: kgCO2eq/kg | BD63: 1.2753256 | BE63: SSP2-PkBudg1000_2030 | BF63: na | BG63: na | BH63: na | BI63: na | BJ63: na | BK63: "capex_power_capacity_eur_per_kw", "opex_one_time_eur", "overall_efficiency", "opex_energy_eur_per_unit", "lifetime_yr", "trl_(1-9): report_VSE_2025, linear_interpolation_2020_2050; "ratios_in", "ratios_out": source_share; "lca_id", "lca_unit", "embedded_carbon_kgco2e_per_lca_unit", "lca_scenario": parameters_lca | BL63: True | BM63: From the data shared by Turhan previously range of transmission line capacity (MVA): 216-100000. Range of line upgrade cost (CHF/MVA) 0.020954-1025600. Average line upgrade cost (CHF/MVA): 186072. | BO63: Not in VSE | BP63: 2700 | BQ63: - | BR63: 81 | BS63: -
A64: FALSE | B64: Partha | D64: FALSE | E64: FALSE | F64: T_C_Net_Elec_El13_El47_2050 | G64: Electrical_Transmission_2050 | I64: Eletricity Transmission | J64: =IFERROR(VLOOKUP(F64,#REF!,2,FALSE),"Not in Tech description") -> Not in Tech description | K64: Transformer | L64: Electricity | M64: Grid | N64: Transmission | O64: Transport | Q64: 2050 | R64: CH | S64: CHF | U64: 9 | V64: =IF(U64="", "", IF(VALUE(LEFT(U64, 1))>=9, "Mature", IF(VALUE(LEFT(U64, 1))>=7, "Emerging", "Prototype"))) -> Mature | X64: FALSE | Y64: 0.99 | AA64: El13 | AB64: na | AE64: 1 | AF64: kWh | AG64: El47 | AH64: El47 | AI64: =AG64 -> El47 | AJ64: =Y64 -> 0.99 | AK64: =Z64 -> 0 | AL64: kWh | AO64: na | AP64: 0 | AQ64: 0 | AR64: 35 | AS64: 0 | AT64: 709 | AU64: 21 | AV64: =AU64/AT64*100 -> 2.9619182 | AW64: 0 | AX64: 0.001 | AZ64: FALSE | BA64: Low | BB64: transformer production, high voltage use; GLO | BC64: kgCO2eq/kg | BD64: 0.9560702 | BE64: SSP2-PkBudg1000_2050 | BF64: na | BG64: na | BH64: na | BI64: na | BJ64: na | BK64: "capex_power_capacity_eur_per_kw", "opex_one_time_eur", "overall_efficiency", "opex_energy_eur_per_unit", "lifetime_yr", "trl_(1-9): report_VSE_2025; "ratios_in", "ratios_out": source_share; "lca_id", "lca_unit", "embedded_carbon_kgco2e_per_lca_unit", "lca_scenario": parameters_lca | BL64: True | BM64: From the data shared by Turhan previously range of transmission line capacity (MVA): 216-100000. Range of line upgrade cost (CHF/MVA) 0.020954-1025600. Average line upgrade cost (CHF/MVA): 186072. | BO64: Not in VSE | BP64: 2700 | BQ64: - | BR64: 81 | BS64: -
A65: FALSE | B65: Partha | D65: FALSE | E65: FALSE | F65: T_C_Net_Elec_El47_ElBdg_2020 | G65: Electricity_Buildings_2020 | I65: Eletricity Transmission | J65: Electricity network connection between El47 and buildings. | K65: Grid | L65: Electricity | M65: Grid | N65: Distribution | O65: Transport | Q65: 2020 | R65: CH | S65: CHF | U65: 9 | V65: =IF(U65="", "", IF(VALUE(LEFT(U65, 1))>=9, "Mature", IF(VALUE(LEFT(U65, 1))>=7, "Emerging", "Prototype"))) -> Mature | X65: FALSE | Y65: 0.96 | AA65: El47 | AB65: na | AE65: 1 | AF65: kWh | AG65: ElBdg | AH65: ElBdg | AI65: =AG65 -> ElBdg | AJ65: 0.96 | AK65: 0.96 | AL65: kWh | AO65: na | AP65: 0 | AQ65: 0 | AR65: 40 | AS65: 0 | AT65: 1459 | AU65: 67 | AV65: =AU65/AT65*100 -> 4.5921864 | AW65: 0 | AX65: 0.001 | AZ65: FALSE | BA65: Low | BB65: distribution network construction, electricity, low voltage; CH | BC65: kgCO2eq/km | BD65: 43028.335 | BE65: SSP2-PkBudg1000_2025 | BF65: na | BG65: na | BH65: na | BI65: na | BJ65: na | BK65: "capex_power_capacity_eur_per_kw", "opex_one_time_eur", "overall_efficiency", "opex_energy_eur_per_unit", "lifetime_yr", "trl_(1-9): report_VSE_2025; "ratios_in", "ratios_out": source_share; "lca_id", "lca_unit", "embedded_carbon_kgco2e_per_lca_unit", "lca_scenario": parameters_lca | BL65: True | BM65: PSI does have any data to share for distribuition lines | BO65: Not in VSE | BP65: 2700 | BQ65: - | BR65: 81 | BS65: -
A66: FALSE | B66: Partha | D66: FALSE | E66: FALSE | F66: T_C_Net_Elec_El47_ElBdg_2030 | G66: Electricity_Buildings_2030 | I66: Eletricity Transmission | J66: Electricity network connection between El47 and buildings. | K66: Grid | L66: Electricity | M66: Grid | N66: Distribution | O66: Transport | Q66: 2030 | R66: CH | S66: CHF | U66: 9 | V66: =IF(U66="", "", IF(VALUE(LEFT(U66, 1))>=9, "Mature", IF(VALUE(LEFT(U66, 1))>=7, "Emerging", "Prototype"))) -> Mature | X66: FALSE | Y66: 0.96 | AA66: El47 | AB66: na | AE66: 1 | AF66: kWh | AG66: ElBdg | AH66: ElBdg | AI66: =AG66 -> ElBdg | AJ66: 0.96 | AK66: 0.96 | AL66: kWh | AO66: na | AP66: 0 | AQ66: 0 | AR66: 40 | AS66: 0 | AT66: =+$AT$11+($AT$14-$AT$11)/30*10 -> #VALUE! | AU66: =+$AU$11+($AU$14-$AU$11)/30*10 -> 0 | AV66: =AU66/AT66*100 -> #VALUE! | AW66: 0 | AX66: 0.001 | AZ66: FALSE | BA66: Low | BB66: distribution network construction, electricity, low voltage; CH | BC66: kgCO2eq/km | BD66: 36510.222 | BE66: SSP2-PkBudg1000_2030 | BF66: na | BG66: na | BH66: na | BI66: na | BJ66: na | BK66: "capex_power_capacity_eur_per_kw", "opex_one_time_eur", "overall_efficiency", "opex_energy_eur_per_unit", "lifetime_yr", "trl_(1-9): report_VSE_2025, linear_interpolation_2020_2050; "ratios_in", "ratios_out": source_share; "lca_id", "lca_unit", "embedded_carbon_kgco2e_per_lca_unit", "lca_scenario": parameters_lca | BL66: True | BM66: PSI does have any data to share for distribuition lines | BO66: Not in VSE | BP66: 2700 | BQ66: - | BR66: 81 | BS66: -
A67: FALSE | B67: Partha | D67: FALSE | E67: FALSE | F67: T_C_Net_Elec_El47_ElBdg_2040 | G67: Electricity_Buildings_2040 | I67: Eletricity Transmission | J67: Electricity network connection between El47 and buildings. | K67: Grid | L67: Electricity | M67: Grid | N67: Distribution | O67: Transport | Q67: 2040 | R67: CH | S67: CHF | U67: 9 | V67: =IF(U67="", "", IF(VALUE(LEFT(U67, 1))>=9, "Mature", IF(VALUE(LEFT(U67, 1))>=7, "Emerging", "Prototype"))) -> Mature | X67: FALSE | Y67: 0.96 | AA67: El47 | AB67: na | AE67: 1 | AF67: kWh | AG67: ElBdg | AH67: ElBdg | AI67: =AG67 -> ElBdg | AJ67: 0.96 | AK67: 0.96 | AL67: kWh | AO67: na | AP67: 0 | AQ67: 0 | AR67: 40 | AS67: 0 | AT67: =+$AT$11+($AT$14-$AT$11)/30*20 -> #VALUE! | AU67: =+$AU$11+($AU$14-$AU$11)/30*20 -> 0 | AV67: =AU67/AT67*100 -> #VALUE! | AW67: 0 | AX67: 0.001 | AZ67: FALSE | BA67: Low | BB67: distribution network construction, electricity, low voltage; CH | BC67: kgCO2eq/km | BD67: 25695.906 | BE67: SSP2-PkBudg1000_2040 | BF67: na | BG67: na | BH67: na | BI67: na | BJ67: na | BK67: "capex_power_capacity_eur_per_kw", "opex_one_time_eur", "overall_efficiency", "opex_energy_eur_per_unit", "lifetime_yr", "trl_(1-9): report_VSE_2025, linear_interpolation_2020_2050; "ratios_in", "ratios_out": source_share; "lca_id", "lca_unit", "embedded_carbon_kgco2e_per_lca_unit", "lca_scenario": parameters_lca | BL67: True | BM67: PSI does have any data to share for distribuition lines | BO67: Not in VSE
A68: FALSE | B68: Partha | D68: FALSE | E68: FALSE | F68: T_C_Net_Elec_El47_ElBdg_2050 | G68: Electricity_Buildings_2050 | I68: Eletricity Transmission | J68: Electricity network connection between El47 and buildings. | K68: Grid | L68: Electricity | M68: Grid | N68: Distribution | O68: Transport | Q68: 2050 | R68: CH | S68: CHF | U68: 9 | V68: =IF(U68="", "", IF(VALUE(LEFT(U68, 1))>=9, "Mature", IF(VALUE(LEFT(U68, 1))>=7, "Emerging", "Prototype"))) -> Mature | X68: FALSE | Y68: 0.96 | AA68: El47 | AB68: na | AE68: 1 | AF68: kWh | AG68: ElBdg | AH68: ElBdg | AI68: =AG68 -> ElBdg | AJ68: 0.96 | AK68: 0.96 | AL68: kWh | AO68: na | AP68: 0 | AQ68: 0 | AR68: 40 | AS68: 0 | AT68: 2920 | AU68: 135 | AV68: =AU68/AT68*100 -> 4.6232877 | AW68: 0 | AX68: 0.001 | AZ68: FALSE | BA68: Low | BB68: distribution network construction, electricity, low voltage; CH | BC68: kgCO2eq/km | BD68: 20028.763 | BE68: SSP2-PkBudg1000_2050 | BF68: na | BG68: na | BH68: na | BI68: na | BJ68: na | BK68: "capex_power_capacity_eur_per_kw", "opex_one_time_eur", "overall_efficiency", "opex_energy_eur_per_unit", "lifetime_yr", "trl_(1-9): report_VSE_2025; "ratios_in", "ratios_out": source_share; "lca_id", "lca_unit", "embedded_carbon_kgco2e_per_lca_unit", "lca_scenario": parameters_lca | BL68: True | BM68: PSI does have any data to share for distribuition lines | BO68: Not in VSE
A69: FALSE | B69: Partha | D69: FALSE | E69: FALSE | F69: T_C_Net_Elec_El47_ElRest_2020 | G69: Electricity_Node47_ToRest_2020 | I69: Eletricity Transmission | J69: Electricity network connection between El47 and other electricity nodes. | K69: Grid | L69: Electricity | M69: Grid | N69: Distribution | O69: Transport | Q69: 2020 | R69: CH | S69: CHF | U69: 9 | V69: =IF(U69="", "", IF(VALUE(LEFT(U69, 1))>=9, "Mature", IF(VALUE(LEFT(U69, 1))>=7, "Emerging", "Prototype"))) -> Mature | X69: FALSE | Y69: 0.99 | AA69: El47 | AB69: na | AE69: 1 | AF69: kWh | AG69: ElRest | AH69: ElRest | AI69: =AG69 -> ElRest | AJ69: 0.99 | AK69: 0.99 | AL69: kWh | AO69: na | AP69: 0 | AQ69: 0 | AR69: 40 | AS69: 0 | AT69: 1459 | AU69: 67 | AV69: =AU69/AT69*100 -> 4.5921864 | AW69: 0 | AX69: 0.001 | AZ69: FALSE | BA69: Low | BF69: na | BG69: na | BH69: na | BI69: na | BJ69: na | BK69: "capex_power_capacity_eur_per_kw", "opex_one_time_eur", "overall_efficiency", "opex_energy_eur_per_unit", "lifetime_yr", "trl_(1-9): report_VSE_2025; "ratios_in", "ratios_out": source_share; "lca_id", "lca_unit", "embedded_carbon_kgco2e_per_lca_unit", "lca_scenario": parameters_lca | BL69: True | BM69: PSI does have any data to share for distribuition lines | BO69: Not in VSE
A70: FALSE | B70: Partha | D70: FALSE | E70: FALSE | F70: T_C_Net_Elec_El47_ElRest_2030 | G70: Electricity_Node47_ToRest_2030 | I70: Eletricity Transmission | J70: Electricity network connection between El47 and other electricity nodes. | K70: Grid | L70: Electricity | M70: Grid | N70: Distribution | O70: Transport | Q70: 2030 | R70: CH | S70: CHF | U70: 9 | V70: =IF(U70="", "", IF(VALUE(LEFT(U70, 1))>=9, "Mature", IF(VALUE(LEFT(U70, 1))>=7, "Emerging", "Prototype"))) -> Mature | X70: FALSE | Y70: 0.99 | AA70: El47 | AB70: na | AE70: 1 | AF70: kWh | AG70: ElRest | AH70: ElRest | AI70: =AG70 -> ElRest | AJ70: 0.99 | AK70: 0.99 | AL70: kWh | AO70: na | AP70: 0 | AQ70: 0 | AR70: 40 | AS70: 0 | AT70: =+$AT$17+($AT$20-$AT$17)/30*10 -> #VALUE! | AU70: =+$AU$17+($AU$20-$AU$17)/30*10 -> 0 | AV70: =AU70/AT70*100 -> #VALUE! | AW70: 0 | AX70: 0.001 | AZ70: FALSE | BA70: Low | BF70: na | BG70: na | BH70: na | BI70: na | BJ70: na | BK70: "capex_power_capacity_eur_per_kw", "opex_one_time_eur", "overall_efficiency", "opex_energy_eur_per_unit", "lifetime_yr", "trl_(1-9): report_VSE_2025, linear_interpolation_2020_2050; "ratios_in", "ratios_out": source_share; "lca_id", "lca_unit", "embedded_carbon_kgco2e_per_lca_unit", "lca_scenario": parameters_lca | BL70: True | BM70: PSI does have any data to share for distribuition lines | BO70: Not in VSE
A71: FALSE | B71: Partha | D71: FALSE | E71: FALSE | F71: T_C_Net_Elec_El47_ElRest_2040 | G71: Electricity_Node47_ToRest_2040 | I71: Eletricity Transmission | J71: Electricity network connection between El47 and other electricity nodes. | K71: Grid | L71: Electricity | M71: Grid | N71: Distribution | O71: Transport | Q71: 2040 | R71: CH | S71: CHF | U71: 9 | V71: =IF(U71="", "", IF(VALUE(LEFT(U71, 1))>=9, "Mature", IF(VALUE(LEFT(U71, 1))>=7, "Emerging", "Prototype"))) -> Mature | X71: FALSE | Y71: 0.99 | AA71: El47 | AB71: na | AE71: 1 | AF71: kWh | AG71: ElRest | AH71: ElRest | AI71: =AG71 -> ElRest | AJ71: 0.99 | AK71: 0.99 | AL71: kWh | AO71: na | AP71: 0 | AQ71: 0 | AR71: 40 | AS71: 0 | AT71: =+$AT$17+($AT$20-$AT$17)/30*20 -> #VALUE! | AU71: =+$AU$17+($AU$20-$AU$17)/30*20 -> 0 | AV71: =AU71/AT71*100 -> #VALUE! | AW71: 0 | AX71: 0.001 | AZ71: FALSE | BA71: Low | BF71: na | BG71: na | BH71: na | BI71: na | BJ71: na | BK71: "capex_power_capacity_eur_per_kw", "opex_one_time_eur", "overall_efficiency", "opex_energy_eur_per_unit", "lifetime_yr", "trl_(1-9): report_VSE_2025, linear_interpolation_2020_2050; "ratios_in", "ratios_out": source_share; "lca_id", "lca_unit", "embedded_carbon_kgco2e_per_lca_unit", "lca_scenario": parameters_lca | BL71: True | BM71: PSI does have any data to share for distribuition lines | BO71: Not in VSE
